{
  "result": {
    "records": [
      {
        "connected": 40,
        "visitors": 391,
        "_full_text": "'-09':4,10 '-21':5,11 '01':14 '1467168112099':1,2 '18':6,12 '2016':3,9 '391':8 '49':13 '49h':7",
        "passerby": 8553,
        "site_id": "1467168112099",
        "_id": 394179,
        "key": "1467168112099 2016-09-21 18:49h",
        "timestamp": "2016-09-21T18:49:01"
      },
      {
        "connected": 0,
        "visitors": 1,
        "_full_text": "'-09':2,10 '-21':3,11 '01':6 '1467168112099':7,8 '18':4,12 '2016':1,9 '50':5 '50h':13",
        "passerby": 11,
        "site_id": "1467168112099",
        "_id": 394180,
        "key": "1467168112099 2016-09-21 18:50h",
        "timestamp": "2016-09-21T18:50:01"
      },
      {
        "connected": 1,
        "visitors": 39,
        "_full_text": "'-09':3,8 '-21':4,9 '01':12 '1':14 '1467168112099':1,13 '18':5,10 '2016':2,7 '51':11 '51h':6",
        "passerby": 251,
        "site_id": "1467168112099",
        "_id": 394182,
        "key": "1467168112099 2016-09-21 18:51h",
        "timestamp": "2016-09-21T18:51:01"
      },
      {
        "connected": 1,
        "visitors": 63,
        "_full_text": "'-09':2,11 '-21':3,12 '01':6 '1467168112099':7,9 '18':4,13 '2016':1,10 '52':5 '52h':14 '63':8",
        "passerby": 479,
        "site_id": "1467168112099",
        "_id": 394184,
        "key": "1467168112099 2016-09-21 18:52h",
        "timestamp": "2016-09-21T18:52:01"
      },
      {
        "connected": 27,
        "visitors": 239,
        "_full_text": "'-09':4,11 '-21':5,12 '01':8 '1467168112099':1,9 '19':6,13 '2016':3,10 '27':2 '36':7 '36h':14",
        "passerby": 5643,
        "site_id": "1467168112099",
        "_id": 394293,
        "key": "1467168112099 2016-09-21 19:36h",
        "timestamp": "2016-09-21T19:36:01"
      },
      {
        "connected": 4,
        "visitors": 78,
        "_full_text": "'-09':3,10 '-21':4,11 '02':14 '1467168112099':1,8 '18':5,12 '2016':2,9 '53':13 '53h':6 '78':7",
        "passerby": 648,
        "site_id": "1467168112099",
        "_id": 394188,
        "key": "1467168112099 2016-09-21 18:53h",
        "timestamp": "2016-09-21T18:53:02"
      },
      {
        "connected": 27,
        "visitors": 233,
        "_full_text": "'-09':2,11 '-21':3,12 '01':6 '1467168112099':7,9 '19':4,13 '2016':1,10 '27':8 '34':5 '34h':14",
        "passerby": null,
        "site_id": "1467168112099",
        "_id": 394288,
        "key": "1467168112099 2016-09-21 19:34h",
        "timestamp": "2016-09-21T19:34:01"
      },
      {
        "connected": 4,
        "visitors": 85,
        "_full_text": "'-09':3,11 '-21':4,12 '01':7 '1467168112099':1,9 '18':5,13 '2016':2,10 '4':8 '54':6 '54h':14",
        "passerby": null,
        "site_id": "1467168112099",
        "_id": 394189,
        "key": "1467168112099 2016-09-21 18:54h",
        "timestamp": "2016-09-21T18:54:01"
      },
      {
        "connected": 5,
        "visitors": 89,
        "_full_text": "'-09':2,10 '-21':3,11 '01':6 '1467168112099':7,8 '18':4,12 '2016':1,9 '55':5 '55h':13 '980':14",
        "passerby": 980,
        "site_id": "1467168112099",
        "_id": 394192,
        "key": "1467168112099 2016-09-21 18:55h",
        "timestamp": "2016-09-21T18:55:01"
      },
      {
        "connected": 5,
        "visitors": 97,
        "_full_text": "'-09':3,10 '-21':4,11 '02':14 '1467168112099':1,7 '18':5,12 '2016':2,9 '56':13 '56h':6 '97':8",
        "passerby": null,
        "site_id": "1467168112099",
        "_id": 394194,
        "key": "1467168112099 2016-09-21 18:56h",
        "timestamp": "2016-09-21T18:56:02"
      },
      {
        "connected": 5,
        "visitors": 98,
        "_full_text": "'-09':4,11 '-21':5,12 '01':8 '1283':1 '1467168112099':2,9 '18':6,13 '2016':3,10 '57':7 '57h':14",
        "passerby": 1283,
        "site_id": "1467168112099",
        "_id": 394197,
        "key": "1467168112099 2016-09-21 18:57h",
        "timestamp": "2016-09-21T18:57:01"
      },
      {
        "connected": 5,
        "visitors": 101,
        "_full_text": "'-09':2,10 '-21':3,11 '01':6 '1467168112099':7,8 '18':4,12 '2016':1,9 '5':14 '58':5 '58h':13",
        "passerby": 1403,
        "site_id": "1467168112099",
        "_id": 394200,
        "key": "1467168112099 2016-09-21 18:58h",
        "timestamp": "2016-09-21T18:58:01"
      },
      {
        "connected": 27,
        "visitors": 238,
        "_full_text": "'-09':3,11 '-21':4,12 '01':7 '1467168112099':1,9 '19':5,13 '2016':2,10 '35':6 '35h':14 '5561':8",
        "passerby": 5561,
        "site_id": "1467168112099",
        "_id": 394291,
        "key": "1467168112099 2016-09-21 19:35h",
        "timestamp": "2016-09-21T19:35:01"
      },
      {
        "connected": 6,
        "visitors": 105,
        "_full_text": "'-09':3,8 '-21':4,9 '01':12 '1467168112099':1,13 '18':5,10 '2016':2,7 '59':11 '59h':6 '6':14",
        "passerby": 1515,
        "site_id": "1467168112099",
        "_id": 394202,
        "key": "1467168112099 2016-09-21 18:59h",
        "timestamp": "2016-09-21T18:59:01"
      },
      {
        "connected": 7,
        "visitors": 109,
        "_full_text": "'-09':2,10 '-21':3,11 '00':5 '00h':13 '02':6 '1467168112099':7,8 '19':4,12 '2016':1,9 '7':14",
        "passerby": 1627,
        "site_id": "1467168112099",
        "_id": 394205,
        "key": "1467168112099 2016-09-21 19:00h",
        "timestamp": "2016-09-21T19:00:02"
      },
      {
        "connected": 8,
        "visitors": 114,
        "_full_text": "'-09':3,8 '-21':4,9 '01':11,12 '01h':6 '1467168112099':1,13 '19':5,10 '2016':2,7 '8':14",
        "passerby": 1748,
        "site_id": "1467168112099",
        "_id": 394206,
        "key": "1467168112099 2016-09-21 19:01h",
        "timestamp": "2016-09-21T19:01:01"
      },
      {
        "connected": 9,
        "visitors": 125,
        "_full_text": "'-09':2,10 '-21':3,11 '01':6 '02':5 '02h':13 '125':14 '1467168112099':7,8 '19':4,12 '2016':1,9",
        "passerby": 1890,
        "site_id": "1467168112099",
        "_id": 394208,
        "key": "1467168112099 2016-09-21 19:02h",
        "timestamp": "2016-09-21T19:02:01"
      },
      {
        "connected": 9,
        "visitors": 130,
        "_full_text": "'-09':3,10 '-21':4,11 '01':14 '03':13 '03h':6 '1467168112099':1,8 '19':5,12 '2006':7 '2016':2,9",
        "passerby": 2006,
        "site_id": "1467168112099",
        "_id": 394211,
        "key": "1467168112099 2016-09-21 19:03h",
        "timestamp": "2016-09-21T19:03:01"
      },
      {
        "connected": 9,
        "visitors": 132,
        "_full_text": "'-09':4,11 '-21':5,12 '01':8 '04':7 '04h':14 '1467168112099':2,9 '19':6,13 '2016':3,10 '9':1",
        "passerby": 2112,
        "site_id": "1467168112099",
        "_id": 394213,
        "key": "1467168112099 2016-09-21 19:04h",
        "timestamp": "2016-09-21T19:04:01"
      },
      {
        "connected": 9,
        "visitors": 138,
        "_full_text": "'-09':2,11 '-21':3,12 '01':6 '05':5 '05h':14 '138':8 '1467168112099':7,9 '19':4,13 '2016':1,10",
        "passerby": null,
        "site_id": "1467168112099",
        "_id": 394216,
        "key": "1467168112099 2016-09-21 19:05h",
        "timestamp": "2016-09-21T19:05:01"
      },
      {
        "connected": 10,
        "visitors": null,
        "_full_text": "'-09':3,9 '-21':4,10 '01':13 '06':12 '06h':6 '10':14 '1467168112099':1,7 '19':5,11 '2016':2,8",
        "passerby": null,
        "site_id": "1467168112099",
        "_id": 394221,
        "key": "1467168112099 2016-09-21 19:06h",
        "timestamp": "2016-09-21T19:06:01"
      },
      {
        "connected": 30,
        "visitors": 255,
        "_full_text": "'-09':2,11 '-21':3,12 '01':6 '1467168112099':7,9 '19':4,13 '2016':1,10 '30':8 '46':5 '46h':14",
        "passerby": 6492,
        "site_id": "1467168112099",
        "_id": 394314,
        "key": "1467168112099 2016-09-21 19:46h",
        "timestamp": "2016-09-21T19:46:01"
      },
      {
        "connected": 12,
        "visitors": 142,
        "_full_text": "'-09':4,11 '-21':5,12 '01':8 '07':7 '07h':14 '142':2 '1467168112099':1,9 '19':6,13 '2016':3,10",
        "passerby": 2484,
        "site_id": "1467168112099",
        "_id": 394224,
        "key": "1467168112099 2016-09-21 19:07h",
        "timestamp": "2016-09-21T19:07:01"
      },
      {
        "connected": 27,
        "visitors": 242,
        "_full_text": "'-09':3,9 '-21':4,10 '02':13 '1467168112099':1,7 '19':5,11 '2016':2,8 '37':12 '37h':6 '5732':14",
        "passerby": 5732,
        "site_id": "1467168112099",
        "_id": 394294,
        "key": "1467168112099 2016-09-21 19:37h",
        "timestamp": "2016-09-21T19:37:02"
      },
      {
        "connected": 12,
        "visitors": 146,
        "_full_text": "'-09':5,10 '-21':6,11 '01':14 '08':13 '08h':8 '1467168112099':2,3 '19':7,12 '2016':4,9 '2595':1",
        "passerby": 2595,
        "site_id": "1467168112099",
        "_id": 394226,
        "key": "1467168112099 2016-09-21 19:08h",
        "timestamp": "2016-09-21T19:08:01"
      },
      {
        "connected": 28,
        "visitors": 246,
        "_full_text": "'-09':3,8 '-21':4,9 '01':12 '1467168112099':1,13 '19':5,10 '2016':2,7 '246':14 '38':11 '38h':6",
        "passerby": null,
        "site_id": "1467168112099",
        "_id": 394297,
        "key": "1467168112099 2016-09-21 19:38h",
        "timestamp": "2016-09-21T19:38:01"
      },
      {
        "connected": 12,
        "visitors": 147,
        "_full_text": "'-09':3,10 '-21':4,11 '02':14 '09':13 '09h':6 '1467168112099':1,8 '147':7 '19':5,12 '2016':2,9",
        "passerby": 2692,
        "site_id": "1467168112099",
        "_id": 394228,
        "key": "1467168112099 2016-09-21 19:09h",
        "timestamp": "2016-09-21T19:09:02"
      },
      {
        "connected": 13,
        "visitors": 151,
        "_full_text": "'-09':5,10 '-21':6,11 '01':14 '11':13 '11h':8 '1467168112099':1,3 '19':7,12 '2016':4,9 '2944':2",
        "passerby": 2944,
        "site_id": "1467168112099",
        "_id": 394232,
        "key": "1467168112099 2016-09-21 19:11h",
        "timestamp": "2016-09-21T19:11:01"
      },
      {
        "connected": 13,
        "visitors": 151,
        "_full_text": "'-09':2,10 '-21':3,11 '01':6 '10':5 '10h':13 '1467168112099':8,14 '151':7 '19':4,12 '2016':1,9",
        "passerby": 2805,
        "site_id": "1467168112099",
        "_id": 394229,
        "key": "1467168112099 2016-09-21 19:10h",
        "timestamp": "2016-09-21T19:10:01"
      },
      {
        "connected": 28,
        "visitors": 246,
        "_full_text": "'-09':2,10 '-21':3,11 '01':6 '1467168112099':7,8 '19':4,12 '2016':1,9 '28':14 '39':5 '39h':13",
        "passerby": 5892,
        "site_id": "1467168112099",
        "_id": 394299,
        "key": "1467168112099 2016-09-21 19:39h",
        "timestamp": "2016-09-21T19:39:01"
      },
      {
        "connected": 31,
        "visitors": 259,
        "_full_text": "'-09':3,10 '-21':4,11 '01':14 '1467168112099':1,8 '19':5,12 '2016':2,9 '259':7 '47':13 '47h':6",
        "passerby": 6601,
        "site_id": "1467168112099",
        "_id": 394317,
        "key": "1467168112099 2016-09-21 19:47h",
        "timestamp": "2016-09-21T19:47:01"
      },
      {
        "connected": 14,
        "visitors": 159,
        "_full_text": "'-09':3,10 '-21':4,11 '02':14 '12':13 '12h':6 '1467168112099':1,8 '159':7 '19':5,12 '2016':2,9",
        "passerby": 3065,
        "site_id": "1467168112099",
        "_id": 394233,
        "key": "1467168112099 2016-09-21 19:12h",
        "timestamp": "2016-09-21T19:12:02"
      },
      {
        "connected": 16,
        "visitors": 165,
        "_full_text": "'-09':5,10 '-21':6,11 '01':14 '13':13 '13h':8 '1467168112099':2,3 '165':1 '19':7,12 '2016':4,9",
        "passerby": null,
        "site_id": "1467168112099",
        "_id": 394235,
        "key": "1467168112099 2016-09-21 19:13h",
        "timestamp": "2016-09-21T19:13:01"
      },
      {
        "connected": 19,
        "visitors": 181,
        "_full_text": "'-09':4,11 '-21':5,12 '02':8 '1467168112099':2,9 '16':7 '16h':14 '19':1,6,13 '2016':3,10",
        "passerby": 3546,
        "site_id": "1467168112099",
        "_id": 394243,
        "key": "1467168112099 2016-09-21 19:16h",
        "timestamp": "2016-09-21T19:16:02"
      },
      {
        "connected": 16,
        "visitors": 172,
        "_full_text": "'-09':3,10 '-21':4,11 '01':7 '14':6 '1467168112099':1,8 '14h':13 '16':14 '19':5,12 '2016':2,9",
        "passerby": 3286,
        "site_id": "1467168112099",
        "_id": 394238,
        "key": "1467168112099 2016-09-21 19:14h",
        "timestamp": "2016-09-21T19:14:01"
      },
      {
        "connected": 22,
        "visitors": 189,
        "_full_text": "'-09':3,10 '-21':4,11 '01':14 '1467168112099':1,7 '19':5,12 '20':13 '2016':2,9 '20h':6 '4021':8",
        "passerby": 4021,
        "site_id": "1467168112099",
        "_id": 394251,
        "key": "1467168112099 2016-09-21 19:20h",
        "timestamp": "2016-09-21T19:20:01"
      },
      {
        "connected": 16,
        "visitors": null,
        "_full_text": "'-09':3,10 '-21':4,11 '02':14 '1467168112099':1,7 '15':13 '15h':6 '19':5,12 '2016':2,9 '3433':8",
        "passerby": 3433,
        "site_id": "1467168112099",
        "_id": 394240,
        "key": "1467168112099 2016-09-21 19:15h",
        "timestamp": "2016-09-21T19:15:02"
      },
      {
        "connected": 28,
        "visitors": 246,
        "_full_text": "'-09':4,11 '-21':5,12 '02':8 '1467168112099':1,9 '19':6,13 '2016':3,10 '40':7 '40h':14 '5992':2",
        "passerby": 5992,
        "site_id": "1467168112099",
        "_id": 394301,
        "key": "1467168112099 2016-09-21 19:40h",
        "timestamp": "2016-09-21T19:40:02"
      },
      {
        "connected": 29,
        "visitors": 246,
        "_full_text": "'-09':4,10 '-21':5,11 '02':14 '1467168112099':1,2 '19':6,12 '2016':3,9 '29':8 '41':13 '41h':7",
        "passerby": null,
        "site_id": "1467168112099",
        "_id": 394304,
        "key": "1467168112099 2016-09-21 19:41h",
        "timestamp": "2016-09-21T19:41:02"
      },
      {
        "connected": 20,
        "visitors": 184,
        "_full_text": "'-09':3,11 '-21':4,12 '01':7 '1467168112099':1,9 '17':6 '17h':14 '19':5,13 '20':8 '2016':2,10",
        "passerby": 3657,
        "site_id": "1467168112099",
        "_id": 394246,
        "key": "1467168112099 2016-09-21 19:17h",
        "timestamp": "2016-09-21T19:17:01"
      },
      {
        "connected": 20,
        "visitors": 186,
        "_full_text": "'-09':2,9 '-21':3,10 '02':6 '1467168112099':7,14 '18':5 '186':13 '18h':12 '19':4,11 '2016':1,8",
        "passerby": 3769,
        "site_id": "1467168112099",
        "_id": 394248,
        "key": "1467168112099 2016-09-21 19:18h",
        "timestamp": "2016-09-21T19:18:02"
      },
      {
        "connected": 21,
        "visitors": 187,
        "_full_text": "'-09':4,10 '-21':5,11 '01':14 '1467168112099':1,2 '19':6,12,13 '19h':7 '2016':3,9 '21':8",
        "passerby": 3889,
        "site_id": "1467168112099",
        "_id": 394250,
        "key": "1467168112099 2016-09-21 19:19h",
        "timestamp": "2016-09-21T19:19:01"
      },
      {
        "connected": null,
        "visitors": 190,
        "_full_text": "'-09':4,11 '-21':5,12 '01':8 '1467168112099':1,9 '19':6,13 '2016':3,10 '21':7 '21h':14 '4159':2",
        "passerby": 4159,
        "site_id": "1467168112099",
        "_id": 394255,
        "key": "1467168112099 2016-09-21 19:21h",
        "timestamp": "2016-09-21T19:21:01"
      },
      {
        "connected": 29,
        "visitors": 246,
        "_full_text": "'-09':3,10 '-21':4,11 '01':14 '1467168112099':1,7 '19':5,12 '2016':2,9 '42':13 '42h':6 '6175':8",
        "passerby": 6175,
        "site_id": "1467168112099",
        "_id": 394306,
        "key": "1467168112099 2016-09-21 19:42h",
        "timestamp": "2016-09-21T19:42:01"
      },
      {
        "connected": 22,
        "visitors": 193,
        "_full_text": "'-09':2,11 '-21':3,12 '02':6 '1467168112099':7,9 '19':4,13 '193':8 '2016':1,10 '22':5 '22h':14",
        "passerby": 4270,
        "site_id": "1467168112099",
        "_id": 394257,
        "key": "1467168112099 2016-09-21 19:22h",
        "timestamp": "2016-09-21T19:22:02"
      },
      {
        "connected": 23,
        "visitors": 197,
        "_full_text": "'-09':3,10 '-21':4,11 '02':7 '1467168112099':1,8 '19':5,12 '197':14 '2016':2,9 '23':6 '23h':13",
        "passerby": 4390,
        "site_id": "1467168112099",
        "_id": 394261,
        "key": "1467168112099 2016-09-21 19:23h",
        "timestamp": "2016-09-21T19:23:02"
      },
      {
        "connected": 29,
        "visitors": 251,
        "_full_text": "'-09':3,8 '-21':4,9 '01':12 '1467168112099':1,13 '19':5,10 '2016':2,7 '29':14 '45':11 '45h':6",
        "passerby": 6406,
        "site_id": "1467168112099",
        "_id": 394312,
        "key": "1467168112099 2016-09-21 19:45h",
        "timestamp": "2016-09-21T19:45:01"
      },
      {
        "connected": 23,
        "visitors": 199,
        "_full_text": "'-09':5,10 '-21':6,11 '01':14 '1467168112099':1,3 '19':7,12 '2016':4,9 '23':2 '24':13 '24h':8",
        "passerby": 4484,
        "site_id": "1467168112099",
        "_id": 394263,
        "key": "1467168112099 2016-09-21 19:24h",
        "timestamp": "2016-09-21T19:24:01"
      },
      {
        "connected": 29,
        "visitors": 247,
        "_full_text": "'-09':2,11 '-21':3,12 '02':6 '1467168112099':7,9 '19':4,13 '2016':1,10 '247':8 '43':5 '43h':14",
        "passerby": 6260,
        "site_id": "1467168112099",
        "_id": 394308,
        "key": "1467168112099 2016-09-21 19:43h",
        "timestamp": "2016-09-21T19:43:02"
      },
      {
        "connected": 23,
        "visitors": 203,
        "_full_text": "'-09':3,10 '-21':4,11 '01':14 '1467168112099':1,8 '19':5,12 '2016':2,9 '25':13 '25h':6 '4625':7",
        "passerby": 4625,
        "site_id": "1467168112099",
        "_id": 394264,
        "key": "1467168112099 2016-09-21 19:25h",
        "timestamp": "2016-09-21T19:25:01"
      },
      {
        "connected": 24,
        "visitors": 207,
        "_full_text": "'-09':4,10 '-21':5,11 '01':14 '1467168112099':1,2 '19':6,12 '2016':3,9 '26':13 '26h':7 '4712':8",
        "passerby": 4712,
        "site_id": "1467168112099",
        "_id": 394266,
        "key": "1467168112099 2016-09-21 19:26h",
        "timestamp": "2016-09-21T19:26:01"
      },
      {
        "connected": 29,
        "visitors": 250,
        "_full_text": "'-09':2,11 '-21':3,12 '02':6 '1467168112099':8,9 '19':4,13 '2016':1,10 '44':5 '44h':14 '6335':7",
        "passerby": 6335,
        "site_id": "1467168112099",
        "_id": 394310,
        "key": "1467168112099 2016-09-21 19:44h",
        "timestamp": "2016-09-21T19:44:02"
      },
      {
        "connected": 25,
        "visitors": 209,
        "_full_text": "'-09':3,10 '-21':4,11 '01':14 '1467168112099':1,8 '19':5,12 '2016':2,9 '209':7 '27':13 '27h':6",
        "passerby": 4810,
        "site_id": "1467168112099",
        "_id": 394268,
        "key": "1467168112099 2016-09-21 19:27h",
        "timestamp": "2016-09-21T19:27:01"
      },
      {
        "connected": 26,
        "visitors": 214,
        "_full_text": "'-09':3,10 '-21':4,11 '01':14 '1467168112099':1,7 '19':5,12 '2016':2,9 '26':8 '28':13 '28h':6",
        "passerby": 4904,
        "site_id": "1467168112099",
        "_id": 394271,
        "key": "1467168112099 2016-09-21 19:28h",
        "timestamp": "2016-09-21T19:28:01"
      },
      {
        "connected": 26,
        "visitors": 216,
        "_full_text": "'-09':4,11 '-21':5,12 '01':8 '1467168112099':1,9 '19':6,13 '2016':3,10 '26':2 '29':7 '29h':14",
        "passerby": 4987,
        "site_id": "1467168112099",
        "_id": 394272,
        "key": "1467168112099 2016-09-21 19:29h",
        "timestamp": "2016-09-21T19:29:01"
      },
      {
        "connected": 26,
        "visitors": 223,
        "_full_text": "'-09':2,10 '-21':3,11 '02':6 '1467168112099':7,8 '19':4,12 '2016':1,9 '223':14 '31':5 '31h':13",
        "passerby": 5239,
        "site_id": "1467168112099",
        "_id": 394278,
        "key": "1467168112099 2016-09-21 19:31h",
        "timestamp": "2016-09-21T19:31:02"
      },
      {
        "connected": 26,
        "visitors": 220,
        "_full_text": "'-09':3,8 '-21':4,9 '01':12 '1467168112099':1,13 '19':5,10 '2016':2,7 '26':14 '30':11 '30h':6",
        "passerby": 5117,
        "site_id": "1467168112099",
        "_id": 394276,
        "key": "1467168112099 2016-09-21 19:30h",
        "timestamp": "2016-09-21T19:30:01"
      },
      {
        "connected": 2,
        "visitors": 40,
        "_full_text": "'-09':2,10 '-21':3,11 '01':6 '1467168112099':7,8 '19':4,12 '2016':1,9 '40':14 '52':5 '52h':13",
        "passerby": 319,
        "site_id": "1467168112099",
        "_id": 394326,
        "key": "1467168112099 2016-09-21 19:52h",
        "timestamp": "2016-09-21T19:52:01"
      },
      {
        "connected": null,
        "visitors": 226,
        "_full_text": "'-09':3,10 '-21':4,11 '01':14 '1467168112099':1,8 '19':5,12 '2016':2,9 '32':13 '32h':6 '5317':7",
        "passerby": 5317,
        "site_id": "1467168112099",
        "_id": 394279,
        "key": "1467168112099 2016-09-21 19:32h",
        "timestamp": "2016-09-21T19:32:01"
      },
      {
        "connected": null,
        "visitors": null,
        "_full_text": "'-09':4,11 '-21':5,12 '02':8 '1467168112099':2,9 '19':6,13 '2016':3,10 '33':7 '33h':14 '5397':1",
        "passerby": 5397,
        "site_id": "1467168112099",
        "_id": 394283,
        "key": "1467168112099 2016-09-21 19:33h",
        "timestamp": "2016-09-21T19:33:02"
      },
      {
        "connected": 31,
        "visitors": 259,
        "_full_text": "'-09':3,11 '-21':4,12 '01':7 '1467168112099':1,9 '19':5,13 '2016':2,10 '48':6 '48h':14 '6705':8",
        "passerby": 6705,
        "site_id": "1467168112099",
        "_id": 394319,
        "key": "1467168112099 2016-09-21 19:48h",
        "timestamp": "2016-09-21T19:48:01"
      },
      {
        "connected": 0,
        "visitors": 0,
        "_full_text": "'-09':3,10 '-21':4,11 '01':7 '1467168112099':1,8 '19':5,12 '2016':2,9 '50':6 '50h':13",
        "passerby": 10,
        "site_id": "1467168112099",
        "_id": 394323,
        "key": "1467168112099 2016-09-21 19:50h",
        "timestamp": "2016-09-21T19:50:01"
      },
      {
        "connected": 31,
        "visitors": 259,
        "_full_text": "'-09':4,10 '-21':5,11 '02':14 '1467168112099':1,2 '19':6,12 '2016':3,9 '31':8 '49':13 '49h':7",
        "passerby": 6770,
        "site_id": "1467168112099",
        "_id": 394321,
        "key": "1467168112099 2016-09-21 19:49h",
        "timestamp": "2016-09-21T19:49:02"
      },
      {
        "connected": 1,
        "visitors": 30,
        "_full_text": "'-09':4,10 '-21':5,11 '01':14 '1':1 '1467168112099':2,8 '19':6,12 '2016':3,9 '51':13 '51h':7",
        "passerby": 172,
        "site_id": "1467168112099",
        "_id": 394325,
        "key": "1467168112099 2016-09-21 19:51h",
        "timestamp": "2016-09-21T19:51:01"
      },
      {
        "connected": 6,
        "visitors": 48,
        "_full_text": "'-09':4,11 '-21':5,12 '01':8 '1467168112099':2,9 '19':6,13 '2016':3,10 '414':1 '53':7 '53h':14",
        "passerby": 414,
        "site_id": "1467168112099",
        "_id": 394328,
        "key": "1467168112099 2016-09-21 19:53h",
        "timestamp": "2016-09-21T19:53:01"
      },
      {
        "connected": 6,
        "visitors": 51,
        "_full_text": "'-09':2,9 '-21':3,10 '02':6 '1467168112099':7,14 '19':4,11 '2016':1,8 '512':13 '54':5 '54h':12",
        "passerby": 512,
        "site_id": "1467168112099",
        "_id": 394330,
        "key": "1467168112099 2016-09-21 19:54h",
        "timestamp": "2016-09-21T19:54:02"
      },
      {
        "connected": 6,
        "visitors": 58,
        "_full_text": "'-09':5,10 '-21':6,11 '01':14 '1467168112099':1,3 '19':7,12 '2016':4,9 '55':13 '55h':8 '6':2",
        "passerby": 606,
        "site_id": "1467168112099",
        "_id": 394334,
        "key": "1467168112099 2016-09-21 19:55h",
        "timestamp": "2016-09-21T19:55:01"
      },
      {
        "connected": 6,
        "visitors": null,
        "_full_text": "'-09':3,10 '-21':4,11 '01':14 '1467168112099':1,8 '19':5,12 '2016':2,9 '56':13 '56h':6 '692':7",
        "passerby": 692,
        "site_id": "1467168112099",
        "_id": 394336,
        "key": "1467168112099 2016-09-21 19:56h",
        "timestamp": "2016-09-21T19:56:01"
      },
      {
        "connected": 6,
        "visitors": 63,
        "_full_text": "'-09':5,10 '-21':6,11 '01':14 '1467168112099':2,3 '19':7,12 '2016':4,9 '57':13 '57h':8 '6':1",
        "passerby": 777,
        "site_id": "1467168112099",
        "_id": 394339,
        "key": "1467168112099 2016-09-21 19:57h",
        "timestamp": "2016-09-21T19:57:01"
      },
      {
        "connected": 6,
        "visitors": 65,
        "_full_text": "'-09':4,11 '-21':5,12 '01':8 '1467168112099':1,9 '19':6,13 '2016':3,10 '58':7 '58h':14 '867':2",
        "passerby": 867,
        "site_id": "1467168112099",
        "_id": 394341,
        "key": "1467168112099 2016-09-21 19:58h",
        "timestamp": "2016-09-21T19:58:01"
      },
      {
        "connected": 6,
        "visitors": 66,
        "_full_text": "'-09':3,10 '-21':4,11 '01':14 '1467168112099':1,7 '19':5,12 '2016':2,9 '59':13 '59h':6 '66':8",
        "passerby": 951,
        "site_id": "1467168112099",
        "_id": 394343,
        "key": "1467168112099 2016-09-21 19:59h",
        "timestamp": "2016-09-21T19:59:01"
      },
      {
        "connected": 20,
        "visitors": 346,
        "_full_text": "'-09':3,10 '-21':4,11 '01':14 '10':13 '10h':6 '1467168112099':1,7 '16':5,12 '2016':2,9 '346':8",
        "passerby": 3411,
        "site_id": "1467168112099",
        "_id": 393812,
        "key": "1467168112099 2016-09-21 16:10h",
        "timestamp": "2016-09-21T16:10:01"
      },
      {
        "connected": 9,
        "visitors": 257,
        "_full_text": "'-09':3,8 '-21':4,9 '00':11 '00h':6 '01':12 '1467168112099':1,13 '16':5,10 '2016':2,7 '2036':14",
        "passerby": 2036,
        "site_id": "1467168112099",
        "_id": 393789,
        "key": "1467168112099 2016-09-21 16:00h",
        "timestamp": "2016-09-21T16:00:01"
      },
      {
        "connected": 10,
        "visitors": 267,
        "_full_text": "'-09':4,10 '-21':5,11 '01':13,14 '01h':7 '1467168112099':1,2 '16':6,12 '2016':3,9 '267':8",
        "passerby": 2179,
        "site_id": "1467168112099",
        "_id": 393791,
        "key": "1467168112099 2016-09-21 16:01h",
        "timestamp": "2016-09-21T16:01:01"
      },
      {
        "connected": 11,
        "visitors": 274,
        "_full_text": "'-09':3,10 '-21':4,11 '02':13,14 '02h':6 '1467168112099':1,8 '16':5,12 '2016':2,9 '274':7",
        "passerby": 2315,
        "site_id": "1467168112099",
        "_id": 393793,
        "key": "1467168112099 2016-09-21 16:02h",
        "timestamp": "2016-09-21T16:02:02"
      },
      {
        "connected": 12,
        "visitors": 282,
        "_full_text": "'-09':3,10 '-21':4,11 '02':7 '03':6 '03h':13 '1467168112099':1,8 '16':5,12 '2016':2,9 '2452':14",
        "passerby": 2452,
        "site_id": "1467168112099",
        "_id": 393796,
        "key": "1467168112099 2016-09-21 16:03h",
        "timestamp": "2016-09-21T16:03:02"
      },
      {
        "connected": 12,
        "visitors": 290,
        "_full_text": "'-09':4,10 '-21':5,11 '02':14 '04':13 '04h':7 '1467168112099':1,2 '16':6,12 '2016':3,9 '290':8",
        "passerby": 2561,
        "site_id": "1467168112099",
        "_id": 393798,
        "key": "1467168112099 2016-09-21 16:04h",
        "timestamp": "2016-09-21T16:04:02"
      },
      {
        "connected": null,
        "visitors": 297,
        "_full_text": "'-09':3,11 '-21':4,12 '01':7 '05':6 '05h':14 '1467168112099':1,9 '16':5,13 '2016':2,10 '2709':8",
        "passerby": 2709,
        "site_id": "1467168112099",
        "_id": 393799,
        "key": "1467168112099 2016-09-21 16:05h",
        "timestamp": "2016-09-21T16:05:01"
      },
      {
        "connected": 12,
        "visitors": 307,
        "_full_text": "'-09':2,10 '-21':3,11 '02':6 '06':5 '06h':13 '1467168112099':7,8 '16':4,12 '2016':1,9 '307':14",
        "passerby": null,
        "site_id": "1467168112099",
        "_id": 393803,
        "key": "1467168112099 2016-09-21 16:06h",
        "timestamp": "2016-09-21T16:06:02"
      },
      {
        "connected": 13,
        "visitors": 313,
        "_full_text": "'-09':3,10 '-21':4,11 '02':14 '07':13 '07h':6 '13':8 '1467168112099':1,7 '16':5,12 '2016':2,9",
        "passerby": 2976,
        "site_id": "1467168112099",
        "_id": 393805,
        "key": "1467168112099 2016-09-21 16:07h",
        "timestamp": "2016-09-21T16:07:02"
      },
      {
        "connected": 15,
        "visitors": 326,
        "_full_text": "'-09':3,8 '-21':4,9 '01':12 '08':11 '08h':6 '1467168112099':1,13 '16':5,10 '2016':2,7 '326':14",
        "passerby": 3125,
        "site_id": "1467168112099",
        "_id": 393808,
        "key": "1467168112099 2016-09-21 16:08h",
        "timestamp": "2016-09-21T16:08:01"
      },
      {
        "connected": 17,
        "visitors": 334,
        "_full_text": "'-09':2,11 '-21':3,12 '02':6 '09':5 '09h':14 '1467168112099':8,9 '16':4,13 '2016':1,10 '334':7",
        "passerby": 3245,
        "site_id": "1467168112099",
        "_id": 393809,
        "key": "1467168112099 2016-09-21 16:09h",
        "timestamp": "2016-09-21T16:09:02"
      },
      {
        "connected": null,
        "visitors": 349,
        "_full_text": "'-09':4,11 '-21':5,12 '01':8 '11':7 '11h':14 '1467168112099':2,9 '16':6,13 '2016':3,10 '3568':1",
        "passerby": 3568,
        "site_id": "1467168112099",
        "_id": 393813,
        "key": "1467168112099 2016-09-21 16:11h",
        "timestamp": "2016-09-21T16:11:01"
      },
      {
        "connected": 23,
        "visitors": 353,
        "_full_text": "'-09':4,11 '-21':5,12 '01':8 '12':7 '12h':14 '1467168112099':2,9 '16':6,13 '2016':3,10 '3712':1",
        "passerby": 3712,
        "site_id": "1467168112099",
        "_id": 393815,
        "key": "1467168112099 2016-09-21 16:12h",
        "timestamp": "2016-09-21T16:12:01"
      },
      {
        "connected": 24,
        "visitors": 362,
        "_full_text": "'-09':2,11 '-21':3,12 '01':6 '13':5 '13h':14 '1467168112099':8,9 '16':4,13 '2016':1,10 '24':7",
        "passerby": 3888,
        "site_id": "1467168112099",
        "_id": 393818,
        "key": "1467168112099 2016-09-21 16:13h",
        "timestamp": "2016-09-21T16:13:01"
      },
      {
        "connected": 25,
        "visitors": 369,
        "_full_text": "'-09':5,10 '-21':6,11 '01':14 '14':13 '1467168112099':1,3 '14h':8 '16':7,12 '2016':4,9 '369':2",
        "passerby": 4021,
        "site_id": "1467168112099",
        "_id": 393820,
        "key": "1467168112099 2016-09-21 16:14h",
        "timestamp": "2016-09-21T16:14:01"
      },
      {
        "connected": 30,
        "visitors": 408,
        "_full_text": "'-09':3,10 '-21':4,11 '01':14 '1467168112099':1,8 '16':5,12 '20':13 '2016':2,9 '20h':6 '408':7",
        "passerby": 4746,
        "site_id": "1467168112099",
        "_id": 393831,
        "key": "1467168112099 2016-09-21 16:20h",
        "timestamp": "2016-09-21T16:20:01"
      },
      {
        "connected": null,
        "visitors": 439,
        "_full_text": "'-09':3,10 '-21':4,11 '01':7 '1467168112099':1,8 '16':5,12 '2016':2,9 '24':6 '24h':13 '5279':14",
        "passerby": 5279,
        "site_id": "1467168112099",
        "_id": 393842,
        "key": "1467168112099 2016-09-21 16:24h",
        "timestamp": "2016-09-21T16:24:01"
      },
      {
        "connected": 40,
        "visitors": 471,
        "_full_text": "'-09':3,9 '-21':4,10 '01':13 '1467168112099':1,7 '16':5,11 '2016':2,8 '28':12 '28h':6 '40':14",
        "passerby": 5727,
        "site_id": "1467168112099",
        "_id": 393851,
        "key": "1467168112099 2016-09-21 16:28h",
        "timestamp": "2016-09-21T16:28:01"
      },
      {
        "connected": 25,
        "visitors": 374,
        "_full_text": "'-09':2,9 '-21':3,10 '01':6 '1467168112099':7,13 '15':5 '15h':12 '16':4,11 '2016':1,8 '374':14",
        "passerby": 4110,
        "site_id": "1467168112099",
        "_id": 393822,
        "key": "1467168112099 2016-09-21 16:15h",
        "timestamp": "2016-09-21T16:15:01"
      },
      {
        "connected": 27,
        "visitors": 382,
        "_full_text": "'-09':4,10 '-21':5,11 '01':14 '1467168112099':1,2 '16':6,12,13 '16h':7 '2016':3,9 '382':8",
        "passerby": 4228,
        "site_id": "1467168112099",
        "_id": 393824,
        "key": "1467168112099 2016-09-21 16:16h",
        "timestamp": "2016-09-21T16:16:01"
      },
      {
        "connected": 29,
        "visitors": 389,
        "_full_text": "'-09':3,10 '-21':4,11 '01':14 '1467168112099':1,8 '16':5,12 '17':13 '17h':6 '2016':2,9 '4372':7",
        "passerby": 4372,
        "site_id": "1467168112099",
        "_id": 393825,
        "key": "1467168112099 2016-09-21 16:17h",
        "timestamp": "2016-09-21T16:17:01"
      },
      {
        "connected": 30,
        "visitors": 395,
        "_full_text": "'-09':3,9 '-21':4,10 '02':13 '1467168112099':1,7 '16':5,11 '18':12 '18h':6 '2016':2,8 '4504':14",
        "passerby": 4504,
        "site_id": "1467168112099",
        "_id": 393827,
        "key": "1467168112099 2016-09-21 16:18h",
        "timestamp": "2016-09-21T16:18:02"
      },
      {
        "connected": 30,
        "visitors": 403,
        "_full_text": "'-09':4,11 '-21':5,12 '01':8 '1467168112099':2,9 '16':6,13 '19':7 '19h':14 '2016':3,10 '4621':1",
        "passerby": 4621,
        "site_id": "1467168112099",
        "_id": 393830,
        "key": "1467168112099 2016-09-21 16:19h",
        "timestamp": "2016-09-21T16:19:01"
      },
      {
        "connected": 31,
        "visitors": 415,
        "_full_text": "'-09':5,10 '-21':6,11 '01':14 '1467168112099':2,3 '16':7,12 '2016':4,9 '21':13 '21h':8 '4877':1",
        "passerby": 4877,
        "site_id": "1467168112099",
        "_id": 393834,
        "key": "1467168112099 2016-09-21 16:21h",
        "timestamp": "2016-09-21T16:21:01"
      },
      {
        "connected": 31,
        "visitors": 421,
        "_full_text": "'-09':3,9 '-21':4,10 '01':13 '1467168112099':1,7 '16':5,11 '2016':2,8 '22':12 '22h':6 '31':14",
        "passerby": 5018,
        "site_id": "1467168112099",
        "_id": 393837,
        "key": "1467168112099 2016-09-21 16:22h",
        "timestamp": "2016-09-21T16:22:01"
      },
      {
        "connected": null,
        "visitors": 432,
        "_full_text": "'-09':4,10 '-21':5,11 '01':14 '1467168112099':1,2 '16':6,12 '2016':3,9 '23':13 '23h':7 '432':8",
        "passerby": null,
        "site_id": "1467168112099",
        "_id": 393840,
        "key": "1467168112099 2016-09-21 16:23h",
        "timestamp": "2016-09-21T16:23:01"
      },
      {
        "connected": 37,
        "visitors": 445,
        "_full_text": "'-09':3,10 '-21':4,11 '01':14 '1467168112099':1,7 '16':5,12 '2016':2,9 '25':13 '25h':6 '445':8",
        "passerby": 5405,
        "site_id": "1467168112099",
        "_id": 393845,
        "key": "1467168112099 2016-09-21 16:25h",
        "timestamp": "2016-09-21T16:25:01"
      },
      {
        "connected": 37,
        "visitors": 455,
        "_full_text": "'-09':2,10 '-21':3,11 '01':6 '1467168112099':7,8 '16':4,12 '2016':1,9 '26':5 '26h':13 '455':14",
        "passerby": 5520,
        "site_id": "1467168112099",
        "_id": 393848,
        "key": "1467168112099 2016-09-21 16:26h",
        "timestamp": "2016-09-21T16:26:01"
      },
      {
        "connected": 39,
        "visitors": 460,
        "_full_text": "'-09':2,11 '-21':3,12 '02':6 '1467168112099':7,9 '16':4,13 '2016':1,10 '27':5 '27h':14 '460':8",
        "passerby": 5624,
        "site_id": "1467168112099",
        "_id": 393850,
        "key": "1467168112099 2016-09-21 16:27h",
        "timestamp": "2016-09-21T16:27:02"
      },
      {
        "connected": 40,
        "visitors": 478,
        "_full_text": "'-09':5,10 '-21':6,11 '02':14 '1467168112099':2,3 '16':7,12 '2016':4,9 '29':13 '29h':8 '478':1",
        "passerby": 5863,
        "site_id": "1467168112099",
        "_id": 393854,
        "key": "1467168112099 2016-09-21 16:29h",
        "timestamp": "2016-09-21T16:29:02"
      },
      {
        "connected": 41,
        "visitors": 484,
        "_full_text": "'-09':5,10 '-21':6,11 '01':14 '1467168112099':2,3 '16':7,12 '2016':4,9 '30':13 '30h':8 '5977':1",
        "passerby": 5977,
        "site_id": "1467168112099",
        "_id": 393858,
        "key": "1467168112099 2016-09-21 16:30h",
        "timestamp": "2016-09-21T16:30:01"
      },
      {
        "connected": 43,
        "visitors": 498,
        "_full_text": "'-09':3,8 '-21':4,9 '01':12 '1467168112099':1,13 '16':5,10 '2016':2,7 '31':11 '31h':6 '43':14",
        "passerby": 6087,
        "site_id": "1467168112099",
        "_id": 393861,
        "key": "1467168112099 2016-09-21 16:31h",
        "timestamp": "2016-09-21T16:31:01"
      },
      {
        "connected": 44,
        "visitors": 508,
        "_full_text": "'-09':2,11 '-21':3,12 '01':6 '1467168112099':7,9 '16':4,13 '2016':1,10 '32':5 '32h':14 '6196':8",
        "passerby": 6196,
        "site_id": "1467168112099",
        "_id": 393863,
        "key": "1467168112099 2016-09-21 16:32h",
        "timestamp": "2016-09-21T16:32:01"
      },
      {
        "connected": 44,
        "visitors": 515,
        "_full_text": "'-09':3,10 '-21':4,11 '01':14 '1467168112099':1,8 '16':5,12 '2016':2,9 '33':13 '33h':6 '515':7",
        "passerby": null,
        "site_id": "1467168112099",
        "_id": 393865,
        "key": "1467168112099 2016-09-21 16:33h",
        "timestamp": "2016-09-21T16:33:01"
      },
      {
        "connected": 44,
        "visitors": 522,
        "_full_text": "'-09':3,11 '-21':4,12 '02':7 '1467168112099':1,9 '16':5,13 '2016':2,10 '34':6 '34h':14 '44':8",
        "passerby": 6415,
        "site_id": "1467168112099",
        "_id": 393867,
        "key": "1467168112099 2016-09-21 16:34h",
        "timestamp": "2016-09-21T16:34:02"
      },
      {
        "connected": 45,
        "visitors": null,
        "_full_text": "'-09':2,11 '-21':3,12 '01':6 '1467168112099':7,9 '16':4,13 '2016':1,10 '35':5 '35h':14 '45':8",
        "passerby": null,
        "site_id": "1467168112099",
        "_id": 393870,
        "key": "1467168112099 2016-09-21 16:35h",
        "timestamp": "2016-09-21T16:35:01"
      },
      {
        "connected": 47,
        "visitors": 535,
        "_full_text": "'-09':4,10 '-21':5,11 '01':14 '1467168112099':2,8 '16':6,12 '2016':3,9 '36':13 '36h':7 '6675':1",
        "passerby": 6675,
        "site_id": "1467168112099",
        "_id": 393873,
        "key": "1467168112099 2016-09-21 16:36h",
        "timestamp": "2016-09-21T16:36:01"
      },
      {
        "connected": 48,
        "visitors": null,
        "_full_text": "'-09':3,10 '-21':4,11 '01':7 '1467168112099':1,8 '16':5,12 '2016':2,9 '37':6 '37h':13 '6803':14",
        "passerby": 6803,
        "site_id": "1467168112099",
        "_id": 393876,
        "key": "1467168112099 2016-09-21 16:37h",
        "timestamp": "2016-09-21T16:37:01"
      },
      {
        "connected": 49,
        "visitors": 554,
        "_full_text": "'-09':3,9 '-21':4,10 '02':13 '1467168112099':1,7 '16':5,11 '2016':2,8 '39':12 '39h':6 '7002':14",
        "passerby": 7002,
        "site_id": "1467168112099",
        "_id": 393881,
        "key": "1467168112099 2016-09-21 16:39h",
        "timestamp": "2016-09-21T16:39:02"
      },
      {
        "connected": 49,
        "visitors": 556,
        "_full_text": "'-09':5,10 '-21':6,11 '02':14 '1467168112099':1,3 '16':7,12 '2016':4,9 '40':13 '40h':8 '49':2",
        "passerby": null,
        "site_id": "1467168112099",
        "_id": 393882,
        "key": "1467168112099 2016-09-21 16:40h",
        "timestamp": "2016-09-21T16:40:02"
      },
      {
        "connected": 48,
        "visitors": 547,
        "_full_text": "'-09':2,10 '-21':3,11 '01':6 '1467168112099':7,8 '16':4,12 '2016':1,9 '38':5 '38h':13 '547':14",
        "passerby": 6923,
        "site_id": "1467168112099",
        "_id": 393879,
        "key": "1467168112099 2016-09-21 16:38h",
        "timestamp": "2016-09-21T16:38:01"
      },
      {
        "connected": 49,
        "visitors": null,
        "_full_text": "'-09':3,11 '-21':4,12 '02':7 '1467168112099':1,9 '16':5,13 '2016':2,10 '41':6 '41h':14 '7227':8",
        "passerby": 7227,
        "site_id": "1467168112099",
        "_id": 393887,
        "key": "1467168112099 2016-09-21 16:41h",
        "timestamp": "2016-09-21T16:41:02"
      },
      {
        "connected": 49,
        "visitors": 565,
        "_full_text": "'-09':3,10 '-21':4,11 '01':7 '1467168112099':1,8 '16':5,12 '2016':2,9 '42':6 '42h':13 '49':14",
        "passerby": 7320,
        "site_id": "1467168112099",
        "_id": 393890,
        "key": "1467168112099 2016-09-21 16:42h",
        "timestamp": "2016-09-21T16:42:01"
      },
      {
        "connected": 50,
        "visitors": 573,
        "_full_text": "'-09':3,10 '-21':4,11 '01':14 '1467168112099':1,7 '16':5,12 '2016':2,9 '43':13 '43h':6 '7438':8",
        "passerby": 7438,
        "site_id": "1467168112099",
        "_id": 393892,
        "key": "1467168112099 2016-09-21 16:43h",
        "timestamp": "2016-09-21T16:43:01"
      },
      {
        "connected": 50,
        "visitors": 577,
        "_full_text": "'-09':3,8 '-21':4,9 '01':12 '1467168112099':1,13 '16':5,10 '2016':2,7 '44':11 '44h':6 '50':14",
        "passerby": 7551,
        "site_id": "1467168112099",
        "_id": 393894,
        "key": "1467168112099 2016-09-21 16:44h",
        "timestamp": "2016-09-21T16:44:01"
      },
      {
        "connected": 50,
        "visitors": 581,
        "_full_text": "'-09':5,10 '-21':6,11 '01':14 '1467168112099':2,3 '16':7,12 '2016':4,9 '45':13 '45h':8 '7658':1",
        "passerby": 7658,
        "site_id": "1467168112099",
        "_id": 393896,
        "key": "1467168112099 2016-09-21 16:45h",
        "timestamp": "2016-09-21T16:45:01"
      },
      {
        "connected": 51,
        "visitors": 591,
        "_full_text": "'-09':4,10 '-21':5,11 '01':14 '1467168112099':2,8 '16':6,12 '2016':3,9 '46':13 '46h':7 '7754':1",
        "passerby": 7754,
        "site_id": "1467168112099",
        "_id": 393897,
        "key": "1467168112099 2016-09-21 16:46h",
        "timestamp": "2016-09-21T16:46:01"
      },
      {
        "connected": 52,
        "visitors": 598,
        "_full_text": "'-09':2,10 '-21':3,11 '01':6 '1467168112099':7,8 '16':4,12 '2016':1,9 '47':5 '47h':13 '52':14",
        "passerby": 7885,
        "site_id": "1467168112099",
        "_id": 393900,
        "key": "1467168112099 2016-09-21 16:47h",
        "timestamp": "2016-09-21T16:47:01"
      },
      {
        "connected": 52,
        "visitors": 603,
        "_full_text": "'-09':5,10 '-21':6,11 '02':14 '1467168112099':1,3 '16':7,12 '2016':4,9 '48':13 '48h':8 '52':2",
        "passerby": 7967,
        "site_id": "1467168112099",
        "_id": 393901,
        "key": "1467168112099 2016-09-21 16:48h",
        "timestamp": "2016-09-21T16:48:02"
      },
      {
        "connected": 52,
        "visitors": 608,
        "_full_text": "'-09':3,11 '-21':4,12 '01':7 '1467168112099':1,9 '16':5,13 '2016':2,10 '49':6 '49h':14 '8076':8",
        "passerby": 8076,
        "site_id": "1467168112099",
        "_id": 393904,
        "key": "1467168112099 2016-09-21 16:49h",
        "timestamp": "2016-09-21T16:49:01"
      },
      {
        "connected": 0,
        "visitors": 7,
        "_full_text": "'-09':5,10 '-21':6,11 '01':14 '13':2 '1467168112099':1,3 '16':7,12 '2016':4,9 '50':13 '50h':8",
        "passerby": 13,
        "site_id": "1467168112099",
        "_id": 393905,
        "key": "1467168112099 2016-09-21 16:50h",
        "timestamp": "2016-09-21T16:50:01"
      },
      {
        "connected": 3,
        "visitors": 80,
        "_full_text": "'-09':2,9 '-21':3,10 '01':6 '1467168112099':7,14 '16':4,11 '2016':1,8 '340':13 '51':5 '51h':12",
        "passerby": 340,
        "site_id": "1467168112099",
        "_id": 393907,
        "key": "1467168112099 2016-09-21 16:51h",
        "timestamp": "2016-09-21T16:51:01"
      },
      {
        "connected": 6,
        "visitors": 128,
        "_full_text": "'-09':5,10 '-21':6,11 '01':14 '128':1 '1467168112099':2,3 '16':7,12 '2016':4,9 '52':13 '52h':8",
        "passerby": 606,
        "site_id": "1467168112099",
        "_id": 393911,
        "key": "1467168112099 2016-09-21 16:52h",
        "timestamp": "2016-09-21T16:52:01"
      },
      {
        "connected": 6,
        "visitors": 157,
        "_full_text": "'-09':3,10 '-21':4,11 '01':14 '1467168112099':1,8 '16':5,12 '2016':2,9 '53':13 '53h':6 '836':7",
        "passerby": 836,
        "site_id": "1467168112099",
        "_id": 393912,
        "key": "1467168112099 2016-09-21 16:53h",
        "timestamp": "2016-09-21T16:53:01"
      },
      {
        "connected": 7,
        "visitors": 178,
        "_full_text": "'-09':3,9 '-21':4,10 '02':13 '1467168112099':1,7 '16':5,11 '2016':2,8 '54':12 '54h':6 '7':14",
        "passerby": 1039,
        "site_id": "1467168112099",
        "_id": 393915,
        "key": "1467168112099 2016-09-21 16:54h",
        "timestamp": "2016-09-21T16:54:02"
      },
      {
        "connected": 8,
        "visitors": 196,
        "_full_text": "'-09':4,11 '-21':5,12 '01':8 '1467168112099':2,9 '16':6,13 '2016':3,10 '55':7 '55h':14 '8':1",
        "passerby": null,
        "site_id": "1467168112099",
        "_id": 393916,
        "key": "1467168112099 2016-09-21 16:55h",
        "timestamp": "2016-09-21T16:55:01"
      },
      {
        "connected": 21,
        "visitors": 289,
        "_full_text": "'-09':4,11 '-21':5,12 '01':8 '05':7 '05h':14 '1467168112099':2,9 '17':6,13 '2016':3,10 '289':1",
        "passerby": 2771,
        "site_id": "1467168112099",
        "_id": 393941,
        "key": "1467168112099 2016-09-21 17:05h",
        "timestamp": "2016-09-21T17:05:01"
      },
      {
        "connected": null,
        "visitors": 210,
        "_full_text": "'-09':3,11 '-21':4,12 '01':7 '1467168112099':1,9 '16':5,13 '2016':2,10 '210':8 '56':6 '56h':14",
        "passerby": 1376,
        "site_id": "1467168112099",
        "_id": 393919,
        "key": "1467168112099 2016-09-21 16:56h",
        "timestamp": "2016-09-21T16:56:01"
      },
      {
        "connected": 15,
        "visitors": 229,
        "_full_text": "'-09':4,11 '-21':5,12 '02':8 '1467168112099':2,9 '15':1 '16':6,13 '2016':3,10 '57':7 '57h':14",
        "passerby": 1576,
        "site_id": "1467168112099",
        "_id": 393921,
        "key": "1467168112099 2016-09-21 16:57h",
        "timestamp": "2016-09-21T16:57:02"
      },
      {
        "connected": null,
        "visitors": 237,
        "_full_text": "'-09':5,10 '-21':6,11 '01':14 '1467168112099':1,3 '16':7,12 '2016':4,9 '237':2 '58':13 '58h':8",
        "passerby": 1745,
        "site_id": "1467168112099",
        "_id": 393923,
        "key": "1467168112099 2016-09-21 16:58h",
        "timestamp": "2016-09-21T16:58:01"
      },
      {
        "connected": 19,
        "visitors": 264,
        "_full_text": "'-09':5,10 '-21':6,11 '01':14 '02':13 '02h':8 '1467168112099':2,3 '17':7,12 '19':1 '2016':4,9",
        "passerby": null,
        "site_id": "1467168112099",
        "_id": 393932,
        "key": "1467168112099 2016-09-21 17:02h",
        "timestamp": "2016-09-21T17:02:01"
      },
      {
        "connected": 18,
        "visitors": 242,
        "_full_text": "'-09':2,9 '-21':3,10 '01':6 '1467168112099':7,13 '16':4,11 '2016':1,8 '242':14 '59':5 '59h':12",
        "passerby": 1939,
        "site_id": "1467168112099",
        "_id": 393926,
        "key": "1467168112099 2016-09-21 16:59h",
        "timestamp": "2016-09-21T16:59:01"
      },
      {
        "connected": 18,
        "visitors": 253,
        "_full_text": "'-09':5,10 '-21':6,11 '00':13 '00h':8 '02':14 '1467168112099':2,3 '17':7,12 '18':1 '2016':4,9",
        "passerby": 2076,
        "site_id": "1467168112099",
        "_id": 393928,
        "key": "1467168112099 2016-09-21 17:00h",
        "timestamp": "2016-09-21T17:00:02"
      },
      {
        "connected": 19,
        "visitors": 259,
        "_full_text": "'-09':4,10 '-21':5,11 '01':13,14 '01h':7 '1467168112099':2,8 '17':6,12 '19':1 '2016':3,9",
        "passerby": 2209,
        "site_id": "1467168112099",
        "_id": 393931,
        "key": "1467168112099 2016-09-21 17:01h",
        "timestamp": "2016-09-21T17:01:01"
      },
      {
        "connected": 20,
        "visitors": 272,
        "_full_text": "'-09':3,10 '-21':4,11 '01':14 '04':13 '04h':6 '1467168112099':1,7 '17':5,12 '20':8 '2016':2,9",
        "passerby": 2624,
        "site_id": "1467168112099",
        "_id": 393940,
        "key": "1467168112099 2016-09-21 17:04h",
        "timestamp": "2016-09-21T17:04:01"
      },
      {
        "connected": 20,
        "visitors": null,
        "_full_text": "'-09':3,10 '-21':4,11 '01':14 '03':13 '03h':6 '1467168112099':1,8 '17':5,12 '2016':2,9 '2498':7",
        "passerby": 2498,
        "site_id": "1467168112099",
        "_id": 393936,
        "key": "1467168112099 2016-09-21 17:03h",
        "timestamp": "2016-09-21T17:03:01"
      },
      {
        "connected": 24,
        "visitors": 297,
        "_full_text": "'-09':3,11 '-21':4,12 '01':7 '06':6 '06h':14 '1467168112099':1,9 '17':5,13 '2016':2,10 '2940':8",
        "passerby": 2940,
        "site_id": "1467168112099",
        "_id": 393945,
        "key": "1467168112099 2016-09-21 17:06h",
        "timestamp": "2016-09-21T17:06:01"
      },
      {
        "connected": null,
        "visitors": 310,
        "_full_text": "'-09':2,11 '-21':3,12 '01':6 '07':5 '07h':14 '1467168112099':8,9 '17':4,13 '2016':1,10 '3081':7",
        "passerby": 3081,
        "site_id": "1467168112099",
        "_id": 393946,
        "key": "1467168112099 2016-09-21 17:07h",
        "timestamp": "2016-09-21T17:07:01"
      },
      {
        "connected": 26,
        "visitors": 318,
        "_full_text": "'-09':5,10 '-21':6,11 '01':14 '08':13 '08h':8 '1467168112099':1,3 '17':7,12 '2016':4,9 '318':2",
        "passerby": 3224,
        "site_id": "1467168112099",
        "_id": 393950,
        "key": "1467168112099 2016-09-21 17:08h",
        "timestamp": "2016-09-21T17:08:01"
      },
      {
        "connected": 28,
        "visitors": 330,
        "_full_text": "'-09':3,8 '-21':4,9 '01':12 '09':11 '09h':6 '1467168112099':1,13 '17':5,10 '2016':2,7 '330':14",
        "passerby": 3361,
        "site_id": "1467168112099",
        "_id": 393951,
        "key": "1467168112099 2016-09-21 17:09h",
        "timestamp": "2016-09-21T17:09:01"
      },
      {
        "connected": 28,
        "visitors": 339,
        "_full_text": "'-09':2,10 '-21':3,11 '01':6 '10':5 '10h':13 '1467168112099':7,8 '17':4,12 '2016':1,9 '339':14",
        "passerby": 3479,
        "site_id": "1467168112099",
        "_id": 393954,
        "key": "1467168112099 2016-09-21 17:10h",
        "timestamp": "2016-09-21T17:10:01"
      },
      {
        "connected": 29,
        "visitors": 345,
        "_full_text": "'-09':4,11 '-21':5,12 '02':8 '11':7 '11h':14 '1467168112099':1,9 '17':6,13 '2016':3,10 '3626':2",
        "passerby": 3626,
        "site_id": "1467168112099",
        "_id": 393955,
        "key": "1467168112099 2016-09-21 17:11h",
        "timestamp": "2016-09-21T17:11:02"
      },
      {
        "connected": 29,
        "visitors": 350,
        "_full_text": "'-09':2,10 '-21':3,11 '02':6 '12':5 '12h':13 '1467168112099':7,8 '17':4,12 '2016':1,9 '350':14",
        "passerby": 3765,
        "site_id": "1467168112099",
        "_id": 393957,
        "key": "1467168112099 2016-09-21 17:12h",
        "timestamp": "2016-09-21T17:12:02"
      },
      {
        "connected": 29,
        "visitors": 357,
        "_full_text": "'-09':3,10 '-21':4,11 '02':14 '13':13 '13h':6 '1467168112099':1,7 '17':5,12 '2016':2,9 '3891':8",
        "passerby": 3891,
        "site_id": "1467168112099",
        "_id": 393960,
        "key": "1467168112099 2016-09-21 17:13h",
        "timestamp": "2016-09-21T17:13:02"
      },
      {
        "connected": 30,
        "visitors": 365,
        "_full_text": "'-09':3,8 '-21':4,9 '01':12 '14':11 '1467168112099':1,13 '14h':6 '17':5,10 '2016':2,7 '4008':14",
        "passerby": 4008,
        "site_id": "1467168112099",
        "_id": 393961,
        "key": "1467168112099 2016-09-21 17:14h",
        "timestamp": "2016-09-21T17:14:01"
      },
      {
        "connected": 30,
        "visitors": 369,
        "_full_text": "'-09':4,9 '-21':5,10 '01':13 '1467168112099':1,2 '15':12 '15h':7 '17':6,11 '2016':3,8 '30':14",
        "passerby": 4125,
        "site_id": "1467168112099",
        "_id": 393963,
        "key": "1467168112099 2016-09-21 17:15h",
        "timestamp": "2016-09-21T17:15:01"
      },
      {
        "connected": 30,
        "visitors": null,
        "_full_text": "'-09':4,10 '-21':5,11 '02':14 '1467168112099':2,8 '16':13 '16h':7 '17':6,12 '2016':3,9 '4214':1",
        "passerby": 4214,
        "site_id": "1467168112099",
        "_id": 393966,
        "key": "1467168112099 2016-09-21 17:16h",
        "timestamp": "2016-09-21T17:16:02"
      },
      {
        "connected": 32,
        "visitors": 380,
        "_full_text": "'-09':5,10 '-21':6,11 '02':14 '1467168112099':2,3 '17':7,12,13 '17h':8 '2016':4,9 '32':1",
        "passerby": null,
        "site_id": "1467168112099",
        "_id": 393968,
        "key": "1467168112099 2016-09-21 17:17h",
        "timestamp": "2016-09-21T17:17:02"
      },
      {
        "connected": 33,
        "visitors": 387,
        "_full_text": "'-09':5,10 '-21':6,11 '02':14 '1467168112099':2,3 '17':7,12 '18':13 '18h':8 '2016':4,9 '33':1",
        "passerby": 4437,
        "site_id": "1467168112099",
        "_id": 393971,
        "key": "1467168112099 2016-09-21 17:18h",
        "timestamp": "2016-09-21T17:18:02"
      },
      {
        "connected": 34,
        "visitors": 395,
        "_full_text": "'-09':3,11 '-21':4,12 '01':7 '1467168112099':1,9 '17':5,13 '19':6 '19h':14 '2016':2,10 '395':8",
        "passerby": 4565,
        "site_id": "1467168112099",
        "_id": 393973,
        "key": "1467168112099 2016-09-21 17:19h",
        "timestamp": "2016-09-21T17:19:01"
      },
      {
        "connected": 34,
        "visitors": 404,
        "_full_text": "'-09':4,11 '-21':5,12 '02':8 '1467168112099':1,9 '17':6,13 '20':7 '2016':3,10 '20h':14 '34':2",
        "passerby": 4699,
        "site_id": "1467168112099",
        "_id": 393977,
        "key": "1467168112099 2016-09-21 17:20h",
        "timestamp": "2016-09-21T17:20:02"
      },
      {
        "connected": 37,
        "visitors": 421,
        "_full_text": "'-09':4,10 '-21':5,11 '01':14 '1467168112099':2,8 '17':6,12 '2016':3,9 '22':13 '22h':7 '421':1",
        "passerby": 5015,
        "site_id": "1467168112099",
        "_id": 393981,
        "key": "1467168112099 2016-09-21 17:22h",
        "timestamp": "2016-09-21T17:22:01"
      },
      {
        "connected": 35,
        "visitors": 415,
        "_full_text": "'-09':2,10 '-21':3,11 '01':6 '1467168112099':7,8 '17':4,12 '2016':1,9 '21':5 '21h':13 '35':14",
        "passerby": 4833,
        "site_id": "1467168112099",
        "_id": 393978,
        "key": "1467168112099 2016-09-21 17:21h",
        "timestamp": "2016-09-21T17:21:01"
      },
      {
        "connected": 38,
        "visitors": 424,
        "_full_text": "'-09':2,11 '-21':3,12 '02':6 '1467168112099':7,9 '17':4,13 '2016':1,10 '23':5 '23h':14 '38':8",
        "passerby": 5201,
        "site_id": "1467168112099",
        "_id": 393984,
        "key": "1467168112099 2016-09-21 17:23h",
        "timestamp": "2016-09-21T17:23:02"
      },
      {
        "connected": 38,
        "visitors": 428,
        "_full_text": "'-09':2,10 '-21':3,11 '01':6 '1467168112099':7,8 '17':4,12 '2016':1,9 '24':5 '24h':13 '5341':14",
        "passerby": 5341,
        "site_id": "1467168112099",
        "_id": 393985,
        "key": "1467168112099 2016-09-21 17:24h",
        "timestamp": "2016-09-21T17:24:01"
      },
      {
        "connected": 39,
        "visitors": 441,
        "_full_text": "'-09':3,9 '-21':4,10 '02':13 '1467168112099':1,7 '17':5,11 '2016':2,8 '25':12 '25h':6 '441':14",
        "passerby": 5513,
        "site_id": "1467168112099",
        "_id": 393988,
        "key": "1467168112099 2016-09-21 17:25h",
        "timestamp": "2016-09-21T17:25:02"
      },
      {
        "connected": 40,
        "visitors": 445,
        "_full_text": "'-09':3,10 '-21':4,11 '02':7 '1467168112099':1,8 '17':5,12 '2016':2,9 '26':6 '26h':13 '5637':14",
        "passerby": 5637,
        "site_id": "1467168112099",
        "_id": 393990,
        "key": "1467168112099 2016-09-21 17:26h",
        "timestamp": "2016-09-21T17:26:02"
      },
      {
        "connected": 41,
        "visitors": 448,
        "_full_text": "'-09':3,10 '-21':4,11 '02':14 '1467168112099':1,8 '17':5,12 '2016':2,9 '27':13 '27h':6 '41':7",
        "passerby": 5761,
        "site_id": "1467168112099",
        "_id": 393991,
        "key": "1467168112099 2016-09-21 17:27h",
        "timestamp": "2016-09-21T17:27:02"
      },
      {
        "connected": 42,
        "visitors": 453,
        "_full_text": "'-09':3,11 '-21':4,12 '01':7 '1467168112099':1,9 '17':5,13 '2016':2,10 '28':6 '28h':14 '42':8",
        "passerby": 5888,
        "site_id": "1467168112099",
        "_id": 393993,
        "key": "1467168112099 2016-09-21 17:28h",
        "timestamp": "2016-09-21T17:28:01"
      },
      {
        "connected": 43,
        "visitors": 456,
        "_full_text": "'-09':2,10 '-21':3,11 '01':6 '1467168112099':7,8 '17':4,12 '2016':1,9 '29':5 '29h':13 '456':14",
        "passerby": 6033,
        "site_id": "1467168112099",
        "_id": 393996,
        "key": "1467168112099 2016-09-21 17:29h",
        "timestamp": "2016-09-21T17:29:01"
      },
      {
        "connected": 44,
        "visitors": 462,
        "_full_text": "'-09':3,10 '-21':4,11 '01':14 '1467168112099':1,7 '17':5,12 '2016':2,9 '31':13 '31h':6 '44':8",
        "passerby": 6252,
        "site_id": "1467168112099",
        "_id": 393999,
        "key": "1467168112099 2016-09-21 17:31h",
        "timestamp": "2016-09-21T17:31:01"
      },
      {
        "connected": null,
        "visitors": 468,
        "_full_text": "'-09':3,10 '-21':4,11 '02':7 '1467168112099':1,8 '17':5,12 '2016':2,9 '32':6 '32h':13 '468':14",
        "passerby": 6365,
        "site_id": "1467168112099",
        "_id": 394001,
        "key": "1467168112099 2016-09-21 17:32h",
        "timestamp": "2016-09-21T17:32:02"
      },
      {
        "connected": 44,
        "visitors": 461,
        "_full_text": "'-09':3,10 '-21':4,11 '01':7 '1467168112099':1,8 '17':5,12 '2016':2,9 '30':6 '30h':13 '44':14",
        "passerby": 6130,
        "site_id": "1467168112099",
        "_id": 393998,
        "key": "1467168112099 2016-09-21 17:30h",
        "timestamp": "2016-09-21T17:30:01"
      },
      {
        "connected": 44,
        "visitors": 472,
        "_full_text": "'-09':3,11 '-21':4,12 '01':7 '1467168112099':1,9 '17':5,13 '2016':2,10 '33':6 '33h':14 '44':8",
        "passerby": 6530,
        "site_id": "1467168112099",
        "_id": 394004,
        "key": "1467168112099 2016-09-21 17:33h",
        "timestamp": "2016-09-21T17:33:01"
      },
      {
        "connected": 44,
        "visitors": 477,
        "_full_text": "'-09':2,9 '-21':3,10 '01':6 '1467168112099':7,13 '17':4,11 '2016':1,8 '34':5 '34h':12 '477':14",
        "passerby": 6636,
        "site_id": "1467168112099",
        "_id": 394006,
        "key": "1467168112099 2016-09-21 17:34h",
        "timestamp": "2016-09-21T17:34:01"
      },
      {
        "connected": 44,
        "visitors": 483,
        "_full_text": "'-09':5,10 '-21':6,11 '02':14 '1467168112099':1,3 '17':7,12 '2016':4,9 '35':13 '35h':8 '6741':2",
        "passerby": 6741,
        "site_id": "1467168112099",
        "_id": 394009,
        "key": "1467168112099 2016-09-21 17:35h",
        "timestamp": "2016-09-21T17:35:02"
      },
      {
        "connected": 44,
        "visitors": 486,
        "_full_text": "'-09':3,9 '-21':4,10 '01':13 '1467168112099':1,7 '17':5,11 '2016':2,8 '36':12 '36h':6 '44':14",
        "passerby": 6861,
        "site_id": "1467168112099",
        "_id": 394011,
        "key": "1467168112099 2016-09-21 17:36h",
        "timestamp": "2016-09-21T17:36:01"
      },
      {
        "connected": 45,
        "visitors": 490,
        "_full_text": "'-09':4,10 '-21':5,11 '01':14 '1467168112099':1,2 '17':6,12 '2016':3,9 '37':13 '37h':7 '6974':8",
        "passerby": 6974,
        "site_id": "1467168112099",
        "_id": 394012,
        "key": "1467168112099 2016-09-21 17:37h",
        "timestamp": "2016-09-21T17:37:01"
      },
      {
        "connected": 46,
        "visitors": 494,
        "_full_text": "'-09':4,11 '-21':5,12 '01':8 '1467168112099':2,9 '17':6,13 '2016':3,10 '38':7 '38h':14 '46':1",
        "passerby": 7093,
        "site_id": "1467168112099",
        "_id": 394014,
        "key": "1467168112099 2016-09-21 17:38h",
        "timestamp": "2016-09-21T17:38:01"
      },
      {
        "connected": 46,
        "visitors": 498,
        "_full_text": "'-09':4,10 '-21':5,11 '02':14 '1467168112099':2,8 '17':6,12 '2016':3,9 '39':13 '39h':7 '46':1",
        "passerby": 7230,
        "site_id": "1467168112099",
        "_id": 394016,
        "key": "1467168112099 2016-09-21 17:39h",
        "timestamp": "2016-09-21T17:39:02"
      },
      {
        "connected": 46,
        "visitors": null,
        "_full_text": "'-09':4,10 '-21':5,11 '01':14 '1467168112099':2,8 '17':6,12 '2016':3,9 '40':13 '40h':7 '46':1",
        "passerby": 7364,
        "site_id": "1467168112099",
        "_id": 394019,
        "key": "1467168112099 2016-09-21 17:40h",
        "timestamp": "2016-09-21T17:40:01"
      },
      {
        "connected": 46,
        "visitors": 502,
        "_full_text": "'-09':4,11 '-21':5,12 '02':8 '1467168112099':1,9 '17':6,13 '2016':3,10 '41':7 '41h':14 '502':2",
        "passerby": 7500,
        "site_id": "1467168112099",
        "_id": 394022,
        "key": "1467168112099 2016-09-21 17:41h",
        "timestamp": "2016-09-21T17:41:02"
      },
      {
        "connected": 49,
        "visitors": 511,
        "_full_text": "'-09':4,11 '-21':5,12 '01':8 '1467168112099':2,9 '17':6,13 '2016':3,10 '42':7 '42h':14 '7606':1",
        "passerby": 7606,
        "site_id": "1467168112099",
        "_id": 394024,
        "key": "1467168112099 2016-09-21 17:42h",
        "timestamp": "2016-09-21T17:42:01"
      },
      {
        "connected": 49,
        "visitors": 513,
        "_full_text": "'-09':2,10 '-21':3,11 '01':6 '1467168112099':7,8 '17':4,12 '2016':1,9 '43':5 '43h':13 '513':14",
        "passerby": 7723,
        "site_id": "1467168112099",
        "_id": 394025,
        "key": "1467168112099 2016-09-21 17:43h",
        "timestamp": "2016-09-21T17:43:01"
      },
      {
        "connected": 51,
        "visitors": 520,
        "_full_text": "'-09':5,10 '-21':6,11 '01':14 '1467168112099':1,3 '17':7,12 '2016':4,9 '44':13 '44h':8 '520':2",
        "passerby": 7821,
        "site_id": "1467168112099",
        "_id": 394028,
        "key": "1467168112099 2016-09-21 17:44h",
        "timestamp": "2016-09-21T17:44:01"
      },
      {
        "connected": 51,
        "visitors": 522,
        "_full_text": "'-09':3,10 '-21':4,11 '01':14 '1467168112099':1,8 '17':5,12 '2016':2,9 '45':13 '45h':6 '51':7",
        "passerby": 7911,
        "site_id": "1467168112099",
        "_id": 394030,
        "key": "1467168112099 2016-09-21 17:45h",
        "timestamp": "2016-09-21T17:45:01"
      },
      {
        "connected": 51,
        "visitors": 522,
        "_full_text": "'-09':4,10 '-21':5,11 '01':14 '1467168112099':1,2 '17':6,12 '2016':3,9 '46':13 '46h':7 '51':8",
        "passerby": 8004,
        "site_id": "1467168112099",
        "_id": 394032,
        "key": "1467168112099 2016-09-21 17:46h",
        "timestamp": "2016-09-21T17:46:01"
      },
      {
        "connected": 52,
        "visitors": 527,
        "_full_text": "'-09':3,10 '-21':4,11 '01':14 '1467168112099':1,7 '17':5,12 '2016':2,9 '47':13 '47h':6 '527':8",
        "passerby": 8131,
        "site_id": "1467168112099",
        "_id": 394033,
        "key": "1467168112099 2016-09-21 17:47h",
        "timestamp": "2016-09-21T17:47:01"
      },
      {
        "connected": 53,
        "visitors": 532,
        "_full_text": "'-09':3,9 '-21':4,10 '02':13 '1467168112099':1,7 '17':5,11 '2016':2,8 '48':12 '48h':6 '532':14",
        "passerby": 8269,
        "site_id": "1467168112099",
        "_id": 394036,
        "key": "1467168112099 2016-09-21 17:48h",
        "timestamp": "2016-09-21T17:48:02"
      },
      {
        "connected": 54,
        "visitors": 539,
        "_full_text": "'-09':3,10 '-21':4,11 '01':7 '1467168112099':1,8 '17':5,12 '2016':2,9 '49':6 '49h':13 '8399':14",
        "passerby": 8399,
        "site_id": "1467168112099",
        "_id": 394038,
        "key": "1467168112099 2016-09-21 17:49h",
        "timestamp": "2016-09-21T17:49:01"
      },
      {
        "connected": 0,
        "visitors": 2,
        "_full_text": "'-09':3,8 '-21':4,9 '01':12 '1467168112099':1,13 '17':5,10 '2016':2,7 '50':11 '50h':6 '8':14",
        "passerby": 8,
        "site_id": "1467168112099",
        "_id": 394040,
        "key": "1467168112099 2016-09-21 17:50h",
        "timestamp": "2016-09-21T17:50:01"
      },
      {
        "connected": 0,
        "visitors": 58,
        "_full_text": "'-09':5,10 '-21':6,11 '01':14 '1467168112099':2,3 '17':7,12 '2016':4,9 '356':1 '51':13 '51h':8",
        "passerby": 356,
        "site_id": "1467168112099",
        "_id": 394043,
        "key": "1467168112099 2016-09-21 17:51h",
        "timestamp": "2016-09-21T17:51:01"
      },
      {
        "connected": 3,
        "visitors": 93,
        "_full_text": "'-09':4,10 '-21':5,11 '01':14 '1467168112099':2,8 '17':6,12 '2016':3,9 '52':13 '52h':7 '666':1",
        "passerby": 666,
        "site_id": "1467168112099",
        "_id": 394044,
        "key": "1467168112099 2016-09-21 17:52h",
        "timestamp": "2016-09-21T17:52:01"
      },
      {
        "connected": 4,
        "visitors": 103,
        "_full_text": "'-09':2,11 '-21':3,12 '01':6 '1467168112099':7,9 '17':4,13 '2016':1,10 '53':5 '53h':14 '893':8",
        "passerby": 893,
        "site_id": "1467168112099",
        "_id": 394046,
        "key": "1467168112099 2016-09-21 17:53h",
        "timestamp": "2016-09-21T17:53:01"
      },
      {
        "connected": 4,
        "visitors": 112,
        "_full_text": "'-09':2,10 '-21':3,11 '01':6 '1467168112099':7,8 '17':4,12 '2016':1,9 '4':14 '54':5 '54h':13",
        "passerby": null,
        "site_id": "1467168112099",
        "_id": 394050,
        "key": "1467168112099 2016-09-21 17:54h",
        "timestamp": "2016-09-21T17:54:01"
      },
      {
        "connected": 5,
        "visitors": 124,
        "_full_text": "'-09':3,11 '-21':4,12 '01':7 '1300':8 '1467168112099':1,9 '17':5,13 '2016':2,10 '55':6 '55h':14",
        "passerby": 1300,
        "site_id": "1467168112099",
        "_id": 394052,
        "key": "1467168112099 2016-09-21 17:55h",
        "timestamp": "2016-09-21T17:55:01"
      },
      {
        "connected": 5,
        "visitors": 132,
        "_full_text": "'-09':4,11 '-21':5,12 '01':8 '1467168112099':1,9 '17':6,13 '2016':3,10 '5':2 '56':7 '56h':14",
        "passerby": 1477,
        "site_id": "1467168112099",
        "_id": 394055,
        "key": "1467168112099 2016-09-21 17:56h",
        "timestamp": "2016-09-21T17:56:01"
      },
      {
        "connected": 7,
        "visitors": 142,
        "_full_text": "'-09':3,10 '-21':4,11 '02':14 '1467168112099':1,7 '17':5,12 '2016':2,9 '57':13 '57h':6 '7':8",
        "passerby": 1633,
        "site_id": "1467168112099",
        "_id": 394057,
        "key": "1467168112099 2016-09-21 17:57h",
        "timestamp": "2016-09-21T17:57:02"
      },
      {
        "connected": 7,
        "visitors": 146,
        "_full_text": "'-09':3,10 '-21':4,11 '02':14 '146':7 '1467168112099':1,8 '17':5,12 '2016':2,9 '58':13 '58h':6",
        "passerby": 1753,
        "site_id": "1467168112099",
        "_id": 394058,
        "key": "1467168112099 2016-09-21 17:58h",
        "timestamp": "2016-09-21T17:58:02"
      },
      {
        "connected": null,
        "visitors": 156,
        "_full_text": "'-09':4,10 '-21':5,11 '01':14 '1467168112099':1,2 '17':6,12 '1902':8 '2016':3,9 '59':13 '59h':7",
        "passerby": 1902,
        "site_id": "1467168112099",
        "_id": 394060,
        "key": "1467168112099 2016-09-21 17:59h",
        "timestamp": "2016-09-21T17:59:01"
      },
      {
        "connected": 8,
        "visitors": 165,
        "_full_text": "'-09':4,11 '-21':5,12 '00':7 '00h':14 '01':8 '1467168112099':2,9 '18':6,13 '2016':3,10 '8':1",
        "passerby": 2081,
        "site_id": "1467168112099",
        "_id": 394064,
        "key": "1467168112099 2016-09-21 18:00h",
        "timestamp": "2016-09-21T18:00:01"
      },
      {
        "connected": 9,
        "visitors": 173,
        "_full_text": "'-09':4,10 '-21':5,11 '01':13,14 '01h':7 '1467168112099':2,8 '18':6,12 '2016':3,9 '9':1",
        "passerby": 2216,
        "site_id": "1467168112099",
        "_id": 394066,
        "key": "1467168112099 2016-09-21 18:01h",
        "timestamp": "2016-09-21T18:01:01"
      },
      {
        "connected": 9,
        "visitors": 182,
        "_full_text": "'-09':4,11 '-21':5,12 '02':7,8 '02h':14 '1467168112099':2,9 '18':6,13 '2016':3,10 '2352':1",
        "passerby": 2352,
        "site_id": "1467168112099",
        "_id": 394067,
        "key": "1467168112099 2016-09-21 18:02h",
        "timestamp": "2016-09-21T18:02:02"
      },
      {
        "connected": null,
        "visitors": 192,
        "_full_text": "'-09':2,11 '-21':3,12 '02':6 '03':5 '03h':14 '1467168112099':7,9 '18':4,13 '2016':1,10 '2484':8",
        "passerby": 2484,
        "site_id": "1467168112099",
        "_id": 394071,
        "key": "1467168112099 2016-09-21 18:03h",
        "timestamp": "2016-09-21T18:03:02"
      },
      {
        "connected": null,
        "visitors": 198,
        "_full_text": "'-09':2,9 '-21':3,10 '02':6 '04':5 '04h':12 '1467168112099':7,13 '18':4,11 '2016':1,8 '2603':14",
        "passerby": 2603,
        "site_id": "1467168112099",
        "_id": 394073,
        "key": "1467168112099 2016-09-21 18:04h",
        "timestamp": "2016-09-21T18:04:02"
      },
      {
        "connected": 13,
        "visitors": 209,
        "_full_text": "'-09':5,10 '-21':6,11 '02':14 '05':13 '05h':8 '1467168112099':2,3 '18':7,12 '2016':4,9 '209':1",
        "passerby": null,
        "site_id": "1467168112099",
        "_id": 394076,
        "key": "1467168112099 2016-09-21 18:05h",
        "timestamp": "2016-09-21T18:05:02"
      },
      {
        "connected": 14,
        "visitors": 217,
        "_full_text": "'-09':3,10 '-21':4,11 '02':14 '06':13 '06h':6 '1467168112099':1,8 '18':5,12 '2016':2,9 '2882':7",
        "passerby": 2882,
        "site_id": "1467168112099",
        "_id": 394079,
        "key": "1467168112099 2016-09-21 18:06h",
        "timestamp": "2016-09-21T18:06:02"
      },
      {
        "connected": 15,
        "visitors": 223,
        "_full_text": "'-09':4,10 '-21':5,11 '01':14 '07':13 '07h':7 '1467168112099':1,2 '18':6,12 '2016':3,9 '223':8",
        "passerby": 3043,
        "site_id": "1467168112099",
        "_id": 394082,
        "key": "1467168112099 2016-09-21 18:07h",
        "timestamp": "2016-09-21T18:07:01"
      },
      {
        "connected": 15,
        "visitors": 228,
        "_full_text": "'-09':4,11 '-21':5,12 '01':8 '08':7 '08h':14 '1467168112099':1,9 '15':2 '18':6,13 '2016':3,10",
        "passerby": null,
        "site_id": "1467168112099",
        "_id": 394083,
        "key": "1467168112099 2016-09-21 18:08h",
        "timestamp": "2016-09-21T18:08:01"
      },
      {
        "connected": 16,
        "visitors": 238,
        "_full_text": "'-09':4,10 '-21':5,11 '01':14 '09':13 '09h':7 '1467168112099':2,8 '18':6,12 '2016':3,9 '3355':1",
        "passerby": 3355,
        "site_id": "1467168112099",
        "_id": 394086,
        "key": "1467168112099 2016-09-21 18:09h",
        "timestamp": "2016-09-21T18:09:01"
      },
      {
        "connected": 16,
        "visitors": 240,
        "_full_text": "'-09':3,11 '-21':4,12 '01':7 '10':6 '10h':14 '1467168112099':1,9 '18':5,13 '2016':2,10 '240':8",
        "passerby": 3500,
        "site_id": "1467168112099",
        "_id": 394088,
        "key": "1467168112099 2016-09-21 18:10h",
        "timestamp": "2016-09-21T18:10:01"
      },
      {
        "connected": 16,
        "visitors": 245,
        "_full_text": "'-09':2,10 '-21':3,11 '01':6 '11':5 '11h':13 '1467168112099':7,8 '18':4,12 '2016':1,9 '3704':14",
        "passerby": 3704,
        "site_id": "1467168112099",
        "_id": 394089,
        "key": "1467168112099 2016-09-21 18:11h",
        "timestamp": "2016-09-21T18:11:01"
      },
      {
        "connected": 16,
        "visitors": 247,
        "_full_text": "'-09':4,10 '-21':5,11 '01':14 '12':13 '12h':7 '1467168112099':2,8 '18':6,12 '2016':3,9 '247':1",
        "passerby": 3846,
        "site_id": "1467168112099",
        "_id": 394091,
        "key": "1467168112099 2016-09-21 18:12h",
        "timestamp": "2016-09-21T18:12:01"
      },
      {
        "connected": 17,
        "visitors": 254,
        "_full_text": "'-09':4,11 '-21':5,12 '01':8 '13':7 '13h':14 '1467168112099':1,9 '18':6,13 '2016':3,10 '254':2",
        "passerby": 3988,
        "site_id": "1467168112099",
        "_id": 394093,
        "key": "1467168112099 2016-09-21 18:13h",
        "timestamp": "2016-09-21T18:13:01"
      },
      {
        "connected": 17,
        "visitors": 255,
        "_full_text": "'-09':2,10 '-21':3,11 '02':6 '14':5 '1467168112099':7,8 '14h':13 '18':4,12 '2016':1,9 '255':14",
        "passerby": null,
        "site_id": "1467168112099",
        "_id": 394098,
        "key": "1467168112099 2016-09-21 18:14h",
        "timestamp": "2016-09-21T18:14:02"
      },
      {
        "connected": 19,
        "visitors": 257,
        "_full_text": "'-09':3,8 '-21':4,9 '01':12 '1467168112099':1,13 '15':11 '15h':6 '18':5,10 '19':14 '2016':2,7",
        "passerby": 4242,
        "site_id": "1467168112099",
        "_id": 394100,
        "key": "1467168112099 2016-09-21 18:15h",
        "timestamp": "2016-09-21T18:15:01"
      },
      {
        "connected": 19,
        "visitors": 261,
        "_full_text": "'-09':2,11 '-21':3,12 '01':6 '1467168112099':7,9 '16':5 '16h':14 '18':4,13 '2016':1,10 '4392':8",
        "passerby": 4392,
        "site_id": "1467168112099",
        "_id": 394102,
        "key": "1467168112099 2016-09-21 18:16h",
        "timestamp": "2016-09-21T18:16:01"
      },
      {
        "connected": 19,
        "visitors": 265,
        "_full_text": "'-09':3,10 '-21':4,11 '01':14 '1467168112099':1,8 '17':13 '17h':6 '18':5,12 '2016':2,9 '265':7",
        "passerby": null,
        "site_id": "1467168112099",
        "_id": 394104,
        "key": "1467168112099 2016-09-21 18:17h",
        "timestamp": "2016-09-21T18:17:01"
      },
      {
        "connected": 19,
        "visitors": 272,
        "_full_text": "'-09':3,11 '-21':4,12 '01':7 '1467168112099':1,9 '18':5,6,13 '18h':14 '2016':2,10 '272':8",
        "passerby": 4712,
        "site_id": "1467168112099",
        "_id": 394107,
        "key": "1467168112099 2016-09-21 18:18h",
        "timestamp": "2016-09-21T18:18:01"
      },
      {
        "connected": 21,
        "visitors": 285,
        "_full_text": "'-09':3,10 '-21':4,11 '01':7 '1467168112099':1,8 '18':5,12 '2016':2,9 '22':6 '22h':13 '5235':14",
        "passerby": 5235,
        "site_id": "1467168112099",
        "_id": 394118,
        "key": "1467168112099 2016-09-21 18:22h",
        "timestamp": "2016-09-21T18:22:01"
      },
      {
        "connected": null,
        "visitors": 274,
        "_full_text": "'-09':2,10 '-21':3,11 '01':6 '1467168112099':7,8 '18':4,12 '19':5 '19h':13 '2016':1,9 '4820':14",
        "passerby": 4820,
        "site_id": "1467168112099",
        "_id": 394111,
        "key": "1467168112099 2016-09-21 18:19h",
        "timestamp": "2016-09-21T18:19:01"
      },
      {
        "connected": 21,
        "visitors": 277,
        "_full_text": "'-09':2,10 '-21':3,11 '01':6 '1467168112099':7,8 '18':4,12 '20':5 '2016':1,9 '20h':13 '277':14",
        "passerby": null,
        "site_id": "1467168112099",
        "_id": 394113,
        "key": "1467168112099 2016-09-21 18:20h",
        "timestamp": "2016-09-21T18:20:01"
      },
      {
        "connected": 21,
        "visitors": 280,
        "_full_text": "'-09':4,11 '-21':5,12 '01':8 '1467168112099':2,9 '18':6,13 '2016':3,10 '21':7 '21h':14 '280':1",
        "passerby": 5083,
        "site_id": "1467168112099",
        "_id": 394117,
        "key": "1467168112099 2016-09-21 18:21h",
        "timestamp": "2016-09-21T18:21:01"
      },
      {
        "connected": 23,
        "visitors": 291,
        "_full_text": "'-09':3,9 '-21':4,10 '01':13 '1467168112099':1,7 '18':5,11 '2016':2,8 '23':12 '23h':6 '5395':14",
        "passerby": 5395,
        "site_id": "1467168112099",
        "_id": 394121,
        "key": "1467168112099 2016-09-21 18:23h",
        "timestamp": "2016-09-21T18:23:01"
      },
      {
        "connected": 25,
        "visitors": 296,
        "_full_text": "'-09':3,8 '-21':4,9 '01':12 '1467168112099':1,13 '18':5,10 '2016':2,7 '24':11 '24h':6 '5521':14",
        "passerby": 5521,
        "site_id": "1467168112099",
        "_id": 394122,
        "key": "1467168112099 2016-09-21 18:24h",
        "timestamp": "2016-09-21T18:24:01"
      },
      {
        "connected": 25,
        "visitors": 299,
        "_full_text": "'-09':4,10 '-21':5,11 '01':14 '1467168112099':1,2 '18':6,12 '2016':3,9 '25':13 '25h':7 '5642':8",
        "passerby": 5642,
        "site_id": "1467168112099",
        "_id": 394125,
        "key": "1467168112099 2016-09-21 18:25h",
        "timestamp": "2016-09-21T18:25:01"
      },
      {
        "connected": 27,
        "visitors": 306,
        "_full_text": "'-09':4,10 '-21':5,11 '01':14 '1467168112099':2,8 '18':6,12 '2016':3,9 '26':13 '26h':7 '306':1",
        "passerby": null,
        "site_id": "1467168112099",
        "_id": 394127,
        "key": "1467168112099 2016-09-21 18:26h",
        "timestamp": "2016-09-21T18:26:01"
      },
      {
        "connected": 28,
        "visitors": 312,
        "_full_text": "'-09':2,11 '-21':3,12 '01':6 '1467168112099':7,9 '18':4,13 '2016':1,10 '27':5 '27h':14 '28':8",
        "passerby": null,
        "site_id": "1467168112099",
        "_id": 394129,
        "key": "1467168112099 2016-09-21 18:27h",
        "timestamp": "2016-09-21T18:27:01"
      },
      {
        "connected": 29,
        "visitors": 316,
        "_full_text": "'-09':2,10 '-21':3,11 '01':6 '1467168112099':7,8 '18':4,12 '2016':1,9 '28':5 '28h':13 '316':14",
        "passerby": 5958,
        "site_id": "1467168112099",
        "_id": 394132,
        "key": "1467168112099 2016-09-21 18:28h",
        "timestamp": "2016-09-21T18:28:01"
      },
      {
        "connected": 29,
        "visitors": 319,
        "_full_text": "'-09':4,11 '-21':5,12 '01':8 '1467168112099':2,9 '18':6,13 '2016':3,10 '29':7 '29h':14 '6086':1",
        "passerby": 6086,
        "site_id": "1467168112099",
        "_id": 394133,
        "key": "1467168112099 2016-09-21 18:29h",
        "timestamp": "2016-09-21T18:29:01"
      },
      {
        "connected": 29,
        "visitors": 320,
        "_full_text": "'-09':4,10 '-21':5,11 '01':14 '1467168112099':1,2 '18':6,12 '2016':3,9 '29':8 '30':13 '30h':7",
        "passerby": 6181,
        "site_id": "1467168112099",
        "_id": 394135,
        "key": "1467168112099 2016-09-21 18:30h",
        "timestamp": "2016-09-21T18:30:01"
      },
      {
        "connected": 29,
        "visitors": 326,
        "_full_text": "'-09':2,9 '-21':3,10 '02':6 '1467168112099':7,13 '18':4,11 '2016':1,8 '31':5 '31h':12 '6281':14",
        "passerby": 6281,
        "site_id": "1467168112099",
        "_id": 394137,
        "key": "1467168112099 2016-09-21 18:31h",
        "timestamp": "2016-09-21T18:31:02"
      },
      {
        "connected": 29,
        "visitors": 328,
        "_full_text": "'-09':4,9 '-21':5,10 '02':13 '1467168112099':1,2 '18':6,11 '2016':3,8 '32':12 '32h':7 '6422':14",
        "passerby": 6422,
        "site_id": "1467168112099",
        "_id": 394139,
        "key": "1467168112099 2016-09-21 18:32h",
        "timestamp": "2016-09-21T18:32:02"
      },
      {
        "connected": null,
        "visitors": 334,
        "_full_text": "'-09':3,9 '-21':4,10 '01':13 '1467168112099':1,7 '18':5,11 '2016':2,8 '33':12 '33h':6 '6551':14",
        "passerby": 6551,
        "site_id": "1467168112099",
        "_id": 394141,
        "key": "1467168112099 2016-09-21 18:33h",
        "timestamp": "2016-09-21T18:33:01"
      },
      {
        "connected": 31,
        "visitors": 337,
        "_full_text": "'-09':3,10 '-21':4,11 '01':14 '1467168112099':1,7 '18':5,12 '2016':2,9 '34':13 '34h':6 '6677':8",
        "passerby": 6677,
        "site_id": "1467168112099",
        "_id": 394144,
        "key": "1467168112099 2016-09-21 18:34h",
        "timestamp": "2016-09-21T18:34:01"
      },
      {
        "connected": 33,
        "visitors": 340,
        "_full_text": "'-09':3,10 '-21':4,11 '02':7 '1467168112099':1,8 '18':5,12 '2016':2,9 '35':6 '35h':13 '6801':14",
        "passerby": 6801,
        "site_id": "1467168112099",
        "_id": 394147,
        "key": "1467168112099 2016-09-21 18:35h",
        "timestamp": "2016-09-21T18:35:02"
      },
      {
        "connected": 35,
        "visitors": 347,
        "_full_text": "'-09':2,11 '-21':3,12 '01':6 '1467168112099':8,9 '18':4,13 '2016':1,10 '37':5 '37h':14 '7075':7",
        "passerby": 7075,
        "site_id": "1467168112099",
        "_id": 394150,
        "key": "1467168112099 2016-09-21 18:37h",
        "timestamp": "2016-09-21T18:37:01"
      },
      {
        "connected": 34,
        "visitors": 343,
        "_full_text": "'-09':2,11 '-21':3,12 '02':6 '1467168112099':7,9 '18':4,13 '2016':1,10 '343':8 '36':5 '36h':14",
        "passerby": 6933,
        "site_id": "1467168112099",
        "_id": 394149,
        "key": "1467168112099 2016-09-21 18:36h",
        "timestamp": "2016-09-21T18:36:02"
      },
      {
        "connected": 36,
        "visitors": 350,
        "_full_text": "'-09':5,10 '-21':6,11 '01':14 '1467168112099':1,3 '18':7,12 '2016':4,9 '350':2 '38':13 '38h':8",
        "passerby": 7204,
        "site_id": "1467168112099",
        "_id": 394152,
        "key": "1467168112099 2016-09-21 18:38h",
        "timestamp": "2016-09-21T18:38:01"
      },
      {
        "connected": 36,
        "visitors": 355,
        "_full_text": "'-09':4,10 '-21':5,11 '01':14 '1467168112099':2,8 '18':6,12 '2016':3,9 '39':13 '39h':7 '7350':1",
        "passerby": 7350,
        "site_id": "1467168112099",
        "_id": 394154,
        "key": "1467168112099 2016-09-21 18:39h",
        "timestamp": "2016-09-21T18:39:01"
      },
      {
        "connected": null,
        "visitors": 358,
        "_full_text": "'-09':2,9 '-21':3,10 '02':6 '1467168112099':7,14 '18':4,11 '2016':1,8 '40':5 '40h':12 '7467':13",
        "passerby": 7467,
        "site_id": "1467168112099",
        "_id": 394158,
        "key": "1467168112099 2016-09-21 18:40h",
        "timestamp": "2016-09-21T18:40:02"
      },
      {
        "connected": 37,
        "visitors": 360,
        "_full_text": "'-09':4,9 '-21':5,10 '02':13 '1467168112099':1,2 '18':6,11 '2016':3,8 '360':14 '41':12 '41h':7",
        "passerby": 7619,
        "site_id": "1467168112099",
        "_id": 394161,
        "key": "1467168112099 2016-09-21 18:41h",
        "timestamp": "2016-09-21T18:41:02"
      },
      {
        "connected": 38,
        "visitors": 362,
        "_full_text": "'-09':3,10 '-21':4,11 '01':14 '1467168112099':1,8 '18':5,12 '2016':2,9 '362':7 '42':13 '42h':6",
        "passerby": 7732,
        "site_id": "1467168112099",
        "_id": 394162,
        "key": "1467168112099 2016-09-21 18:42h",
        "timestamp": "2016-09-21T18:42:01"
      },
      {
        "connected": 39,
        "visitors": 365,
        "_full_text": "'-09':5,10 '-21':6,11 '01':14 '1467168112099':2,3 '18':7,12 '2016':4,9 '43':13 '43h':8 '7845':1",
        "passerby": 7845,
        "site_id": "1467168112099",
        "_id": 394164,
        "key": "1467168112099 2016-09-21 18:43h",
        "timestamp": "2016-09-21T18:43:01"
      },
      {
        "connected": 40,
        "visitors": 368,
        "_full_text": "'-09':4,11 '-21':5,12 '02':8 '1467168112099':1,9 '18':6,13 '2016':3,10 '44':7 '44h':14 '7959':2",
        "passerby": 7959,
        "site_id": "1467168112099",
        "_id": 394166,
        "key": "1467168112099 2016-09-21 18:44h",
        "timestamp": "2016-09-21T18:44:02"
      },
      {
        "connected": 40,
        "visitors": 370,
        "_full_text": "'-09':3,10 '-21':4,11 '01':14 '1467168112099':1,7 '18':5,12 '2016':2,9 '370':8 '45':13 '45h':6",
        "passerby": 8094,
        "site_id": "1467168112099",
        "_id": 394168,
        "key": "1467168112099 2016-09-21 18:45h",
        "timestamp": "2016-09-21T18:45:01"
      },
      {
        "connected": 40,
        "visitors": 370,
        "_full_text": "'-09':3,10 '-21':4,11 '02':7 '1467168112099':1,8 '18':5,12 '2016':2,9 '40':14 '46':6 '46h':13",
        "passerby": 8208,
        "site_id": "1467168112099",
        "_id": 394170,
        "key": "1467168112099 2016-09-21 18:46h",
        "timestamp": "2016-09-21T18:46:02"
      },
      {
        "connected": 40,
        "visitors": 375,
        "_full_text": "'-09':3,11 '-21':4,12 '01':7 '1467168112099':1,9 '18':5,13 '2016':2,10 '40':8 '47':6 '47h':14",
        "passerby": 8340,
        "site_id": "1467168112099",
        "_id": 394172,
        "key": "1467168112099 2016-09-21 18:47h",
        "timestamp": "2016-09-21T18:47:01"
      },
      {
        "connected": null,
        "visitors": 383,
        "_full_text": "'-09':4,10 '-21':5,11 '01':14 '1467168112099':2,8 '18':6,12 '2016':3,9 '48':13 '48h':7 '8457':1",
        "passerby": 8457,
        "site_id": "1467168112099",
        "_id": 394176,
        "key": "1467168112099 2016-09-21 18:48h",
        "timestamp": "2016-09-21T18:48:01"
      }
    ],
    "fields": [
      {
        "id": "_id",
        "type": "int4"
      },
      {
        "id": "_full_text",
        "type": "tsvector"
      },
      {
        "id": "key",
        "type": "text"
      },
      {
        "id": "site_id",
        "type": "text"
      },
      {
        "id": "timestamp",
        "type": "timestamp"
      },
      {
        "id": "visitors",
        "type": "int4"
      },
      {
        "id": "connected",
        "type": "int4"
      },
      {
        "id": "passerby",
        "type": "int4"
      }
    ],
    "sql": "SELECT * from \"62e2e9ff-0c99-47cf-bc37-6b3a0617095b\" WHERE timestamp >= '2016-09-21 16:00:00'  AND timestamp < '2016-09-21 20:00:00' AND site_id = '1467168112099'"
  },
  "help": "http://10.90.129.12/api/3/action/help_show?name=datastore_search_sql",
  "success": true
}