{
  "result": {
    "records": [
      {
        "connected": 12,
        "visitors": 29,
        "_full_text": "'-09':3,10 '-29':4,11 '00':5,12,13 '00h':6 '01':14 '1467168112099':1,7 '2016':2,9 '29':8",
        "passerby": null,
        "site_id": "1467168112099",
        "_id": 418113,
        "key": "1467168112099 2016-09-29 00:00h",
        "timestamp": "2016-09-29T00:00:01"
      },
      {
        "connected": 13,
        "visitors": 33,
        "_full_text": "'-09':4,11 '-29':5,12 '00':6,13 '01':7,8 '01h':14 '13':2 '1467168112099':1,9 '2016':3,10",
        "passerby": 718,
        "site_id": "1467168112099",
        "_id": 418115,
        "key": "1467168112099 2016-09-29 00:01h",
        "timestamp": "2016-09-29T00:01:01"
      },
      {
        "connected": 13,
        "visitors": 35,
        "_full_text": "'-09':2,11 '-29':3,12 '00':4,13 '02':5,6 '02h':14 '1467168112099':7,9 '2016':1,10 '756':8",
        "passerby": 756,
        "site_id": "1467168112099",
        "_id": 418118,
        "key": "1467168112099 2016-09-29 00:02h",
        "timestamp": "2016-09-29T00:02:02"
      },
      {
        "connected": 14,
        "visitors": 36,
        "_full_text": "'-09':2,10 '-29':3,11 '00':4,12 '01':6 '03':5 '03h':13 '1467168112099':7,8 '2016':1,9 '36':14",
        "passerby": 794,
        "site_id": "1467168112099",
        "_id": 418119,
        "key": "1467168112099 2016-09-29 00:03h",
        "timestamp": "2016-09-29T00:03:01"
      },
      {
        "connected": 16,
        "visitors": 38,
        "_full_text": "'-09':5,10 '-29':6,11 '00':7,12 '01':14 '04':13 '04h':8 '1467168112099':1,3 '16':2 '2016':4,9",
        "passerby": 845,
        "site_id": "1467168112099",
        "_id": 418122,
        "key": "1467168112099 2016-09-29 00:04h",
        "timestamp": "2016-09-29T00:04:01"
      },
      {
        "connected": null,
        "visitors": 39,
        "_full_text": "'-09':4,10 '-29':5,11 '00':6,12 '01':14 '05':13 '05h':7 '1467168112099':2,8 '2016':3,9 '39':1",
        "passerby": 878,
        "site_id": "1467168112099",
        "_id": 418123,
        "key": "1467168112099 2016-09-29 00:05h",
        "timestamp": "2016-09-29T00:05:01"
      },
      {
        "connected": 16,
        "visitors": 39,
        "_full_text": "'-09':4,10 '-29':5,11 '00':6,12 '01':14 '06':13 '06h':7 '1467168112099':1,2 '2016':3,9 '39':8",
        "passerby": 906,
        "site_id": "1467168112099",
        "_id": 418127,
        "key": "1467168112099 2016-09-29 00:06h",
        "timestamp": "2016-09-29T00:06:01"
      },
      {
        "connected": 17,
        "visitors": 42,
        "_full_text": "'-09':3,10 '-29':4,11 '00':5,12 '02':14 '07':13 '07h':6 '1467168112099':1,7 '2016':2,9 '937':8",
        "passerby": 937,
        "site_id": "1467168112099",
        "_id": 418129,
        "key": "1467168112099 2016-09-29 00:07h",
        "timestamp": "2016-09-29T00:07:02"
      },
      {
        "connected": 17,
        "visitors": 42,
        "_full_text": "'-09':3,10 '-29':4,11 '00':5,12 '01':14 '08':13 '08h':6 '1467168112099':1,7 '2016':2,9 '963':8",
        "passerby": 963,
        "site_id": "1467168112099",
        "_id": 418130,
        "key": "1467168112099 2016-09-29 00:08h",
        "timestamp": "2016-09-29T00:08:01"
      },
      {
        "connected": 18,
        "visitors": 44,
        "_full_text": "'-09':3,10 '-29':4,11 '00':5,12 '02':7 '09':6 '09h':13 '1467168112099':1,8 '2016':2,9 '44':14",
        "passerby": 999,
        "site_id": "1467168112099",
        "_id": 418132,
        "key": "1467168112099 2016-09-29 00:09h",
        "timestamp": "2016-09-29T00:09:02"
      },
      {
        "connected": 19,
        "visitors": 46,
        "_full_text": "'-09':3,8 '-29':4,9 '00':5,10 '01':12 '10':11 '1021':14 '10h':6 '1467168112099':1,13 '2016':2,7",
        "passerby": 1021,
        "site_id": "1467168112099",
        "_id": 418134,
        "key": "1467168112099 2016-09-29 00:10h",
        "timestamp": "2016-09-29T00:10:01"
      },
      {
        "connected": 19,
        "visitors": 46,
        "_full_text": "'-09':3,11 '-29':4,12 '00':5,13 '01':7 '11':6 '11h':14 '1467168112099':8,9 '2016':2,10 '46':1",
        "passerby": 1050,
        "site_id": "1467168112099",
        "_id": 418137,
        "key": "1467168112099 2016-09-29 00:11h",
        "timestamp": "2016-09-29T00:11:01"
      },
      {
        "connected": 19,
        "visitors": 47,
        "_full_text": "'-09':3,9 '-29':4,10 '00':5,11 '01':13 '1080':14 '12':12 '12h':6 '1467168112099':1,7 '2016':2,8",
        "passerby": 1080,
        "site_id": "1467168112099",
        "_id": 418139,
        "key": "1467168112099 2016-09-29 00:12h",
        "timestamp": "2016-09-29T00:12:01"
      },
      {
        "connected": 20,
        "visitors": 51,
        "_full_text": "'-09':3,11 '-29':4,12 '00':5,13 '02':7 '1119':1 '13':6 '13h':14 '1467168112099':8,9 '2016':2,10",
        "passerby": 1119,
        "site_id": "1467168112099",
        "_id": 418140,
        "key": "1467168112099 2016-09-29 00:13h",
        "timestamp": "2016-09-29T00:13:02"
      },
      {
        "connected": 20,
        "visitors": 52,
        "_full_text": "'-09':2,10 '-29':3,11 '00':4,12 '01':6 '14':5 '1467168112099':7,8 '14h':13 '20':14 '2016':1,9",
        "passerby": 1144,
        "site_id": "1467168112099",
        "_id": 418142,
        "key": "1467168112099 2016-09-29 00:14h",
        "timestamp": "2016-09-29T00:14:01"
      },
      {
        "connected": 20,
        "visitors": 53,
        "_full_text": "'-09':3,11 '-29':4,12 '00':5,13 '01':7 '1174':8 '1467168112099':1,9 '15':6 '15h':14 '2016':2,10",
        "passerby": 1174,
        "site_id": "1467168112099",
        "_id": 418144,
        "key": "1467168112099 2016-09-29 00:15h",
        "timestamp": "2016-09-29T00:15:01"
      },
      {
        "connected": 20,
        "visitors": null,
        "_full_text": "'-09':2,11 '-29':3,12 '00':4,13 '02':6 '1219':8 '1467168112099':7,9 '16':5 '16h':14 '2016':1,10",
        "passerby": 1219,
        "site_id": "1467168112099",
        "_id": 418148,
        "key": "1467168112099 2016-09-29 00:16h",
        "timestamp": "2016-09-29T00:16:02"
      },
      {
        "connected": 20,
        "visitors": 53,
        "_full_text": "'-09':3,9 '-29':4,10 '00':5,11 '01':13 '1254':14 '1467168112099':1,7 '17':12 '17h':6 '2016':2,8",
        "passerby": 1254,
        "site_id": "1467168112099",
        "_id": 418151,
        "key": "1467168112099 2016-09-29 00:17h",
        "timestamp": "2016-09-29T00:17:01"
      },
      {
        "connected": 20,
        "visitors": 53,
        "_full_text": "'-09':3,8 '-29':4,9 '00':5,10 '01':12 '1467168112099':1,13 '18':11 '18h':6 '20':14 '2016':2,7",
        "passerby": 1305,
        "site_id": "1467168112099",
        "_id": 418152,
        "key": "1467168112099 2016-09-29 00:18h",
        "timestamp": "2016-09-29T00:18:01"
      },
      {
        "connected": 20,
        "visitors": 53,
        "_full_text": "'-09':4,10 '-29':5,11 '00':6,12 '01':14 '1467168112099':1,2 '19':13 '19h':7 '2016':3,9 '53':8",
        "passerby": 1343,
        "site_id": "1467168112099",
        "_id": 418154,
        "key": "1467168112099 2016-09-29 00:19h",
        "timestamp": "2016-09-29T00:19:01"
      },
      {
        "connected": 20,
        "visitors": 53,
        "_full_text": "'-09':2,10 '-29':3,11 '00':4,12 '01':6 '1467168112099':7,8 '20':5,14 '2016':1,9 '20h':13",
        "passerby": 1375,
        "site_id": "1467168112099",
        "_id": 418156,
        "key": "1467168112099 2016-09-29 00:20h",
        "timestamp": "2016-09-29T00:20:01"
      },
      {
        "connected": 20,
        "visitors": 53,
        "_full_text": "'-09':3,9 '-29':4,10 '00':5,11 '02':13 '1405':14 '1467168112099':1,7 '2016':2,8 '21':12 '21h':6",
        "passerby": 1405,
        "site_id": "1467168112099",
        "_id": 418159,
        "key": "1467168112099 2016-09-29 00:21h",
        "timestamp": "2016-09-29T00:21:02"
      },
      {
        "connected": 20,
        "visitors": 53,
        "_full_text": "'-09':2,10 '-29':3,11 '00':4,12 '01':6 '1467168112099':7,8 '2016':1,9 '22':5 '22h':13 '53':14",
        "passerby": 1425,
        "site_id": "1467168112099",
        "_id": 418160,
        "key": "1467168112099 2016-09-29 00:22h",
        "timestamp": "2016-09-29T00:22:01"
      },
      {
        "connected": 20,
        "visitors": 53,
        "_full_text": "'-09':4,10 '-29':5,11 '00':6,12 '02':14 '1442':1 '1467168112099':2,8 '2016':3,9 '23':13 '23h':7",
        "passerby": 1442,
        "site_id": "1467168112099",
        "_id": 418162,
        "key": "1467168112099 2016-09-29 00:23h",
        "timestamp": "2016-09-29T00:23:02"
      },
      {
        "connected": 20,
        "visitors": 55,
        "_full_text": "'-09':3,11 '-29':4,12 '00':5,13 '01':7 '1467168112099':1,9 '20':8 '2016':2,10 '24':6 '24h':14",
        "passerby": 1455,
        "site_id": "1467168112099",
        "_id": 418165,
        "key": "1467168112099 2016-09-29 00:24h",
        "timestamp": "2016-09-29T00:24:01"
      },
      {
        "connected": 20,
        "visitors": null,
        "_full_text": "'-09':2,10 '-29':3,11 '00':4,12 '01':6 '1467168112099':7,8 '20':14 '2016':1,9 '25':5 '25h':13",
        "passerby": 1461,
        "site_id": "1467168112099",
        "_id": 418166,
        "key": "1467168112099 2016-09-29 00:25h",
        "timestamp": "2016-09-29T00:25:01"
      },
      {
        "connected": 21,
        "visitors": 60,
        "_full_text": "'-09':3,10 '-29':4,11 '00':5,12 '02':14 '1467168112099':1,7 '2016':2,9 '21':8 '26':13 '26h':6",
        "passerby": 1475,
        "site_id": "1467168112099",
        "_id": 418169,
        "key": "1467168112099 2016-09-29 00:26h",
        "timestamp": "2016-09-29T00:26:02"
      },
      {
        "connected": 21,
        "visitors": 60,
        "_full_text": "'-09':3,10 '-29':4,11 '00':5,12 '01':7 '1467168112099':1,8 '2016':2,9 '21':14 '27':6 '27h':13",
        "passerby": 1491,
        "site_id": "1467168112099",
        "_id": 418171,
        "key": "1467168112099 2016-09-29 00:27h",
        "timestamp": "2016-09-29T00:27:01"
      },
      {
        "connected": 21,
        "visitors": 60,
        "_full_text": "'-09':5,10 '-29':6,11 '00':7,12 '01':14 '1467168112099':2,3 '2016':4,9 '28':13 '28h':8 '60':1",
        "passerby": 1498,
        "site_id": "1467168112099",
        "_id": 418174,
        "key": "1467168112099 2016-09-29 00:28h",
        "timestamp": "2016-09-29T00:28:01"
      },
      {
        "connected": 23,
        "visitors": 65,
        "_full_text": "'-09':3,10 '-29':4,11 '00':5,12 '02':14 '1467168112099':1,8 '1509':7 '2016':2,9 '29':13 '29h':6",
        "passerby": 1509,
        "site_id": "1467168112099",
        "_id": 418175,
        "key": "1467168112099 2016-09-29 00:29h",
        "timestamp": "2016-09-29T00:29:02"
      },
      {
        "connected": 23,
        "visitors": 65,
        "_full_text": "'-09':2,9 '-29':3,10 '00':4,11 '01':6 '1467168112099':7,13 '2016':1,8 '23':14 '30':5 '30h':12",
        "passerby": 1525,
        "site_id": "1467168112099",
        "_id": 418177,
        "key": "1467168112099 2016-09-29 00:30h",
        "timestamp": "2016-09-29T00:30:01"
      },
      {
        "connected": 24,
        "visitors": 66,
        "_full_text": "'-09':5,10 '-29':6,11 '00':7,12 '01':14 '1467168112099':1,3 '1533':2 '2016':4,9 '31':13 '31h':8",
        "passerby": 1533,
        "site_id": "1467168112099",
        "_id": 418180,
        "key": "1467168112099 2016-09-29 00:31h",
        "timestamp": "2016-09-29T00:31:01"
      },
      {
        "connected": 24,
        "visitors": 66,
        "_full_text": "'-09':3,9 '-29':4,10 '00':5,11 '01':13 '1467168112099':1,7 '1541':14 '2016':2,8 '32':12 '32h':6",
        "passerby": 1541,
        "site_id": "1467168112099",
        "_id": 418181,
        "key": "1467168112099 2016-09-29 00:32h",
        "timestamp": "2016-09-29T00:32:01"
      },
      {
        "connected": 24,
        "visitors": 66,
        "_full_text": "'-09':4,10 '-29':5,11 '00':6,12 '01':14 '1467168112099':1,2 '2016':3,9 '33':13 '33h':7 '66':8",
        "passerby": 1555,
        "site_id": "1467168112099",
        "_id": 418183,
        "key": "1467168112099 2016-09-29 00:33h",
        "timestamp": "2016-09-29T00:33:01"
      },
      {
        "connected": 24,
        "visitors": 66,
        "_full_text": "'-09':3,10 '-29':4,11 '00':5,12 '02':7 '1467168112099':1,8 '1565':14 '2016':2,9 '34':6 '34h':13",
        "passerby": 1565,
        "site_id": "1467168112099",
        "_id": 418186,
        "key": "1467168112099 2016-09-29 00:34h",
        "timestamp": "2016-09-29T00:34:02"
      },
      {
        "connected": 24,
        "visitors": 67,
        "_full_text": "'-09':4,10 '-29':5,11 '00':6,12 '01':14 '1467168112099':2,8 '2016':3,9 '24':1 '35':13 '35h':7",
        "passerby": 1577,
        "site_id": "1467168112099",
        "_id": 418188,
        "key": "1467168112099 2016-09-29 00:35h",
        "timestamp": "2016-09-29T00:35:01"
      },
      {
        "connected": 24,
        "visitors": 67,
        "_full_text": "'-09':2,10 '-29':3,11 '00':4,12 '01':6 '1467168112099':7,8 '2016':1,9 '36':5 '36h':13 '67':14",
        "passerby": 1597,
        "site_id": "1467168112099",
        "_id": 418190,
        "key": "1467168112099 2016-09-29 00:36h",
        "timestamp": "2016-09-29T00:36:01"
      },
      {
        "connected": 24,
        "visitors": 67,
        "_full_text": "'-09':4,11 '-29':5,12 '00':6,13 '01':8 '1467168112099':2,9 '2016':3,10 '24':1 '37':7 '37h':14",
        "passerby": 1603,
        "site_id": "1467168112099",
        "_id": 418192,
        "key": "1467168112099 2016-09-29 00:37h",
        "timestamp": "2016-09-29T00:37:01"
      },
      {
        "connected": 24,
        "visitors": 68,
        "_full_text": "'-09':3,10 '-29':4,11 '00':5,12 '02':7 '1467168112099':8,14 '2016':2,9 '24':1 '38':6 '38h':13",
        "passerby": 1617,
        "site_id": "1467168112099",
        "_id": 418194,
        "key": "1467168112099 2016-09-29 00:38h",
        "timestamp": "2016-09-29T00:38:02"
      },
      {
        "connected": 24,
        "visitors": 68,
        "_full_text": "'-09':5,10 '-29':6,11 '00':7,12 '01':14 '1467168112099':1,3 '1632':2 '2016':4,9 '39':13 '39h':8",
        "passerby": 1632,
        "site_id": "1467168112099",
        "_id": 418196,
        "key": "1467168112099 2016-09-29 00:39h",
        "timestamp": "2016-09-29T00:39:01"
      },
      {
        "connected": 24,
        "visitors": 68,
        "_full_text": "'-09':5,10 '-29':6,11 '00':7,12 '01':14 '1467168112099':2,3 '2016':4,9 '40':13 '40h':8 '68':1",
        "passerby": 1653,
        "site_id": "1467168112099",
        "_id": 418198,
        "key": "1467168112099 2016-09-29 00:40h",
        "timestamp": "2016-09-29T00:40:01"
      },
      {
        "connected": 24,
        "visitors": 69,
        "_full_text": "'-09':3,10 '-29':4,11 '00':5,12 '01':7 '1467168112099':8,14 '2016':2,9 '24':1 '41':6 '41h':13",
        "passerby": 1658,
        "site_id": "1467168112099",
        "_id": 418199,
        "key": "1467168112099 2016-09-29 00:41h",
        "timestamp": "2016-09-29T00:41:01"
      },
      {
        "connected": 24,
        "visitors": 70,
        "_full_text": "'-09':4,10 '-29':5,11 '00':6,12 '01':14 '1467168112099':1,2 '2016':3,9 '42':13 '42h':7 '70':8",
        "passerby": 1670,
        "site_id": "1467168112099",
        "_id": 418203,
        "key": "1467168112099 2016-09-29 00:42h",
        "timestamp": "2016-09-29T00:42:01"
      },
      {
        "connected": 25,
        "visitors": 71,
        "_full_text": "'-09':3,10 '-29':4,11 '00':5,12 '01':14 '1467168112099':1,8 '2016':2,9 '25':7 '43':13 '43h':6",
        "passerby": 1688,
        "site_id": "1467168112099",
        "_id": 418205,
        "key": "1467168112099 2016-09-29 00:43h",
        "timestamp": "2016-09-29T00:43:01"
      },
      {
        "connected": 25,
        "visitors": 71,
        "_full_text": "'-09':3,9 '-29':4,10 '00':5,11 '02':13 '1467168112099':1,7 '2016':2,8 '44':12 '44h':6 '71':14",
        "passerby": 1694,
        "site_id": "1467168112099",
        "_id": 418206,
        "key": "1467168112099 2016-09-29 00:44h",
        "timestamp": "2016-09-29T00:44:02"
      },
      {
        "connected": 25,
        "visitors": 72,
        "_full_text": "'-09':4,11 '-29':5,12 '00':6,13 '01':8 '1467168112099':2,9 '2016':3,10 '25':1 '45':7 '45h':14",
        "passerby": 1709,
        "site_id": "1467168112099",
        "_id": 418208,
        "key": "1467168112099 2016-09-29 00:45h",
        "timestamp": "2016-09-29T00:45:01"
      },
      {
        "connected": 25,
        "visitors": 72,
        "_full_text": "'-09':3,11 '-29':4,12 '00':5,13 '01':7 '1467168112099':1,9 '1720':8 '2016':2,10 '46':6 '46h':14",
        "passerby": 1720,
        "site_id": "1467168112099",
        "_id": 418211,
        "key": "1467168112099 2016-09-29 00:46h",
        "timestamp": "2016-09-29T00:46:01"
      },
      {
        "connected": 25,
        "visitors": 72,
        "_full_text": "'-09':2,11 '-29':3,12 '00':4,13 '01':6 '1467168112099':8,9 '2016':1,10 '25':7 '47':5 '47h':14",
        "passerby": 1733,
        "site_id": "1467168112099",
        "_id": 418212,
        "key": "1467168112099 2016-09-29 00:47h",
        "timestamp": "2016-09-29T00:47:01"
      },
      {
        "connected": 25,
        "visitors": null,
        "_full_text": "'-09':5,10 '-29':6,11 '00':7,12 '01':14 '1467168112099':2,3 '1752':1 '2016':4,9 '48':13 '48h':8",
        "passerby": 1752,
        "site_id": "1467168112099",
        "_id": 418217,
        "key": "1467168112099 2016-09-29 00:48h",
        "timestamp": "2016-09-29T00:48:01"
      },
      {
        "connected": 25,
        "visitors": 73,
        "_full_text": "'-09':2,9 '-29':3,10 '00':4,11 '02':6 '1467168112099':7,14 '2016':1,8 '49':5 '49h':12 '73':13",
        "passerby": 1770,
        "site_id": "1467168112099",
        "_id": 418219,
        "key": "1467168112099 2016-09-29 00:49h",
        "timestamp": "2016-09-29T00:49:02"
      },
      {
        "connected": 0,
        "visitors": 16,
        "_full_text": "'-09':2,10 '-29':3,11 '00':4,12 '01':6 '1467168112099':7,8 '2016':1,9 '50':5 '50h':13",
        "passerby": 53,
        "site_id": "1467168112099",
        "_id": 418222,
        "key": "1467168112099 2016-09-29 00:50h",
        "timestamp": "2016-09-29T00:50:01"
      },
      {
        "connected": 0,
        "visitors": null,
        "_full_text": "'-09':3,11 '-29':4,12 '00':5,13 '01':7 '112':8 '1467168112099':1,9 '2016':2,10 '51':6 '51h':14",
        "passerby": 112,
        "site_id": "1467168112099",
        "_id": 418224,
        "key": "1467168112099 2016-09-29 00:51h",
        "timestamp": "2016-09-29T00:51:01"
      },
      {
        "connected": 0,
        "visitors": 29,
        "_full_text": "'-09':2,11 '-29':3,12 '00':4,13 '02':6 '1467168112099':7,9 '157':8 '2016':1,10 '52':5 '52h':14",
        "passerby": 157,
        "site_id": "1467168112099",
        "_id": 418227,
        "key": "1467168112099 2016-09-29 00:52h",
        "timestamp": "2016-09-29T00:52:02"
      },
      {
        "connected": 0,
        "visitors": 31,
        "_full_text": "'-09':3,9 '-29':4,10 '00':5,11 '01':13 '1467168112099':1,7 '2016':2,8 '53':12 '53h':6",
        "passerby": 187,
        "site_id": "1467168112099",
        "_id": 418229,
        "key": "1467168112099 2016-09-29 00:53h",
        "timestamp": "2016-09-29T00:53:01"
      },
      {
        "connected": 1,
        "visitors": 34,
        "_full_text": "'-09':3,8 '-29':4,9 '00':5,10 '01':12 '1':14 '1467168112099':1,13 '2016':2,7 '54':11 '54h':6",
        "passerby": 210,
        "site_id": "1467168112099",
        "_id": 418232,
        "key": "1467168112099 2016-09-29 00:54h",
        "timestamp": "2016-09-29T00:54:01"
      },
      {
        "connected": 1,
        "visitors": 36,
        "_full_text": "'-09':2,11 '-29':3,12 '00':4,13 '02':6 '1467168112099':8,9 '2016':1,10 '227':7 '55':5 '55h':14",
        "passerby": 227,
        "site_id": "1467168112099",
        "_id": 418234,
        "key": "1467168112099 2016-09-29 00:55h",
        "timestamp": "2016-09-29T00:55:02"
      },
      {
        "connected": 1,
        "visitors": 36,
        "_full_text": "'-09':4,10 '-29':5,11 '00':6,12 '01':14 '1':1 '1467168112099':2,8 '2016':3,9 '56':13 '56h':7",
        "passerby": 236,
        "site_id": "1467168112099",
        "_id": 418236,
        "key": "1467168112099 2016-09-29 00:56h",
        "timestamp": "2016-09-29T00:56:01"
      },
      {
        "connected": 1,
        "visitors": 37,
        "_full_text": "'-09':4,11 '-29':5,12 '00':6,13 '02':8 '1467168112099':2,9 '2016':3,10 '37':1 '57':7 '57h':14",
        "passerby": 255,
        "site_id": "1467168112099",
        "_id": 418237,
        "key": "1467168112099 2016-09-29 00:57h",
        "timestamp": "2016-09-29T00:57:02"
      },
      {
        "connected": 1,
        "visitors": 38,
        "_full_text": "'-09':3,11 '-29':4,12 '00':5,13 '01':7 '1':1 '1467168112099':8,9 '2016':2,10 '58':6 '58h':14",
        "passerby": 273,
        "site_id": "1467168112099",
        "_id": 418239,
        "key": "1467168112099 2016-09-29 00:58h",
        "timestamp": "2016-09-29T00:58:01"
      },
      {
        "connected": null,
        "visitors": 39,
        "_full_text": "'-09':3,11 '-29':4,12 '00':5,13 '01':7 '1467168112099':1,9 '2016':2,10 '287':8 '59':6 '59h':14",
        "passerby": 287,
        "site_id": "1467168112099",
        "_id": 418241,
        "key": "1467168112099 2016-09-29 00:59h",
        "timestamp": "2016-09-29T00:59:01"
      },
      {
        "connected": 1,
        "visitors": 39,
        "_full_text": "'-09':5,10 '-29':6,11 '00':13 '00h':8 '01':7,12 '02':14 '1':1 '1467168112099':2,3 '2016':4,9",
        "passerby": 297,
        "site_id": "1467168112099",
        "_id": 418245,
        "key": "1467168112099 2016-09-29 01:00h",
        "timestamp": "2016-09-29T01:00:02"
      },
      {
        "connected": 1,
        "visitors": 39,
        "_full_text": "'-09':3,11 '-29':4,12 '01':5,6,7,13 '01h':14 '1467168112099':1,9 '2016':2,10 '39':8",
        "passerby": 318,
        "site_id": "1467168112099",
        "_id": 418247,
        "key": "1467168112099 2016-09-29 01:01h",
        "timestamp": "2016-09-29T01:01:01"
      },
      {
        "connected": 3,
        "visitors": 40,
        "_full_text": "'-09':4,11 '-29':5,12 '01':6,8,13 '02':7 '02h':14 '1467168112099':2,9 '2016':3,10 '333':1",
        "passerby": 333,
        "site_id": "1467168112099",
        "_id": 418249,
        "key": "1467168112099 2016-09-29 01:02h",
        "timestamp": "2016-09-29T01:02:01"
      },
      {
        "connected": 3,
        "visitors": 40,
        "_full_text": "'-09':3,9 '-29':4,10 '01':5,11,13 '03':12 '03h':6 '1467168112099':1,7 '2016':2,8 '40':14",
        "passerby": 348,
        "site_id": "1467168112099",
        "_id": 418251,
        "key": "1467168112099 2016-09-29 01:03h",
        "timestamp": "2016-09-29T01:03:01"
      },
      {
        "connected": 3,
        "visitors": 40,
        "_full_text": "'-09':3,8 '-29':4,9 '01':5,10,12 '04':11 '04h':6 '1467168112099':1,13 '2016':2,7 '3':14",
        "passerby": 368,
        "site_id": "1467168112099",
        "_id": 418252,
        "key": "1467168112099 2016-09-29 01:04h",
        "timestamp": "2016-09-29T01:04:01"
      },
      {
        "connected": 3,
        "visitors": 42,
        "_full_text": "'-09':2,10 '-29':3,11 '01':4,12 '02':6 '05':5 '05h':13 '1467168112099':7,8 '2016':1,9 '383':14",
        "passerby": 383,
        "site_id": "1467168112099",
        "_id": 418254,
        "key": "1467168112099 2016-09-29 01:05h",
        "timestamp": "2016-09-29T01:05:02"
      },
      {
        "connected": 3,
        "visitors": 44,
        "_full_text": "'-09':3,9 '-29':4,10 '01':5,11,13 '06':12 '06h':6 '1467168112099':1,7 '2016':2,8 '3':14",
        "passerby": 402,
        "site_id": "1467168112099",
        "_id": 418257,
        "key": "1467168112099 2016-09-29 01:06h",
        "timestamp": "2016-09-29T01:06:01"
      },
      {
        "connected": 4,
        "visitors": 44,
        "_full_text": "'-09':3,11 '-29':4,12 '01':5,7,13 '07':6 '07h':14 '1467168112099':8,9 '2016':2,10 '421':1",
        "passerby": 421,
        "site_id": "1467168112099",
        "_id": 418258,
        "key": "1467168112099 2016-09-29 01:07h",
        "timestamp": "2016-09-29T01:07:01"
      },
      {
        "connected": 4,
        "visitors": null,
        "_full_text": "'-09':4,10 '-29':5,11 '01':6,12 '02':14 '08':13 '08h':7 '1467168112099':1,2 '2016':3,9 '4':8",
        "passerby": 428,
        "site_id": "1467168112099",
        "_id": 418262,
        "key": "1467168112099 2016-09-29 01:08h",
        "timestamp": "2016-09-29T01:08:02"
      },
      {
        "connected": 4,
        "visitors": 46,
        "_full_text": "'-09':3,11 '-29':4,12 '01':5,7,13 '09':6 '09h':14 '1467168112099':1,9 '2016':2,10 '433':8",
        "passerby": 433,
        "site_id": "1467168112099",
        "_id": 418264,
        "key": "1467168112099 2016-09-29 01:09h",
        "timestamp": "2016-09-29T01:09:01"
      },
      {
        "connected": 5,
        "visitors": 47,
        "_full_text": "'-09':5,10 '-29':6,11 '01':7,12,14 '10':13 '10h':8 '1467168112099':1,3 '2016':4,9 '5':2",
        "passerby": 444,
        "site_id": "1467168112099",
        "_id": 418266,
        "key": "1467168112099 2016-09-29 01:10h",
        "timestamp": "2016-09-29T01:10:01"
      },
      {
        "connected": 5,
        "visitors": 48,
        "_full_text": "'-09':4,9 '-29':5,10 '01':6,11,13 '11':12 '11h':7 '1467168112099':2,14 '2016':3,8 '5':1",
        "passerby": 449,
        "site_id": "1467168112099",
        "_id": 418269,
        "key": "1467168112099 2016-09-29 01:11h",
        "timestamp": "2016-09-29T01:11:01"
      },
      {
        "connected": 5,
        "visitors": 48,
        "_full_text": "'-09':4,10 '-29':5,11 '01':6,12,14 '12':13 '12h':7 '1467168112099':1,2 '2016':3,9 '467':8",
        "passerby": 467,
        "site_id": "1467168112099",
        "_id": 418270,
        "key": "1467168112099 2016-09-29 01:12h",
        "timestamp": "2016-09-29T01:12:01"
      },
      {
        "connected": null,
        "visitors": 49,
        "_full_text": "'-09':3,10 '-29':4,11 '01':5,12 '02':14 '13':13 '13h':6 '1467168112099':1,7 '2016':2,9 '49':8",
        "passerby": 479,
        "site_id": "1467168112099",
        "_id": 418272,
        "key": "1467168112099 2016-09-29 01:13h",
        "timestamp": "2016-09-29T01:13:02"
      },
      {
        "connected": 6,
        "visitors": 49,
        "_full_text": "'-09':3,10 '-29':4,11 '01':5,12,14 '14':13 '1467168112099':1,7 '14h':6 '2016':2,9 '493':8",
        "passerby": 493,
        "site_id": "1467168112099",
        "_id": 418275,
        "key": "1467168112099 2016-09-29 01:14h",
        "timestamp": "2016-09-29T01:14:01"
      },
      {
        "connected": 6,
        "visitors": null,
        "_full_text": "'-09':3,10 '-29':4,11 '01':5,12 '02':7 '1467168112099':1,8 '15':6 '15h':13 '2016':2,9 '6':14",
        "passerby": 505,
        "site_id": "1467168112099",
        "_id": 418277,
        "key": "1467168112099 2016-09-29 01:15h",
        "timestamp": "2016-09-29T01:15:02"
      },
      {
        "connected": 6,
        "visitors": 49,
        "_full_text": "'-09':4,11 '-29':5,12 '01':6,8,13 '1467168112099':2,9 '16':7 '16h':14 '2016':3,10 '6':1",
        "passerby": 510,
        "site_id": "1467168112099",
        "_id": 418281,
        "key": "1467168112099 2016-09-29 01:16h",
        "timestamp": "2016-09-29T01:16:01"
      },
      {
        "connected": 6,
        "visitors": 49,
        "_full_text": "'-09':2,10 '-29':3,11 '01':4,6,12 '1467168112099':7,8 '17':5 '17h':13 '2016':1,9 '49':14",
        "passerby": 520,
        "site_id": "1467168112099",
        "_id": 418282,
        "key": "1467168112099 2016-09-29 01:17h",
        "timestamp": "2016-09-29T01:17:01"
      },
      {
        "connected": 6,
        "visitors": 49,
        "_full_text": "'-09':4,9 '-29':5,10 '01':6,11 '02':13 '1467168112099':1,2 '18':12 '18h':7 '2016':3,8 '6':14",
        "passerby": 530,
        "site_id": "1467168112099",
        "_id": 418285,
        "key": "1467168112099 2016-09-29 01:18h",
        "timestamp": "2016-09-29T01:18:02"
      },
      {
        "connected": 6,
        "visitors": 49,
        "_full_text": "'-09':4,10 '-29':5,11 '01':6,12,14 '1467168112099':2,8 '19':13 '19h':7 '2016':3,9 '537':1",
        "passerby": 537,
        "site_id": "1467168112099",
        "_id": 418288,
        "key": "1467168112099 2016-09-29 01:19h",
        "timestamp": "2016-09-29T01:19:01"
      },
      {
        "connected": null,
        "visitors": 50,
        "_full_text": "'-09':3,10 '-29':4,11 '01':5,7,12 '1467168112099':1,8 '20':6 '2016':2,9 '20h':13 '50':14",
        "passerby": 548,
        "site_id": "1467168112099",
        "_id": 418291,
        "key": "1467168112099 2016-09-29 01:20h",
        "timestamp": "2016-09-29T01:20:01"
      },
      {
        "connected": 6,
        "visitors": 50,
        "_full_text": "'-09':3,9 '-29':4,10 '01':5,11 '02':13 '1467168112099':1,7 '2016':2,8 '21':12 '21h':6 '6':14",
        "passerby": 563,
        "site_id": "1467168112099",
        "_id": 418293,
        "key": "1467168112099 2016-09-29 01:21h",
        "timestamp": "2016-09-29T01:21:02"
      },
      {
        "connected": 6,
        "visitors": 50,
        "_full_text": "'-09':2,10 '-29':3,11 '01':4,6,12 '1467168112099':7,8 '2016':1,9 '22':5 '22h':13 '50':14",
        "passerby": 573,
        "site_id": "1467168112099",
        "_id": 418295,
        "key": "1467168112099 2016-09-29 01:22h",
        "timestamp": "2016-09-29T01:22:01"
      },
      {
        "connected": 6,
        "visitors": 51,
        "_full_text": "'-09':4,11 '-29':5,12 '01':6,8,13 '1467168112099':2,9 '2016':3,10 '23':7 '23h':14 '6':1",
        "passerby": 580,
        "site_id": "1467168112099",
        "_id": 418298,
        "key": "1467168112099 2016-09-29 01:23h",
        "timestamp": "2016-09-29T01:23:01"
      },
      {
        "connected": 6,
        "visitors": 51,
        "_full_text": "'-09':2,9 '-29':3,10 '01':4,6,11 '1467168112099':7,14 '2016':1,8 '24':5 '24h':12 '592':13",
        "passerby": 592,
        "site_id": "1467168112099",
        "_id": 418301,
        "key": "1467168112099 2016-09-29 01:24h",
        "timestamp": "2016-09-29T01:24:01"
      },
      {
        "connected": 6,
        "visitors": 52,
        "_full_text": "'-09':5,10 '-29':6,11 '01':7,12,14 '1467168112099':1,3 '2016':4,9 '25':13 '25h':8 '6':2",
        "passerby": 599,
        "site_id": "1467168112099",
        "_id": 418302,
        "key": "1467168112099 2016-09-29 01:25h",
        "timestamp": "2016-09-29T01:25:01"
      },
      {
        "connected": 6,
        "visitors": 52,
        "_full_text": "'-09':3,10 '-29':4,11 '01':5,12,14 '1467168112099':1,8 '2016':2,9 '26':13 '26h':6 '613':7",
        "passerby": 613,
        "site_id": "1467168112099",
        "_id": 418304,
        "key": "1467168112099 2016-09-29 01:26h",
        "timestamp": "2016-09-29T01:26:01"
      },
      {
        "connected": 6,
        "visitors": 52,
        "_full_text": "'-09':5,10 '-29':6,11 '01':7,12,14 '1467168112099':2,3 '2016':4,9 '27':13 '27h':8 '52':1",
        "passerby": 624,
        "site_id": "1467168112099",
        "_id": 418307,
        "key": "1467168112099 2016-09-29 01:27h",
        "timestamp": "2016-09-29T01:27:01"
      },
      {
        "connected": 6,
        "visitors": 52,
        "_full_text": "'-09':3,10 '-29':4,11 '01':5,7,12 '1467168112099':1,8 '2016':2,9 '28':6 '28h':13 '52':14",
        "passerby": 636,
        "site_id": "1467168112099",
        "_id": 418308,
        "key": "1467168112099 2016-09-29 01:28h",
        "timestamp": "2016-09-29T01:28:01"
      },
      {
        "connected": 6,
        "visitors": 52,
        "_full_text": "'-09':3,9 '-29':4,10 '01':5,11 '02':13 '1467168112099':1,7 '2016':2,8 '29':12 '29h':6 '52':14",
        "passerby": 643,
        "site_id": "1467168112099",
        "_id": 418310,
        "key": "1467168112099 2016-09-29 01:29h",
        "timestamp": "2016-09-29T01:29:02"
      },
      {
        "connected": 6,
        "visitors": 52,
        "_full_text": "'-09':4,11 '-29':5,12 '01':6,13 '02':8 '1467168112099':1,9 '2016':3,10 '30':7 '30h':14 '52':2",
        "passerby": 654,
        "site_id": "1467168112099",
        "_id": 418312,
        "key": "1467168112099 2016-09-29 01:30h",
        "timestamp": "2016-09-29T01:30:02"
      },
      {
        "connected": 6,
        "visitors": 52,
        "_full_text": "'-09':2,10 '-29':3,11 '01':4,6,12 '1467168112099':7,8 '2016':1,9 '31':5 '31h':13 '6':14",
        "passerby": 664,
        "site_id": "1467168112099",
        "_id": 418315,
        "key": "1467168112099 2016-09-29 01:31h",
        "timestamp": "2016-09-29T01:31:01"
      },
      {
        "connected": 6,
        "visitors": 52,
        "_full_text": "'-09':3,9 '-29':4,10 '01':5,11,13 '1467168112099':1,7 '2016':2,8 '32':12 '32h':6 '52':14",
        "passerby": 668,
        "site_id": "1467168112099",
        "_id": 418317,
        "key": "1467168112099 2016-09-29 01:32h",
        "timestamp": "2016-09-29T01:32:01"
      },
      {
        "connected": 6,
        "visitors": 52,
        "_full_text": "'-09':2,10 '-29':3,11 '01':4,12 '02':6 '1467168112099':7,8 '2016':1,9 '33':5 '33h':13 '6':14",
        "passerby": 676,
        "site_id": "1467168112099",
        "_id": 418318,
        "key": "1467168112099 2016-09-29 01:33h",
        "timestamp": "2016-09-29T01:33:02"
      },
      {
        "connected": 6,
        "visitors": 52,
        "_full_text": "'-09':4,10 '-29':5,11 '01':6,12,14 '1467168112099':1,2 '2016':3,9 '34':13 '34h':7 '680':8",
        "passerby": 680,
        "site_id": "1467168112099",
        "_id": 418320,
        "key": "1467168112099 2016-09-29 01:34h",
        "timestamp": "2016-09-29T01:34:01"
      },
      {
        "connected": 6,
        "visitors": 52,
        "_full_text": "'-09':3,9 '-29':4,10 '01':5,11 '02':13 '1467168112099':1,7 '2016':2,8 '35':12 '35h':6 '687':14",
        "passerby": 687,
        "site_id": "1467168112099",
        "_id": 418322,
        "key": "1467168112099 2016-09-29 01:35h",
        "timestamp": "2016-09-29T01:35:02"
      },
      {
        "connected": 6,
        "visitors": 52,
        "_full_text": "'-09':2,10 '-29':3,11 '01':4,6,12 '1467168112099':7,8 '2016':1,9 '36':5 '36h':13 '6':14",
        "passerby": 693,
        "site_id": "1467168112099",
        "_id": 418325,
        "key": "1467168112099 2016-09-29 01:36h",
        "timestamp": "2016-09-29T01:36:01"
      },
      {
        "connected": 6,
        "visitors": 52,
        "_full_text": "'-09':3,9 '-29':4,10 '01':5,11,13 '1467168112099':1,7 '2016':2,8 '37':12 '37h':6 '6':14",
        "passerby": 701,
        "site_id": "1467168112099",
        "_id": 418326,
        "key": "1467168112099 2016-09-29 01:37h",
        "timestamp": "2016-09-29T01:37:01"
      },
      {
        "connected": 6,
        "visitors": 53,
        "_full_text": "'-09':3,11 '-29':4,12 '01':5,13 '02':7 '1467168112099':1,9 '2016':2,10 '38':6 '38h':14 '53':8",
        "passerby": 707,
        "site_id": "1467168112099",
        "_id": 418329,
        "key": "1467168112099 2016-09-29 01:38h",
        "timestamp": "2016-09-29T01:38:02"
      },
      {
        "connected": 7,
        "visitors": 54,
        "_full_text": "'-09':2,10 '-29':3,11 '01':4,6,12 '1467168112099':7,8 '2016':1,9 '39':5 '39h':13 '54':14",
        "passerby": 713,
        "site_id": "1467168112099",
        "_id": 418330,
        "key": "1467168112099 2016-09-29 01:39h",
        "timestamp": "2016-09-29T01:39:01"
      },
      {
        "connected": null,
        "visitors": 54,
        "_full_text": "'-09':3,8 '-29':4,9 '01':5,10,12 '1467168112099':1,13 '2016':2,7 '40':11 '40h':6 '722':14",
        "passerby": 722,
        "site_id": "1467168112099",
        "_id": 418333,
        "key": "1467168112099 2016-09-29 01:40h",
        "timestamp": "2016-09-29T01:40:01"
      },
      {
        "connected": 7,
        "visitors": 54,
        "_full_text": "'-09':2,10 '-29':3,11 '01':4,12 '02':6 '1467168112099':7,8 '2016':1,9 '41':5 '41h':13 '733':14",
        "passerby": 733,
        "site_id": "1467168112099",
        "_id": 418336,
        "key": "1467168112099 2016-09-29 01:41h",
        "timestamp": "2016-09-29T01:41:02"
      },
      {
        "connected": 8,
        "visitors": 54,
        "_full_text": "'-09':4,10 '-29':5,11 '01':6,12,14 '1467168112099':2,8 '2016':3,9 '42':13 '42h':7 '54':1",
        "passerby": 744,
        "site_id": "1467168112099",
        "_id": 418338,
        "key": "1467168112099 2016-09-29 01:42h",
        "timestamp": "2016-09-29T01:42:01"
      },
      {
        "connected": 8,
        "visitors": 54,
        "_full_text": "'-09':3,11 '-29':4,12 '01':5,7,13 '1467168112099':1,9 '2016':2,10 '45':6 '45h':14 '809':8",
        "passerby": 809,
        "site_id": "1467168112099",
        "_id": 418344,
        "key": "1467168112099 2016-09-29 01:45h",
        "timestamp": "2016-09-29T01:45:01"
      },
      {
        "connected": 8,
        "visitors": 54,
        "_full_text": "'-09':2,10 '-29':3,11 '01':4,6,12 '1467168112099':7,8 '2016':1,9 '43':5 '43h':13 '8':14",
        "passerby": 777,
        "site_id": "1467168112099",
        "_id": 418339,
        "key": "1467168112099 2016-09-29 01:43h",
        "timestamp": "2016-09-29T01:43:01"
      },
      {
        "connected": null,
        "visitors": 54,
        "_full_text": "'-09':5,10 '-29':6,11 '01':7,12 '02':14 '1467168112099':2,3 '2016':4,9 '44':13 '44h':8 '54':1",
        "passerby": 804,
        "site_id": "1467168112099",
        "_id": 418342,
        "key": "1467168112099 2016-09-29 01:44h",
        "timestamp": "2016-09-29T01:44:02"
      },
      {
        "connected": 8,
        "visitors": 54,
        "_full_text": "'-09':4,11 '-29':5,12 '01':6,8,13 '1467168112099':2,9 '2016':3,10 '46':7 '46h':14 '8':1",
        "passerby": 812,
        "site_id": "1467168112099",
        "_id": 418347,
        "key": "1467168112099 2016-09-29 01:46h",
        "timestamp": "2016-09-29T01:46:01"
      },
      {
        "connected": 8,
        "visitors": 54,
        "_full_text": "'-09':3,9 '-29':4,10 '01':5,11,13 '1467168112099':1,7 '2016':2,8 '47':12 '47h':6 '817':14",
        "passerby": 817,
        "site_id": "1467168112099",
        "_id": 418348,
        "key": "1467168112099 2016-09-29 01:47h",
        "timestamp": "2016-09-29T01:47:01"
      },
      {
        "connected": 10,
        "visitors": 57,
        "_full_text": "'-09':3,8 '-29':4,9 '01':5,10,12 '10':14 '1467168112099':1,13 '2016':2,7 '48':11 '48h':6",
        "passerby": 823,
        "site_id": "1467168112099",
        "_id": 418350,
        "key": "1467168112099 2016-09-29 01:48h",
        "timestamp": "2016-09-29T01:48:01"
      },
      {
        "connected": null,
        "visitors": 59,
        "_full_text": "'-09':2,10 '-29':3,11 '01':4,12 '02':6 '1467168112099':7,8 '2016':1,9 '49':5 '49h':13 '59':14",
        "passerby": null,
        "site_id": "1467168112099",
        "_id": 418353,
        "key": "1467168112099 2016-09-29 01:49h",
        "timestamp": "2016-09-29T01:49:02"
      },
      {
        "connected": 0,
        "visitors": 11,
        "_full_text": "'-09':3,9 '-29':4,10 '01':5,11,13 '1467168112099':1,7 '2016':2,8 '50':12 '50h':6",
        "passerby": 48,
        "site_id": "1467168112099",
        "_id": 418357,
        "key": "1467168112099 2016-09-29 01:50h",
        "timestamp": "2016-09-29T01:50:01"
      },
      {
        "connected": 0,
        "visitors": 17,
        "_full_text": "'-09':4,11 '-29':5,12 '01':6,8,13 '109':2 '1467168112099':1,9 '2016':3,10 '51':7 '51h':14",
        "passerby": 109,
        "site_id": "1467168112099",
        "_id": 418358,
        "key": "1467168112099 2016-09-29 01:51h",
        "timestamp": "2016-09-29T01:51:01"
      },
      {
        "connected": 0,
        "visitors": 20,
        "_full_text": "'-09':2,10 '-29':3,11 '01':4,12 '02':6 '1467168112099':7,8 '2016':1,9 '52':5 '52h':13",
        "passerby": 140,
        "site_id": "1467168112099",
        "_id": 418360,
        "key": "1467168112099 2016-09-29 01:52h",
        "timestamp": "2016-09-29T01:52:02"
      },
      {
        "connected": 0,
        "visitors": 22,
        "_full_text": "'-09':2,10 '-29':3,11 '01':4,6,12 '1467168112099':7,8 '2016':1,9 '22':14 '53':5 '53h':13",
        "passerby": 158,
        "site_id": "1467168112099",
        "_id": 418362,
        "key": "1467168112099 2016-09-29 01:53h",
        "timestamp": "2016-09-29T01:53:01"
      },
      {
        "connected": 1,
        "visitors": 24,
        "_full_text": "'-09':5,10 '-29':6,11 '01':7,12,14 '1467168112099':2,3 '183':1 '2016':4,9 '54':13 '54h':8",
        "passerby": 183,
        "site_id": "1467168112099",
        "_id": 418365,
        "key": "1467168112099 2016-09-29 01:54h",
        "timestamp": "2016-09-29T01:54:01"
      },
      {
        "connected": 2,
        "visitors": 25,
        "_full_text": "'-09':2,9 '-29':3,10 '01':4,6,11 '1467168112099':7,13 '194':14 '2016':1,8 '55':5 '55h':12",
        "passerby": 194,
        "site_id": "1467168112099",
        "_id": 418366,
        "key": "1467168112099 2016-09-29 01:55h",
        "timestamp": "2016-09-29T01:55:01"
      },
      {
        "connected": 3,
        "visitors": 27,
        "_full_text": "'-09':4,10 '-29':5,11 '01':6,12,14 '1467168112099':1,2 '2016':3,9 '3':8 '56':13 '56h':7",
        "passerby": 213,
        "site_id": "1467168112099",
        "_id": 418368,
        "key": "1467168112099 2016-09-29 01:56h",
        "timestamp": "2016-09-29T01:56:01"
      },
      {
        "connected": 3,
        "visitors": 27,
        "_full_text": "'-09':3,10 '-29':4,11 '01':5,12,14 '1467168112099':1,8 '2016':2,9 '238':7 '57':13 '57h':6",
        "passerby": 238,
        "site_id": "1467168112099",
        "_id": 418370,
        "key": "1467168112099 2016-09-29 01:57h",
        "timestamp": "2016-09-29T01:57:01"
      },
      {
        "connected": 4,
        "visitors": 29,
        "_full_text": "'-09':3,9 '-29':4,10 '01':5,11 '02':13 '1467168112099':1,7 '2016':2,8 '29':14 '58':12 '58h':6",
        "passerby": 255,
        "site_id": "1467168112099",
        "_id": 418372,
        "key": "1467168112099 2016-09-29 01:58h",
        "timestamp": "2016-09-29T01:58:02"
      },
      {
        "connected": 4,
        "visitors": 30,
        "_full_text": "'-09':4,11 '-29':5,12 '01':6,8,13 '1467168112099':1,9 '2016':3,10 '30':2 '59':7 '59h':14",
        "passerby": 277,
        "site_id": "1467168112099",
        "_id": 418376,
        "key": "1467168112099 2016-09-29 01:59h",
        "timestamp": "2016-09-29T01:59:01"
      },
      {
        "connected": 4,
        "visitors": 31,
        "_full_text": "'-09':2,10 '-29':3,11 '00':5 '00h':13 '02':4,6,12 '1467168112099':7,8 '2016':1,9 '4':14",
        "passerby": 288,
        "site_id": "1467168112099",
        "_id": 418377,
        "key": "1467168112099 2016-09-29 02:00h",
        "timestamp": "2016-09-29T02:00:02"
      },
      {
        "connected": 4,
        "visitors": 32,
        "_full_text": "'-09':3,9 '-29':4,10 '01':12 '01h':6 '02':5,11,13 '1467168112099':1,7 '2016':2,8 '4':14",
        "passerby": null,
        "site_id": "1467168112099",
        "_id": 418379,
        "key": "1467168112099 2016-09-29 02:01h",
        "timestamp": "2016-09-29T02:01:02"
      },
      {
        "connected": 4,
        "visitors": 33,
        "_full_text": "'-09':2,10 '-29':3,11 '01':6 '02':4,5,12 '02h':13 '1467168112099':7,8 '2016':1,9 '4':14",
        "passerby": 319,
        "site_id": "1467168112099",
        "_id": 418382,
        "key": "1467168112099 2016-09-29 02:02h",
        "timestamp": "2016-09-29T02:02:01"
      },
      {
        "connected": 5,
        "visitors": 34,
        "_full_text": "'-09':3,10 '-29':4,11 '01':14 '02':5,12 '03':13 '03h':6 '1467168112099':1,8 '2016':2,9 '5':7",
        "passerby": 328,
        "site_id": "1467168112099",
        "_id": 418383,
        "key": "1467168112099 2016-09-29 02:03h",
        "timestamp": "2016-09-29T02:03:01"
      },
      {
        "connected": null,
        "visitors": 35,
        "_full_text": "'-09':3,11 '-29':4,12 '02':5,7,13 '04':6 '04h':14 '1467168112099':1,9 '2016':2,10 '35':8",
        "passerby": 336,
        "site_id": "1467168112099",
        "_id": 418386,
        "key": "1467168112099 2016-09-29 02:04h",
        "timestamp": "2016-09-29T02:04:02"
      },
      {
        "connected": 5,
        "visitors": 36,
        "_full_text": "'-09':2,11 '-29':3,12 '01':6 '02':4,13 '05':5 '05h':14 '1467168112099':7,9 '2016':1,10 '5':8",
        "passerby": 347,
        "site_id": "1467168112099",
        "_id": 418388,
        "key": "1467168112099 2016-09-29 02:05h",
        "timestamp": "2016-09-29T02:05:01"
      },
      {
        "connected": 6,
        "visitors": 36,
        "_full_text": "'-09':3,9 '-29':4,10 '01':13 '02':5,11 '06':12 '06h':6 '1467168112099':1,7 '2016':2,8 '36':14",
        "passerby": 357,
        "site_id": "1467168112099",
        "_id": 418391,
        "key": "1467168112099 2016-09-29 02:06h",
        "timestamp": "2016-09-29T02:06:01"
      },
      {
        "connected": 6,
        "visitors": 36,
        "_full_text": "'-09':3,10 '-29':4,11 '01':7 '02':5,12 '07':6 '07h':13 '1467168112099':1,8 '2016':2,9 '36':14",
        "passerby": 368,
        "site_id": "1467168112099",
        "_id": 418392,
        "key": "1467168112099 2016-09-29 02:07h",
        "timestamp": "2016-09-29T02:07:01"
      },
      {
        "connected": 6,
        "visitors": 36,
        "_full_text": "'-09':2,10 '-29':3,11 '01':6 '02':4,12 '08':5 '08h':13 '1467168112099':7,8 '2016':1,9 '36':14",
        "passerby": null,
        "site_id": "1467168112099",
        "_id": 418394,
        "key": "1467168112099 2016-09-29 02:08h",
        "timestamp": "2016-09-29T02:08:01"
      },
      {
        "connected": 6,
        "visitors": 36,
        "_full_text": "'-09':3,8 '-29':4,9 '01':12 '02':5,10 '09':11 '09h':6 '1467168112099':1,13 '2016':2,7 '6':14",
        "passerby": null,
        "site_id": "1467168112099",
        "_id": 418397,
        "key": "1467168112099 2016-09-29 02:09h",
        "timestamp": "2016-09-29T02:09:01"
      },
      {
        "connected": 6,
        "visitors": 36,
        "_full_text": "'-09':2,9 '-29':3,10 '02':4,6,11 '10':5 '10h':12 '1467168112099':7,13 '2016':1,8 '394':14",
        "passerby": 394,
        "site_id": "1467168112099",
        "_id": 418399,
        "key": "1467168112099 2016-09-29 02:10h",
        "timestamp": "2016-09-29T02:10:02"
      },
      {
        "connected": 6,
        "visitors": 36,
        "_full_text": "'-09':5,10 '-29':6,11 '01':14 '02':7,12 '11':13 '11h':8 '1467168112099':1,3 '2016':4,9 '6':2",
        "passerby": 403,
        "site_id": "1467168112099",
        "_id": 418402,
        "key": "1467168112099 2016-09-29 02:11h",
        "timestamp": "2016-09-29T02:11:01"
      },
      {
        "connected": 6,
        "visitors": 36,
        "_full_text": "'-09':3,9 '-29':4,10 '01':13 '02':5,11 '12':12 '12h':6 '1467168112099':1,7 '2016':2,8 '36':14",
        "passerby": 411,
        "site_id": "1467168112099",
        "_id": 418405,
        "key": "1467168112099 2016-09-29 02:12h",
        "timestamp": "2016-09-29T02:12:01"
      },
      {
        "connected": 6,
        "visitors": 36,
        "_full_text": "'-09':4,10 '-29':5,11 '01':14 '02':6,12 '13':13 '13h':7 '1467168112099':1,2 '2016':3,9 '36':8",
        "passerby": 420,
        "site_id": "1467168112099",
        "_id": 418407,
        "key": "1467168112099 2016-09-29 02:13h",
        "timestamp": "2016-09-29T02:13:01"
      },
      {
        "connected": 6,
        "visitors": 37,
        "_full_text": "'-09':4,11 '-29':5,12 '01':8 '02':6,13 '14':7 '1467168112099':2,9 '14h':14 '2016':3,10 '430':1",
        "passerby": 430,
        "site_id": "1467168112099",
        "_id": 418409,
        "key": "1467168112099 2016-09-29 02:14h",
        "timestamp": "2016-09-29T02:14:01"
      },
      {
        "connected": 6,
        "visitors": 37,
        "_full_text": "'-09':3,10 '-29':4,11 '02':5,12,14 '1467168112099':1,7 '15':13 '15h':6 '2016':2,9 '37':8",
        "passerby": 440,
        "site_id": "1467168112099",
        "_id": 418412,
        "key": "1467168112099 2016-09-29 02:15h",
        "timestamp": "2016-09-29T02:15:02"
      },
      {
        "connected": 6,
        "visitors": 37,
        "_full_text": "'-09':2,10 '-29':3,11 '01':6 '02':4,12 '1467168112099':7,8 '16':5 '16h':13 '2016':1,9 '6':14",
        "passerby": 453,
        "site_id": "1467168112099",
        "_id": 418413,
        "key": "1467168112099 2016-09-29 02:16h",
        "timestamp": "2016-09-29T02:16:01"
      },
      {
        "connected": 6,
        "visitors": 38,
        "_full_text": "'-09':4,11 '-29':5,12 '01':8 '02':6,13 '1467168112099':2,9 '17':7 '17h':14 '2016':3,10 '6':1",
        "passerby": 460,
        "site_id": "1467168112099",
        "_id": 418415,
        "key": "1467168112099 2016-09-29 02:17h",
        "timestamp": "2016-09-29T02:17:01"
      },
      {
        "connected": 6,
        "visitors": 38,
        "_full_text": "'-09':2,9 '-29':3,10 '02':4,6,11 '1467168112099':7,13 '18':5 '18h':12 '2016':1,8 '6':14",
        "passerby": 468,
        "site_id": "1467168112099",
        "_id": 418418,
        "key": "1467168112099 2016-09-29 02:18h",
        "timestamp": "2016-09-29T02:18:02"
      },
      {
        "connected": 6,
        "visitors": 39,
        "_full_text": "'-09':5,10 '-29':6,11 '01':14 '02':7,12 '1467168112099':2,3 '19':13 '19h':8 '2016':4,9 '39':1",
        "passerby": 472,
        "site_id": "1467168112099",
        "_id": 418420,
        "key": "1467168112099 2016-09-29 02:19h",
        "timestamp": "2016-09-29T02:19:01"
      },
      {
        "connected": 6,
        "visitors": 39,
        "_full_text": "'-09':3,10 '-29':4,11 '02':5,12,14 '1467168112099':1,7 '20':13 '2016':2,9 '20h':6 '39':8",
        "passerby": 486,
        "site_id": "1467168112099",
        "_id": 418421,
        "key": "1467168112099 2016-09-29 02:20h",
        "timestamp": "2016-09-29T02:20:02"
      },
      {
        "connected": 6,
        "visitors": 40,
        "_full_text": "'-09':3,10 '-29':4,11 '01':7 '02':5,12 '1467168112099':1,8 '2016':2,9 '21':6 '21h':13 '6':14",
        "passerby": null,
        "site_id": "1467168112099",
        "_id": 418423,
        "key": "1467168112099 2016-09-29 02:21h",
        "timestamp": "2016-09-29T02:21:01"
      },
      {
        "connected": 6,
        "visitors": 40,
        "_full_text": "'-09':3,11 '-29':4,12 '01':7 '02':5,13 '1467168112099':1,9 '2016':2,10 '22':6 '22h':14 '40':8",
        "passerby": 500,
        "site_id": "1467168112099",
        "_id": 418427,
        "key": "1467168112099 2016-09-29 02:22h",
        "timestamp": "2016-09-29T02:22:01"
      },
      {
        "connected": null,
        "visitors": 40,
        "_full_text": "'-09':3,10 '-29':4,11 '02':5,7,12 '1467168112099':1,8 '2016':2,9 '23':6 '23h':13 '40':14",
        "passerby": null,
        "site_id": "1467168112099",
        "_id": 418430,
        "key": "1467168112099 2016-09-29 02:23h",
        "timestamp": "2016-09-29T02:23:02"
      },
      {
        "connected": 6,
        "visitors": 40,
        "_full_text": "'-09':5,10 '-29':6,11 '01':14 '02':7,12 '1467168112099':1,3 '2016':4,9 '24':13 '24h':8 '516':2",
        "passerby": 516,
        "site_id": "1467168112099",
        "_id": 418434,
        "key": "1467168112099 2016-09-29 02:24h",
        "timestamp": "2016-09-29T02:24:01"
      },
      {
        "connected": 6,
        "visitors": 40,
        "_full_text": "'-09':2,9 '-29':3,10 '02':4,6,11 '1467168112099':7,13 '2016':1,8 '25':5 '25h':12 '40':14",
        "passerby": 520,
        "site_id": "1467168112099",
        "_id": 418436,
        "key": "1467168112099 2016-09-29 02:25h",
        "timestamp": "2016-09-29T02:25:02"
      },
      {
        "connected": 6,
        "visitors": 40,
        "_full_text": "'-09':4,10 '-29':5,11 '01':14 '02':6,12 '1467168112099':1,2 '2016':3,9 '26':13 '26h':7 '40':8",
        "passerby": 523,
        "site_id": "1467168112099",
        "_id": 418438,
        "key": "1467168112099 2016-09-29 02:26h",
        "timestamp": "2016-09-29T02:26:01"
      },
      {
        "connected": 6,
        "visitors": 40,
        "_full_text": "'-09':3,9 '-29':4,10 '01':13 '02':5,11 '1467168112099':1,7 '2016':2,8 '27':12 '27h':6 '538':14",
        "passerby": 538,
        "site_id": "1467168112099",
        "_id": 418440,
        "key": "1467168112099 2016-09-29 02:27h",
        "timestamp": "2016-09-29T02:27:01"
      },
      {
        "connected": 6,
        "visitors": 40,
        "_full_text": "'-09':3,10 '-29':4,11 '01':14 '02':5,12 '1467168112099':1,7 '2016':2,9 '28':13 '28h':6 '40':8",
        "passerby": 551,
        "site_id": "1467168112099",
        "_id": 418441,
        "key": "1467168112099 2016-09-29 02:28h",
        "timestamp": "2016-09-29T02:28:01"
      },
      {
        "connected": null,
        "visitors": 40,
        "_full_text": "'-09':3,10 '-29':4,11 '01':7 '02':5,12 '1467168112099':1,8 '2016':2,9 '29':6 '29h':13 '557':14",
        "passerby": 557,
        "site_id": "1467168112099",
        "_id": 418444,
        "key": "1467168112099 2016-09-29 02:29h",
        "timestamp": "2016-09-29T02:29:01"
      },
      {
        "connected": 7,
        "visitors": 41,
        "_full_text": "'-09':3,9 '-29':4,10 '02':5,11,13 '1467168112099':1,7 '2016':2,8 '30':12 '30h':6 '7':14",
        "passerby": 564,
        "site_id": "1467168112099",
        "_id": 418446,
        "key": "1467168112099 2016-09-29 02:30h",
        "timestamp": "2016-09-29T02:30:02"
      },
      {
        "connected": 7,
        "visitors": 41,
        "_full_text": "'-09':2,10 '-29':3,11 '01':6 '02':4,12 '1467168112099':7,8 '2016':1,9 '31':5 '31h':13 '571':14",
        "passerby": 571,
        "site_id": "1467168112099",
        "_id": 418449,
        "key": "1467168112099 2016-09-29 02:31h",
        "timestamp": "2016-09-29T02:31:01"
      },
      {
        "connected": 7,
        "visitors": 42,
        "_full_text": "'-09':4,10 '-29':5,11 '01':14 '02':6,12 '1467168112099':2,8 '2016':3,9 '32':13 '32h':7 '575':1",
        "passerby": 575,
        "site_id": "1467168112099",
        "_id": 418450,
        "key": "1467168112099 2016-09-29 02:32h",
        "timestamp": "2016-09-29T02:32:01"
      },
      {
        "connected": 7,
        "visitors": 42,
        "_full_text": "'-09':2,11 '-29':3,12 '02':4,6,13 '1467168112099':7,9 '2016':1,10 '33':5 '33h':14 '42':8",
        "passerby": 579,
        "site_id": "1467168112099",
        "_id": 418452,
        "key": "1467168112099 2016-09-29 02:33h",
        "timestamp": "2016-09-29T02:33:02"
      },
      {
        "connected": 7,
        "visitors": 42,
        "_full_text": "'-09':2,11 '-29':3,12 '01':6 '02':4,13 '1467168112099':7,9 '2016':1,10 '34':5 '34h':14 '42':8",
        "passerby": null,
        "site_id": "1467168112099",
        "_id": 418457,
        "key": "1467168112099 2016-09-29 02:34h",
        "timestamp": "2016-09-29T02:34:01"
      },
      {
        "connected": 7,
        "visitors": 42,
        "_full_text": "'-09':4,11 '-29':5,12 '02':6,8,13 '1467168112099':2,9 '2016':3,10 '35':7 '35h':14 '590':1",
        "passerby": 590,
        "site_id": "1467168112099",
        "_id": 418459,
        "key": "1467168112099 2016-09-29 02:35h",
        "timestamp": "2016-09-29T02:35:02"
      },
      {
        "connected": 7,
        "visitors": 42,
        "_full_text": "'-09':4,11 '-29':5,12 '01':8 '02':6,13 '1467168112099':1,9 '2016':3,10 '36':7 '36h':14 '42':2",
        "passerby": null,
        "site_id": "1467168112099",
        "_id": 418462,
        "key": "1467168112099 2016-09-29 02:36h",
        "timestamp": "2016-09-29T02:36:01"
      },
      {
        "connected": null,
        "visitors": 42,
        "_full_text": "'-09':3,9 '-29':4,10 '01':13 '02':5,11 '1467168112099':1,7 '2016':2,8 '37':12 '37h':6 '604':14",
        "passerby": 604,
        "site_id": "1467168112099",
        "_id": 418464,
        "key": "1467168112099 2016-09-29 02:37h",
        "timestamp": "2016-09-29T02:37:01"
      },
      {
        "connected": 7,
        "visitors": 42,
        "_full_text": "'-09':3,9 '-29':4,10 '02':5,11,13 '1467168112099':1,7 '2016':2,8 '38':12 '38h':6 '7':14",
        "passerby": 607,
        "site_id": "1467168112099",
        "_id": 418468,
        "key": "1467168112099 2016-09-29 02:38h",
        "timestamp": "2016-09-29T02:38:02"
      },
      {
        "connected": 7,
        "visitors": null,
        "_full_text": "'-09':4,10 '-29':5,11 '01':14 '02':6,12 '1467168112099':1,2 '2016':3,9 '39':13 '39h':7 '609':8",
        "passerby": 609,
        "site_id": "1467168112099",
        "_id": 418470,
        "key": "1467168112099 2016-09-29 02:39h",
        "timestamp": "2016-09-29T02:39:01"
      },
      {
        "connected": 7,
        "visitors": 42,
        "_full_text": "'-09':3,11 '-29':4,12 '01':7 '02':5,13 '1467168112099':1,9 '2016':2,10 '40':6 '40h':14 '614':8",
        "passerby": 614,
        "site_id": "1467168112099",
        "_id": 418472,
        "key": "1467168112099 2016-09-29 02:40h",
        "timestamp": "2016-09-29T02:40:01"
      },
      {
        "connected": 8,
        "visitors": 42,
        "_full_text": "'-09':2,11 '-29':3,12 '01':6 '02':4,13 '1467168112099':7,9 '2016':1,10 '41':5 '41h':14 '42':8",
        "passerby": 622,
        "site_id": "1467168112099",
        "_id": 418474,
        "key": "1467168112099 2016-09-29 02:41h",
        "timestamp": "2016-09-29T02:41:01"
      },
      {
        "connected": 8,
        "visitors": 43,
        "_full_text": "'-09':3,9 '-29':4,10 '01':13 '02':5,11 '1467168112099':1,7 '2016':2,8 '42':12 '42h':6 '631':14",
        "passerby": 631,
        "site_id": "1467168112099",
        "_id": 418477,
        "key": "1467168112099 2016-09-29 02:42h",
        "timestamp": "2016-09-29T02:42:01"
      },
      {
        "connected": null,
        "visitors": 43,
        "_full_text": "'-09':3,11 '-29':4,12 '02':5,7,13 '1467168112099':8,9 '2016':2,10 '43':6 '43h':14 '638':1",
        "passerby": 638,
        "site_id": "1467168112099",
        "_id": 418479,
        "key": "1467168112099 2016-09-29 02:43h",
        "timestamp": "2016-09-29T02:43:02"
      },
      {
        "connected": null,
        "visitors": 44,
        "_full_text": "'-09':2,10 '-29':3,11 '01':6 '02':4,12 '1467168112099':7,8 '2016':1,9 '44':5 '44h':13 '644':14",
        "passerby": 644,
        "site_id": "1467168112099",
        "_id": 418482,
        "key": "1467168112099 2016-09-29 02:44h",
        "timestamp": "2016-09-29T02:44:01"
      },
      {
        "connected": 8,
        "visitors": 44,
        "_full_text": "'-09':3,8 '-29':4,9 '01':12 '02':5,10 '1467168112099':1,13 '2016':2,7 '45':11 '45h':6 '8':14",
        "passerby": 646,
        "site_id": "1467168112099",
        "_id": 418485,
        "key": "1467168112099 2016-09-29 02:45h",
        "timestamp": "2016-09-29T02:45:01"
      },
      {
        "connected": 8,
        "visitors": 44,
        "_full_text": "'-09':2,10 '-29':3,11 '01':6 '02':4,12 '1467168112099':7,8 '2016':1,9 '46':5 '46h':13 '8':14",
        "passerby": 648,
        "site_id": "1467168112099",
        "_id": 418486,
        "key": "1467168112099 2016-09-29 02:46h",
        "timestamp": "2016-09-29T02:46:01"
      },
      {
        "connected": 8,
        "visitors": 44,
        "_full_text": "'-09':3,9 '-29':4,10 '01':13 '02':5,11 '1467168112099':1,7 '2016':2,8 '47':12 '47h':6 '651':14",
        "passerby": 651,
        "site_id": "1467168112099",
        "_id": 418488,
        "key": "1467168112099 2016-09-29 02:47h",
        "timestamp": "2016-09-29T02:47:01"
      },
      {
        "connected": 8,
        "visitors": 44,
        "_full_text": "'-09':3,11 '-29':4,12 '01':7 '02':5,13 '1467168112099':1,9 '2016':2,10 '48':6 '48h':14 '658':8",
        "passerby": 658,
        "site_id": "1467168112099",
        "_id": 418492,
        "key": "1467168112099 2016-09-29 02:48h",
        "timestamp": "2016-09-29T02:48:01"
      },
      {
        "connected": 8,
        "visitors": 44,
        "_full_text": "'-09':5,10 '-29':6,11 '02':7,12,14 '1467168112099':2,3 '2016':4,9 '49':13 '49h':8 '667':1",
        "passerby": 667,
        "site_id": "1467168112099",
        "_id": 418493,
        "key": "1467168112099 2016-09-29 02:49h",
        "timestamp": "2016-09-29T02:49:02"
      },
      {
        "connected": 0,
        "visitors": 12,
        "_full_text": "'-09':4,11 '-29':5,12 '01':8 '02':6,13 '12':2 '1467168112099':1,9 '2016':3,10 '50':7 '50h':14",
        "passerby": 68,
        "site_id": "1467168112099",
        "_id": 418496,
        "key": "1467168112099 2016-09-29 02:50h",
        "timestamp": "2016-09-29T02:50:01"
      },
      {
        "connected": 0,
        "visitors": 20,
        "_full_text": "'-09':3,10 '-29':4,11 '02':5,12,14 '1467168112099':1,7 '20':8 '2016':2,9 '51':13 '51h':6",
        "passerby": 127,
        "site_id": "1467168112099",
        "_id": 418498,
        "key": "1467168112099 2016-09-29 02:51h",
        "timestamp": "2016-09-29T02:51:02"
      },
      {
        "connected": 0,
        "visitors": 22,
        "_full_text": "'-09':2,10 '-29':3,11 '01':6 '02':4,12 '1467168112099':7,8 '2016':1,9 '52':5 '52h':13",
        "passerby": 155,
        "site_id": "1467168112099",
        "_id": 418500,
        "key": "1467168112099 2016-09-29 02:52h",
        "timestamp": "2016-09-29T02:52:01"
      },
      {
        "connected": 0,
        "visitors": 24,
        "_full_text": "'-09':4,11 '-29':5,12 '01':8 '02':6,13 '1467168112099':2,9 '2016':3,10 '24':1 '53':7 '53h':14",
        "passerby": 176,
        "site_id": "1467168112099",
        "_id": 418501,
        "key": "1467168112099 2016-09-29 02:53h",
        "timestamp": "2016-09-29T02:53:01"
      },
      {
        "connected": null,
        "visitors": 27,
        "_full_text": "'-09':4,9 '-29':5,10 '01':13 '02':6,11 '1467168112099':2,14 '2016':3,8 '27':1 '54':12 '54h':7",
        "passerby": 190,
        "site_id": "1467168112099",
        "_id": 418504,
        "key": "1467168112099 2016-09-29 02:54h",
        "timestamp": "2016-09-29T02:54:01"
      },
      {
        "connected": 1,
        "visitors": 27,
        "_full_text": "'-09':4,10 '-29':5,11 '01':14 '02':6,12 '1467168112099':1,2 '2016':3,9 '214':8 '55':13 '55h':7",
        "passerby": 214,
        "site_id": "1467168112099",
        "_id": 418506,
        "key": "1467168112099 2016-09-29 02:55h",
        "timestamp": "2016-09-29T02:55:01"
      },
      {
        "connected": 1,
        "visitors": 28,
        "_full_text": "'-09':3,10 '-29':4,11 '02':5,12,14 '1':7 '1467168112099':1,8 '2016':2,9 '56':13 '56h':6",
        "passerby": null,
        "site_id": "1467168112099",
        "_id": 418511,
        "key": "1467168112099 2016-09-29 02:56h",
        "timestamp": "2016-09-29T02:56:02"
      },
      {
        "connected": 1,
        "visitors": 28,
        "_full_text": "'-09':4,10 '-29':5,11 '01':14 '02':6,12 '1467168112099':1,2 '2016':3,9 '28':8 '57':13 '57h':7",
        "passerby": 238,
        "site_id": "1467168112099",
        "_id": 418514,
        "key": "1467168112099 2016-09-29 02:57h",
        "timestamp": "2016-09-29T02:57:01"
      },
      {
        "connected": 1,
        "visitors": 29,
        "_full_text": "'-09':4,11 '-29':5,12 '01':8 '02':6,13 '1':1 '1467168112099':2,9 '2016':3,10 '58':7 '58h':14",
        "passerby": 252,
        "site_id": "1467168112099",
        "_id": 418516,
        "key": "1467168112099 2016-09-29 02:58h",
        "timestamp": "2016-09-29T02:58:01"
      },
      {
        "connected": 1,
        "visitors": 30,
        "_full_text": "'-09':4,10 '-29':5,11 '01':14 '02':6,12 '1467168112099':2,8 '2016':3,9 '263':1 '59':13 '59h':7",
        "passerby": 263,
        "site_id": "1467168112099",
        "_id": 418517,
        "key": "1467168112099 2016-09-29 02:59h",
        "timestamp": "2016-09-29T02:59:01"
      },
      {
        "connected": null,
        "visitors": 30,
        "_full_text": "'-09':4,11 '-29':5,12 '00':7 '00h':14 '01':8 '03':6,13 '1467168112099':1,9 '2016':3,10 '269':2",
        "passerby": 269,
        "site_id": "1467168112099",
        "_id": 418521,
        "key": "1467168112099 2016-09-29 03:00h",
        "timestamp": "2016-09-29T03:00:01"
      },
      {
        "connected": 2,
        "visitors": 31,
        "_full_text": "'-09':3,9 '-29':4,10 '01':12 '01h':6 '02':13 '03':5,11 '1467168112099':1,7 '2016':2,8 '275':14",
        "passerby": 275,
        "site_id": "1467168112099",
        "_id": 418523,
        "key": "1467168112099 2016-09-29 03:01h",
        "timestamp": "2016-09-29T03:01:02"
      },
      {
        "connected": 2,
        "visitors": 31,
        "_full_text": "'-09':2,10 '-29':3,11 '01':6 '02':5 '02h':13 '03':4,12 '1467168112099':7,8 '2016':1,9 '286':14",
        "passerby": 286,
        "site_id": "1467168112099",
        "_id": 418525,
        "key": "1467168112099 2016-09-29 03:02h",
        "timestamp": "2016-09-29T03:02:01"
      },
      {
        "connected": 3,
        "visitors": 33,
        "_full_text": "'-09':3,11 '-29':4,12 '01':7 '03':5,6,13 '03h':14 '1467168112099':1,9 '2016':2,10 '3':8",
        "passerby": 292,
        "site_id": "1467168112099",
        "_id": 418528,
        "key": "1467168112099 2016-09-29 03:03h",
        "timestamp": "2016-09-29T03:03:01"
      },
      {
        "connected": 3,
        "visitors": 34,
        "_full_text": "'-09':2,9 '-29':3,10 '01':6 '03':4,11 '04':5 '04h':12 '1467168112099':7,13 '2016':1,8 '34':14",
        "passerby": 298,
        "site_id": "1467168112099",
        "_id": 418530,
        "key": "1467168112099 2016-09-29 03:04h",
        "timestamp": "2016-09-29T03:04:01"
      },
      {
        "connected": 3,
        "visitors": null,
        "_full_text": "'-09':5,10 '-29':6,11 '01':14 '03':7,12 '05':13 '05h':8 '1467168112099':1,3 '2016':4,9 '3':2",
        "passerby": 308,
        "site_id": "1467168112099",
        "_id": 418532,
        "key": "1467168112099 2016-09-29 03:05h",
        "timestamp": "2016-09-29T03:05:01"
      },
      {
        "connected": 4,
        "visitors": 35,
        "_full_text": "'-09':3,10 '-29':4,11 '02':14 '03':5,12 '06':13 '06h':6 '1467168112099':1,8 '2016':2,9 '323':7",
        "passerby": 323,
        "site_id": "1467168112099",
        "_id": 418536,
        "key": "1467168112099 2016-09-29 03:06h",
        "timestamp": "2016-09-29T03:06:02"
      },
      {
        "connected": 4,
        "visitors": 35,
        "_full_text": "'-09':4,10 '-29':5,11 '01':14 '03':6,12 '07':13 '07h':7 '1467168112099':1,2 '2016':3,9 '35':8",
        "passerby": 334,
        "site_id": "1467168112099",
        "_id": 418537,
        "key": "1467168112099 2016-09-29 03:07h",
        "timestamp": "2016-09-29T03:07:01"
      },
      {
        "connected": 4,
        "visitors": 35,
        "_full_text": "'-09':4,11 '-29':5,12 '01':8 '03':6,13 '08':7 '08h':14 '1467168112099':2,9 '2016':3,10 '344':1",
        "passerby": 344,
        "site_id": "1467168112099",
        "_id": 418539,
        "key": "1467168112099 2016-09-29 03:08h",
        "timestamp": "2016-09-29T03:08:01"
      },
      {
        "connected": 4,
        "visitors": 35,
        "_full_text": "'-09':3,9 '-29':4,10 '02':13 '03':5,11 '09':12 '09h':6 '1467168112099':1,7 '2016':2,8 '35':14",
        "passerby": 352,
        "site_id": "1467168112099",
        "_id": 418541,
        "key": "1467168112099 2016-09-29 03:09h",
        "timestamp": "2016-09-29T03:09:02"
      },
      {
        "connected": 4,
        "visitors": 35,
        "_full_text": "'-09':3,11 '-29':4,12 '01':7 '03':5,13 '10':6 '10h':14 '1467168112099':1,9 '2016':2,10 '35':8",
        "passerby": 355,
        "site_id": "1467168112099",
        "_id": 418543,
        "key": "1467168112099 2016-09-29 03:10h",
        "timestamp": "2016-09-29T03:10:01"
      },
      {
        "connected": 5,
        "visitors": 36,
        "_full_text": "'-09':2,10 '-29':3,11 '01':6 '03':4,12 '11':5 '11h':13 '1467168112099':7,8 '2016':1,9 '361':14",
        "passerby": 361,
        "site_id": "1467168112099",
        "_id": 418545,
        "key": "1467168112099 2016-09-29 03:11h",
        "timestamp": "2016-09-29T03:11:01"
      },
      {
        "connected": null,
        "visitors": 37,
        "_full_text": "'-09':3,9 '-29':4,10 '01':13 '03':5,11 '12':12 '12h':6 '1467168112099':1,7 '2016':2,8 '368':14",
        "passerby": 368,
        "site_id": "1467168112099",
        "_id": 418547,
        "key": "1467168112099 2016-09-29 03:12h",
        "timestamp": "2016-09-29T03:12:01"
      },
      {
        "connected": 5,
        "visitors": null,
        "_full_text": "'-09':2,10 '-29':3,11 '02':6 '03':4,12 '13':5 '13h':13 '1467168112099':7,8 '2016':1,9 '370':14",
        "passerby": 370,
        "site_id": "1467168112099",
        "_id": 418551,
        "key": "1467168112099 2016-09-29 03:13h",
        "timestamp": "2016-09-29T03:13:02"
      },
      {
        "connected": 5,
        "visitors": 38,
        "_full_text": "'-09':4,9 '-29':5,10 '01':13 '03':6,11 '14':12 '1467168112099':1,2 '14h':7 '2016':3,8 '377':14",
        "passerby": 377,
        "site_id": "1467168112099",
        "_id": 418553,
        "key": "1467168112099 2016-09-29 03:14h",
        "timestamp": "2016-09-29T03:14:01"
      },
      {
        "connected": 5,
        "visitors": 38,
        "_full_text": "'-09':3,8 '-29':4,9 '01':12 '03':5,10 '1467168112099':1,13 '15':11 '15h':6 '2016':2,7 '38':14",
        "passerby": 379,
        "site_id": "1467168112099",
        "_id": 418555,
        "key": "1467168112099 2016-09-29 03:15h",
        "timestamp": "2016-09-29T03:15:01"
      },
      {
        "connected": null,
        "visitors": null,
        "_full_text": "'-09':2,10 '-29':3,11 '01':6 '03':4,12 '1467168112099':7,8 '16':5 '16h':13 '2016':1,9 '387':14",
        "passerby": 387,
        "site_id": "1467168112099",
        "_id": 418559,
        "key": "1467168112099 2016-09-29 03:16h",
        "timestamp": "2016-09-29T03:16:01"
      },
      {
        "connected": 5,
        "visitors": 38,
        "_full_text": "'-09':3,10 '-29':4,11 '01':14 '03':5,12 '1467168112099':1,8 '17':13 '17h':6 '2016':2,9 '38':7",
        "passerby": 399,
        "site_id": "1467168112099",
        "_id": 418563,
        "key": "1467168112099 2016-09-29 03:17h",
        "timestamp": "2016-09-29T03:17:01"
      },
      {
        "connected": 5,
        "visitors": 38,
        "_full_text": "'-09':4,11 '-29':5,12 '02':8 '03':6,13 '1467168112099':2,9 '18':7 '18h':14 '2016':3,10 '5':1",
        "passerby": 403,
        "site_id": "1467168112099",
        "_id": 418564,
        "key": "1467168112099 2016-09-29 03:18h",
        "timestamp": "2016-09-29T03:18:02"
      },
      {
        "connected": 5,
        "visitors": 38,
        "_full_text": "'-09':2,10 '-29':3,11 '01':6 '03':4,12 '1467168112099':7,8 '19':5 '19h':13 '2016':1,9 '408':14",
        "passerby": 408,
        "site_id": "1467168112099",
        "_id": 418566,
        "key": "1467168112099 2016-09-29 03:19h",
        "timestamp": "2016-09-29T03:19:01"
      },
      {
        "connected": 5,
        "visitors": null,
        "_full_text": "'-09':2,11 '-29':3,12 '01':6 '03':4,13 '1467168112099':7,9 '20':5 '2016':1,10 '20h':14 '5':8",
        "passerby": null,
        "site_id": "1467168112099",
        "_id": 418569,
        "key": "1467168112099 2016-09-29 03:20h",
        "timestamp": "2016-09-29T03:20:01"
      },
      {
        "connected": 6,
        "visitors": 39,
        "_full_text": "'-09':3,11 '-29':4,12 '01':7 '03':5,13 '1467168112099':1,9 '2016':2,10 '21':6 '21h':14 '39':8",
        "passerby": 425,
        "site_id": "1467168112099",
        "_id": 418572,
        "key": "1467168112099 2016-09-29 03:21h",
        "timestamp": "2016-09-29T03:21:01"
      },
      {
        "connected": 6,
        "visitors": 39,
        "_full_text": "'-09':3,10 '-29':4,11 '01':7 '03':5,12 '1467168112099':1,8 '2016':2,9 '22':6 '22h':13 '6':14",
        "passerby": 433,
        "site_id": "1467168112099",
        "_id": 418574,
        "key": "1467168112099 2016-09-29 03:22h",
        "timestamp": "2016-09-29T03:22:01"
      },
      {
        "connected": 6,
        "visitors": 39,
        "_full_text": "'-09':3,9 '-29':4,10 '02':13 '03':5,11 '1467168112099':1,7 '2016':2,8 '23':12 '23h':6 '6':14",
        "passerby": 435,
        "site_id": "1467168112099",
        "_id": 418577,
        "key": "1467168112099 2016-09-29 03:23h",
        "timestamp": "2016-09-29T03:23:02"
      },
      {
        "connected": null,
        "visitors": 39,
        "_full_text": "'-09':3,8 '-29':4,9 '01':12 '03':5,10 '1467168112099':1,13 '2016':2,7 '24':11 '24h':6 '442':14",
        "passerby": 442,
        "site_id": "1467168112099",
        "_id": 418579,
        "key": "1467168112099 2016-09-29 03:24h",
        "timestamp": "2016-09-29T03:24:01"
      },
      {
        "connected": 6,
        "visitors": 39,
        "_full_text": "'-09':2,10 '-29':3,11 '02':6 '03':4,12 '1467168112099':7,8 '2016':1,9 '25':5 '25h':13 '6':14",
        "passerby": 449,
        "site_id": "1467168112099",
        "_id": 418581,
        "key": "1467168112099 2016-09-29 03:25h",
        "timestamp": "2016-09-29T03:25:02"
      },
      {
        "connected": 6,
        "visitors": 39,
        "_full_text": "'-09':3,9 '-29':4,10 '01':13 '03':5,11 '1467168112099':1,7 '2016':2,8 '26':12 '26h':6 '6':14",
        "passerby": 456,
        "site_id": "1467168112099",
        "_id": 418583,
        "key": "1467168112099 2016-09-29 03:26h",
        "timestamp": "2016-09-29T03:26:01"
      },
      {
        "connected": 7,
        "visitors": 40,
        "_full_text": "'-09':2,10 '-29':3,11 '01':6 '03':4,12 '1467168112099':7,8 '2016':1,9 '27':5 '27h':13 '40':14",
        "passerby": 461,
        "site_id": "1467168112099",
        "_id": 418585,
        "key": "1467168112099 2016-09-29 03:27h",
        "timestamp": "2016-09-29T03:27:01"
      },
      {
        "connected": 7,
        "visitors": 41,
        "_full_text": "'-09':2,10 '-29':3,11 '01':6 '03':4,12 '1467168112099':7,8 '2016':1,9 '28':5 '28h':13 '470':14",
        "passerby": 470,
        "site_id": "1467168112099",
        "_id": 418587,
        "key": "1467168112099 2016-09-29 03:28h",
        "timestamp": "2016-09-29T03:28:01"
      },
      {
        "connected": 7,
        "visitors": 41,
        "_full_text": "'-09':3,11 '-29':4,12 '01':7 '03':5,13 '1467168112099':1,9 '2016':2,10 '29':6 '29h':14 '7':8",
        "passerby": 475,
        "site_id": "1467168112099",
        "_id": 418589,
        "key": "1467168112099 2016-09-29 03:29h",
        "timestamp": "2016-09-29T03:29:01"
      },
      {
        "connected": 7,
        "visitors": 42,
        "_full_text": "'-09':5,10 '-29':6,11 '01':14 '03':7,12 '1467168112099':2,3 '2016':4,9 '30':13 '30h':8 '486':1",
        "passerby": 486,
        "site_id": "1467168112099",
        "_id": 418592,
        "key": "1467168112099 2016-09-29 03:30h",
        "timestamp": "2016-09-29T03:30:01"
      },
      {
        "connected": 7,
        "visitors": 42,
        "_full_text": "'-09':2,9 '-29':3,10 '02':6 '03':4,11 '1467168112099':7,13 '2016':1,8 '31':5 '31h':12 '7':14",
        "passerby": null,
        "site_id": "1467168112099",
        "_id": 418593,
        "key": "1467168112099 2016-09-29 03:31h",
        "timestamp": "2016-09-29T03:31:02"
      },
      {
        "connected": 7,
        "visitors": 42,
        "_full_text": "'-09':4,10 '-29':5,11 '01':14 '03':6,12 '1467168112099':1,2 '2016':3,9 '32':13 '32h':7 '42':8",
        "passerby": 502,
        "site_id": "1467168112099",
        "_id": 418595,
        "key": "1467168112099 2016-09-29 03:32h",
        "timestamp": "2016-09-29T03:32:01"
      },
      {
        "connected": 7,
        "visitors": 43,
        "_full_text": "'-09':3,10 '-29':4,11 '01':14 '03':5,12 '1467168112099':1,8 '2016':2,9 '33':13 '33h':6 '510':7",
        "passerby": 510,
        "site_id": "1467168112099",
        "_id": 418597,
        "key": "1467168112099 2016-09-29 03:33h",
        "timestamp": "2016-09-29T03:33:01"
      },
      {
        "connected": null,
        "visitors": 43,
        "_full_text": "'-09':3,9 '-29':4,10 '02':13 '03':5,11 '1467168112099':1,7 '2016':2,8 '34':12 '34h':6 '43':14",
        "passerby": 517,
        "site_id": "1467168112099",
        "_id": 418600,
        "key": "1467168112099 2016-09-29 03:34h",
        "timestamp": "2016-09-29T03:34:02"
      },
      {
        "connected": 7,
        "visitors": 44,
        "_full_text": "'-09':3,10 '-29':4,11 '01':7 '03':5,12 '1467168112099':1,8 '2016':2,9 '35':6 '35h':13 '44':14",
        "passerby": 522,
        "site_id": "1467168112099",
        "_id": 418602,
        "key": "1467168112099 2016-09-29 03:35h",
        "timestamp": "2016-09-29T03:35:01"
      },
      {
        "connected": 7,
        "visitors": 44,
        "_full_text": "'-09':3,11 '-29':4,12 '01':7 '03':5,13 '1467168112099':1,9 '2016':2,10 '36':6 '36h':14 '7':8",
        "passerby": 528,
        "site_id": "1467168112099",
        "_id": 418605,
        "key": "1467168112099 2016-09-29 03:36h",
        "timestamp": "2016-09-29T03:36:01"
      },
      {
        "connected": null,
        "visitors": 44,
        "_full_text": "'-09':2,11 '-29':3,12 '01':6 '03':4,13 '1467168112099':8,9 '2016':1,10 '37':5 '37h':14 '533':7",
        "passerby": 533,
        "site_id": "1467168112099",
        "_id": 418607,
        "key": "1467168112099 2016-09-29 03:37h",
        "timestamp": "2016-09-29T03:37:01"
      },
      {
        "connected": 7,
        "visitors": 45,
        "_full_text": "'-09':4,10 '-29':5,11 '01':14 '03':6,12 '1467168112099':1,2 '2016':3,9 '38':13 '38h':7 '7':8",
        "passerby": 535,
        "site_id": "1467168112099",
        "_id": 418610,
        "key": "1467168112099 2016-09-29 03:38h",
        "timestamp": "2016-09-29T03:38:01"
      },
      {
        "connected": 7,
        "visitors": 45,
        "_full_text": "'-09':2,9 '-29':3,10 '02':6 '03':4,11 '1467168112099':7,14 '2016':1,8 '39':5 '39h':12 '541':13",
        "passerby": 541,
        "site_id": "1467168112099",
        "_id": 418611,
        "key": "1467168112099 2016-09-29 03:39h",
        "timestamp": "2016-09-29T03:39:02"
      },
      {
        "connected": 7,
        "visitors": null,
        "_full_text": "'-09':2,9 '-29':3,10 '01':6 '03':4,11 '1467168112099':7,14 '2016':1,8 '40':5 '40h':12 '546':13",
        "passerby": 546,
        "site_id": "1467168112099",
        "_id": 418613,
        "key": "1467168112099 2016-09-29 03:40h",
        "timestamp": "2016-09-29T03:40:01"
      },
      {
        "connected": 7,
        "visitors": 45,
        "_full_text": "'-09':5,10 '-29':6,11 '01':14 '03':7,12 '1467168112099':1,3 '2016':4,9 '41':13 '41h':8 '45':2",
        "passerby": 558,
        "site_id": "1467168112099",
        "_id": 418616,
        "key": "1467168112099 2016-09-29 03:41h",
        "timestamp": "2016-09-29T03:41:01"
      },
      {
        "connected": 7,
        "visitors": 45,
        "_full_text": "'-09':3,9 '-29':4,10 '01':13 '03':5,11 '1467168112099':1,7 '2016':2,8 '42':12 '42h':6 '7':14",
        "passerby": 567,
        "site_id": "1467168112099",
        "_id": 418619,
        "key": "1467168112099 2016-09-29 03:42h",
        "timestamp": "2016-09-29T03:42:01"
      },
      {
        "connected": 7,
        "visitors": 45,
        "_full_text": "'-09':4,10 '-29':5,11 '01':14 '03':6,12 '1467168112099':1,2 '2016':3,9 '43':13 '43h':7 '45':8",
        "passerby": 575,
        "site_id": "1467168112099",
        "_id": 418621,
        "key": "1467168112099 2016-09-29 03:43h",
        "timestamp": "2016-09-29T03:43:01"
      },
      {
        "connected": 7,
        "visitors": 45,
        "_full_text": "'-09':4,11 '-29':5,12 '02':8 '03':6,13 '1467168112099':2,9 '2016':3,10 '44':7 '44h':14 '579':1",
        "passerby": 579,
        "site_id": "1467168112099",
        "_id": 418622,
        "key": "1467168112099 2016-09-29 03:44h",
        "timestamp": "2016-09-29T03:44:02"
      },
      {
        "connected": 7,
        "visitors": 46,
        "_full_text": "'-09':4,10 '-29':5,11 '01':14 '03':6,12 '1467168112099':2,8 '2016':3,9 '45':13 '45h':7 '46':1",
        "passerby": 587,
        "site_id": "1467168112099",
        "_id": 418625,
        "key": "1467168112099 2016-09-29 03:45h",
        "timestamp": "2016-09-29T03:45:01"
      },
      {
        "connected": 7,
        "visitors": 46,
        "_full_text": "'-09':2,11 '-29':3,12 '01':6 '03':4,13 '1467168112099':8,9 '2016':1,10 '46':5,7 '46h':14",
        "passerby": 594,
        "site_id": "1467168112099",
        "_id": 418626,
        "key": "1467168112099 2016-09-29 03:46h",
        "timestamp": "2016-09-29T03:46:01"
      },
      {
        "connected": 7,
        "visitors": 46,
        "_full_text": "'-09':3,11 '-29':4,12 '01':7 '03':5,13 '1467168112099':1,9 '2016':2,10 '47':6 '47h':14 '7':8",
        "passerby": 597,
        "site_id": "1467168112099",
        "_id": 418628,
        "key": "1467168112099 2016-09-29 03:47h",
        "timestamp": "2016-09-29T03:47:01"
      },
      {
        "connected": 7,
        "visitors": 46,
        "_full_text": "'-09':2,9 '-29':3,10 '01':6 '03':4,11 '1467168112099':7,13 '2016':1,8 '48':5 '48h':12 '7':14",
        "passerby": 605,
        "site_id": "1467168112099",
        "_id": 418631,
        "key": "1467168112099 2016-09-29 03:48h",
        "timestamp": "2016-09-29T03:48:01"
      },
      {
        "connected": 7,
        "visitors": 46,
        "_full_text": "'-09':4,9 '-29':5,10 '02':13 '03':6,11 '1467168112099':1,2 '2016':3,8 '49':12 '49h':7 '7':14",
        "passerby": 617,
        "site_id": "1467168112099",
        "_id": 418633,
        "key": "1467168112099 2016-09-29 03:49h",
        "timestamp": "2016-09-29T03:49:02"
      },
      {
        "connected": 0,
        "visitors": 8,
        "_full_text": "'-09':4,9 '-29':5,10 '01':13 '03':6,11 '1467168112099':1,2 '2016':3,8 '50':12 '50h':7",
        "passerby": 42,
        "site_id": "1467168112099",
        "_id": 418634,
        "key": "1467168112099 2016-09-29 03:50h",
        "timestamp": "2016-09-29T03:50:01"
      },
      {
        "connected": 0,
        "visitors": 15,
        "_full_text": "'-09':3,8 '-29':4,9 '01':12 '03':5,10 '1467168112099':1,13 '15':14 '2016':2,7 '51':11 '51h':6",
        "passerby": 98,
        "site_id": "1467168112099",
        "_id": 418637,
        "key": "1467168112099 2016-09-29 03:51h",
        "timestamp": "2016-09-29T03:51:01"
      },
      {
        "connected": 0,
        "visitors": 15,
        "_full_text": "'-09':2,11 '-29':3,12 '01':6 '03':4,13 '1467168112099':7,9 '15':8 '2016':1,10 '52':5 '52h':14",
        "passerby": 137,
        "site_id": "1467168112099",
        "_id": 418640,
        "key": "1467168112099 2016-09-29 03:52h",
        "timestamp": "2016-09-29T03:52:01"
      },
      {
        "connected": null,
        "visitors": 19,
        "_full_text": "'-09':4,10 '-29':5,11 '01':14 '03':6,12 '1467168112099':2,8 '19':1 '2016':3,9 '53':13 '53h':7",
        "passerby": 162,
        "site_id": "1467168112099",
        "_id": 418642,
        "key": "1467168112099 2016-09-29 03:53h",
        "timestamp": "2016-09-29T03:53:01"
      },
      {
        "connected": 0,
        "visitors": 20,
        "_full_text": "'-09':3,10 '-29':4,11 '01':7 '03':5,12 '1467168112099':1,8 '2016':2,9 '54':6 '54h':13",
        "passerby": 183,
        "site_id": "1467168112099",
        "_id": 418644,
        "key": "1467168112099 2016-09-29 03:54h",
        "timestamp": "2016-09-29T03:54:01"
      },
      {
        "connected": 0,
        "visitors": 22,
        "_full_text": "'-09':4,10 '-29':5,11 '02':14 '03':6,12 '1467168112099':1,2 '198':8 '2016':3,9 '55':13 '55h':7",
        "passerby": 198,
        "site_id": "1467168112099",
        "_id": 418647,
        "key": "1467168112099 2016-09-29 03:55h",
        "timestamp": "2016-09-29T03:55:02"
      },
      {
        "connected": 0,
        "visitors": 22,
        "_full_text": "'-09':3,9 '-29':4,10 '01':13 '03':5,11 '1467168112099':1,7 '2016':2,8 '22':14 '56':12 '56h':6",
        "passerby": 216,
        "site_id": "1467168112099",
        "_id": 418649,
        "key": "1467168112099 2016-09-29 03:56h",
        "timestamp": "2016-09-29T03:56:01"
      },
      {
        "connected": 0,
        "visitors": 22,
        "_full_text": "'-09':4,11 '-29':5,12 '01':8 '03':6,13 '1467168112099':2,9 '2016':3,10 '232':1 '57':7 '57h':14",
        "passerby": 232,
        "site_id": "1467168112099",
        "_id": 418651,
        "key": "1467168112099 2016-09-29 03:57h",
        "timestamp": "2016-09-29T03:57:01"
      },
      {
        "connected": 0,
        "visitors": 23,
        "_full_text": "'-09':4,9 '-29':5,10 '01':13 '03':6,11 '1467168112099':1,2 '2016':3,8 '247':14 '58':12 '58h':7",
        "passerby": 247,
        "site_id": "1467168112099",
        "_id": 418653,
        "key": "1467168112099 2016-09-29 03:58h",
        "timestamp": "2016-09-29T03:58:01"
      },
      {
        "connected": 0,
        "visitors": 23,
        "_full_text": "'-09':3,8 '-29':4,9 '01':12 '03':5,10 '1467168112099':1,13 '2016':2,7 '23':14 '59':11 '59h':6",
        "passerby": 255,
        "site_id": "1467168112099",
        "_id": 418655,
        "key": "1467168112099 2016-09-29 03:59h",
        "timestamp": "2016-09-29T03:59:01"
      }
    ],
    "fields": [
      {
        "id": "_id",
        "type": "int4"
      },
      {
        "id": "_full_text",
        "type": "tsvector"
      },
      {
        "id": "key",
        "type": "text"
      },
      {
        "id": "site_id",
        "type": "text"
      },
      {
        "id": "timestamp",
        "type": "timestamp"
      },
      {
        "id": "visitors",
        "type": "int4"
      },
      {
        "id": "connected",
        "type": "int4"
      },
      {
        "id": "passerby",
        "type": "int4"
      }
    ],
    "sql": "SELECT * from \"62e2e9ff-0c99-47cf-bc37-6b3a0617095b\" WHERE timestamp >= '2016-09-29 00:00:00'  AND timestamp < '2016-09-29 04:00:00' AND site_id = '1467168112099'"
  },
  "help": "http://10.90.129.12/api/3/action/help_show?name=datastore_search_sql",
  "success": true
}